Workbook
Name AnnualRentGrowth: [1]Input!$L$54:$P$54
Name AnnualRentGrowth: [1]Input!$L$54:$P$54
Name AnnualRentGrowth: [1]Input!$L$54:$P$54
Name AnnualRentGrowth: [1]Input!$L$54:$P$54
Name AnnualRentGrowth: [1]Input!$L$54:$P$54
Name AnnualRentGrowth: [1]Input!$L$54:$P$54
Name AnnualRentGrowth: [1]Input!$L$54:$P$54
Name AnnualRentGrowth: [1]Input!$L$54:$P$54
Name AnnualRentGrowth: [1]Input!$L$54:$P$54
Name AnnualRentGrowth: [1]Input!$L$54:$P$54
Name AssedValuePerc: [1]Input!$L$96
Name AssedValuePerc: [1]Input!$L$96
Name AssedValuePerc: [1]Input!$L$96
Name AssedValuePerc: [1]Input!$L$96
Name AssedValuePerc: [1]Input!$L$96
Name AssedValuePerc: [1]Input!$L$96
Name AssedValuePerc: [1]Input!$L$96
Name AssedValuePerc: [1]Input!$L$96
Name AssedValuePerc: [1]Input!$L$96
Name AssedValuePerc: [1]Input!$L$96
Name BadDebt: [1]Input!$L$49:$P$49
Name BadDebt: [1]Input!$L$49:$P$49
Name BadDebt: [1]Input!$L$49:$P$49
Name BadDebt: [1]Input!$L$49:$P$49
Name BadDebt: [1]Input!$L$49:$P$49
Name BadDebt: [1]Input!$L$49:$P$49
Name BadDebt: [1]Input!$L$49:$P$49
Name BadDebt: [1]Input!$L$49:$P$49
Name BadDebt: [1]Input!$L$49:$P$49
Name BadDebt: [1]Input!$L$49:$P$49
Name CashRateMezz: [1]Input!$E$43
Name CashRateMezz: [1]Input!$E$43
Name CashRateMezz: [1]Input!$E$43
Name CashRateMezz: [1]Input!$E$43
Name CashRateMezz: [1]Input!$E$43
Name CashRateMezz: [1]Input!$E$43
Name CashRateMezz: [1]Input!$E$43
Name CashRateMezz: [1]Input!$E$43
Name CashRateMezz: [1]Input!$E$43
Name CashRateMezz: [1]Input!$E$43
Name CircuitBreaker: [1]Input!$B$12
Name CircuitBreaker: [1]Input!$B$12
Name CircuitBreaker: [1]Input!$B$12
Name CircuitBreaker: [1]Input!$B$12
Name CircuitBreaker: [1]Input!$B$12
Name CircuitBreaker: [1]Input!$B$12
Name CircuitBreaker: [1]Input!$B$12
Name CircuitBreaker: [1]Input!$B$12
Name CircuitBreaker: [1]Input!$B$12
Name CircuitBreaker: [1]Input!$B$12
Name Concessions: [1]Input!$L$50:$P$50
Name Concessions: [1]Input!$L$50:$P$50
Name Concessions: [1]Input!$L$50:$P$50
Name Concessions: [1]Input!$L$50:$P$50
Name Concessions: [1]Input!$L$50:$P$50
Name Concessions: [1]Input!$L$50:$P$50
Name Concessions: [1]Input!$L$50:$P$50
Name Concessions: [1]Input!$L$50:$P$50
Name Concessions: [1]Input!$L$50:$P$50
Name Concessions: [1]Input!$L$50:$P$50

Sheet Portfolio Level Dashboards-->

Sheet Senior Maturity Tracker
B2: Fund | C2: Fund 1
B5: Deal Name | C5: Loan Amount | D5: Initial Maturity | E5: Extensions | F5: Extended Maturity (If Passing) | G5: DSCR Test | H5: Forecasted DSCR | I5: DY Test | J5: Forecasted DY | K5: Estimated Refinance Proceeds | L5: Implied Shortfall/ Paydown | M5: 2025 | Q5: 2026 | U5: 2027 | Y5: 2028
M6: 45747 | N6: =EOMONTH(M6,3) -> 45838 | O6: =EOMONTH(N6,3) -> 45930 | P6: =EOMONTH(O6,3) -> 46022 | Q6: =EOMONTH(P6,3) -> 46112 | R6: =EOMONTH(Q6,3) -> 46203 | S6: =EOMONTH(R6,3) -> 46295 | T6: =EOMONTH(S6,3) -> 46387 | U6: =EOMONTH(T6,3) -> 46477 | ... AB6: =EOMONTH(AA6,3) -> 47118
B7: Riverwalk Flats | C7: 50000000 | D7: 46228 | F7: 46228 | G7: 1.2 | H7: 1 | I7: 0.08 | J7: 0.08 | K7: =C7-500000 -> 49500000 | L7: =C7-K7 -> 500000 | M7: =IF(AND($F7>=M$6-90,$F7<M$6),$L7,0) -> 0 | N7: =IF(AND($F7>=N$6-90,$F7<N$6),$L7,0) -> 0 | O7: =IF(AND($F7>=O$6-90,$F7<O$6),$L7,0) -> 0 | P7: =IF(AND($F7>=P$6-90,$F7<P$6),$L7,0) -> 0 | Q7: =IF(AND($F7>=Q$6-90,$F7<Q$6),$L7,0) -> 0 | R7: =IF(AND($F7>=R$6-90,$F7<R$6),$L7,0) -> 0 | S7: =IF(AND($F7>=S$6-90,$F7<S$6),$L7,0) -> 500000 | T7: =IF(AND($F7>=T$6-90,$F7<T$6),$L7,0) -> 0 | ... AB7: =IF(AND($F7>=AB$6-90,$F7<AB$6),$L7,0) -> 0
B8: Harborlight Apartments | C8: 50000000 | D8: 46687 | F8: 46687 | G8: 1.2 | H8: 1 | I8: 0.08 | J8: 0.08 | K8: =C8-500000 -> 49500000 | L8: =C8-K8 -> 500000 | M8: =IF(AND($F8>=M$6-90,$F8<M$6),$L8,0) -> 0 | N8: =IF(AND($F8>=N$6-90,$F8<N$6),$L8,0) -> 0 | O8: =IF(AND($F8>=O$6-90,$F8<O$6),$L8,0) -> 0 | P8: =IF(AND($F8>=P$6-90,$F8<P$6),$L8,0) -> 0 | Q8: =IF(AND($F8>=Q$6-90,$F8<Q$6),$L8,0) -> 0 | R8: =IF(AND($F8>=R$6-90,$F8<R$6),$L8,0) -> 0 | S8: =IF(AND($F8>=S$6-90,$F8<S$6),$L8,0) -> 0 | T8: =IF(AND($F8>=T$6-90,$F8<T$6),$L8,0) -> 0 | ... AB8: =IF(AND($F8>=AB$6-90,$F8<AB$6),$L8,0) -> 0
B9: The Parkhaven | C9: 50000000 | D9: 46713 | F9: 46713 | G9: 1.2 | H9: 1 | I9: 0.08 | J9: 0.08 | K9: =C9-500000 -> 49500000 | L9: =C9-K9 -> 500000 | M9: =IF(AND($F9>=M$6-90,$F9<M$6),$L9,0) -> 0 | N9: =IF(AND($F9>=N$6-90,$F9<N$6),$L9,0) -> 0 | O9: =IF(AND($F9>=O$6-90,$F9<O$6),$L9,0) -> 0 | P9: =IF(AND($F9>=P$6-90,$F9<P$6),$L9,0) -> 0 | Q9: =IF(AND($F9>=Q$6-90,$F9<Q$6),$L9,0) -> 0 | R9: =IF(AND($F9>=R$6-90,$F9<R$6),$L9,0) -> 0 | S9: =IF(AND($F9>=S$6-90,$F9<S$6),$L9,0) -> 0 | T9: =IF(AND($F9>=T$6-90,$F9<T$6),$L9,0) -> 0 | ... AB9: =IF(AND($F9>=AB$6-90,$F9<AB$6),$L9,0) -> 0
B10: Golden Oak Terrace | C10: 50000000 | D10: 46768 | F10: 46768 | G10: 1.2 | H10: 1 | I10: 0.08 | J10: 0.08 | K10: =C10-500000 -> 49500000 | L10: =C10-K10 -> 500000 | M10: =IF(AND($F10>=M$6-90,$F10<M$6),$L10,0) -> 0 | N10: =IF(AND($F10>=N$6-90,$F10<N$6),$L10,0) -> 0 | O10: =IF(AND($F10>=O$6-90,$F10<O$6),$L10,0) -> 0 | P10: =IF(AND($F10>=P$6-90,$F10<P$6),$L10,0) -> 0 | Q10: =IF(AND($F10>=Q$6-90,$F10<Q$6),$L10,0) -> 0 | R10: =IF(AND($F10>=R$6-90,$F10<R$6),$L10,0) -> 0 | S10: =IF(AND($F10>=S$6-90,$F10<S$6),$L10,0) -> 0 | T10: =IF(AND($F10>=T$6-90,$F10<T$6),$L10,0) -> 0 | ... AB10: =IF(AND($F10>=AB$6-90,$F10<AB$6),$L10,0) -> 0
B11: Aurora Heights | C11: 50000000 | D11: 46891 | F11: 46891 | G11: 1.2 | H11: 1 | I11: 0.08 | J11: 0.08 | K11: =C11-500000 -> 49500000 | L11: =C11-K11 -> 500000 | M11: =IF(AND($F11>=M$6-90,$F11<M$6),$L11,0) -> 0 | N11: =IF(AND($F11>=N$6-90,$F11<N$6),$L11,0) -> 0 | O11: =IF(AND($F11>=O$6-90,$F11<O$6),$L11,0) -> 0 | P11: =IF(AND($F11>=P$6-90,$F11<P$6),$L11,0) -> 0 | Q11: =IF(AND($F11>=Q$6-90,$F11<Q$6),$L11,0) -> 0 | R11: =IF(AND($F11>=R$6-90,$F11<R$6),$L11,0) -> 0 | S11: =IF(AND($F11>=S$6-90,$F11<S$6),$L11,0) -> 0 | T11: =IF(AND($F11>=T$6-90,$F11<T$6),$L11,0) -> 0 | ... AB11: =IF(AND($F11>=AB$6-90,$F11<AB$6),$L11,0) -> 0
B12: The Summit at Westview | C12: 50000000 | D12: 46929 | F12: 46929 | G12: 1.2 | H12: 1.25 | I12: 0.08 | J12: 0.08 | K12: =C12-500000 -> 49500000 | L12: =C12-K12 -> 500000 | M12: =IF(AND($F12>=M$6-90,$F12<M$6),$L12,0) -> 0 | N12: =IF(AND($F12>=N$6-90,$F12<N$6),$L12,0) -> 0 | O12: =IF(AND($F12>=O$6-90,$F12<O$6),$L12,0) -> 0 | P12: =IF(AND($F12>=P$6-90,$F12<P$6),$L12,0) -> 0 | Q12: =IF(AND($F12>=Q$6-90,$F12<Q$6),$L12,0) -> 0 | R12: =IF(AND($F12>=R$6-90,$F12<R$6),$L12,0) -> 0 | S12: =IF(AND($F12>=S$6-90,$F12<S$6),$L12,0) -> 0 | T12: =IF(AND($F12>=T$6-90,$F12<T$6),$L12,0) -> 0 | ... AB12: =IF(AND($F12>=AB$6-90,$F12<AB$6),$L12,0) -> 0
B13: Lakeside Loft | C13: 40000000 | D13: 46964 | F13: 46964 | G13: 1.2 | H13: 1.7 | I13: 0.08 | J13: 0.08 | K13: =C13-500000 -> 39500000 | L13: =C13-K13 -> 500000 | M13: =IF(AND($F13>=M$6-90,$F13<M$6),$L13,0) -> 0 | N13: =IF(AND($F13>=N$6-90,$F13<N$6),$L13,0) -> 0 | O13: =IF(AND($F13>=O$6-90,$F13<O$6),$L13,0) -> 0 | P13: =IF(AND($F13>=P$6-90,$F13<P$6),$L13,0) -> 0 | Q13: =IF(AND($F13>=Q$6-90,$F13<Q$6),$L13,0) -> 0 | R13: =IF(AND($F13>=R$6-90,$F13<R$6),$L13,0) -> 0 | S13: =IF(AND($F13>=S$6-90,$F13<S$6),$L13,0) -> 0 | T13: =IF(AND($F13>=T$6-90,$F13<T$6),$L13,0) -> 0 | ... AB13: =IF(AND($F13>=AB$6-90,$F13<AB$6),$L13,0) -> 0
B14: Cedarstone Residences | C14: 50000000 | D14: 46969 | F14: 46969 | G14: 1.2 | H14: 1 | I14: 0.08 | J14: 0.08 | K14: =C14-500000 -> 49500000 | L14: =C14-K14 -> 500000 | M14: =IF(AND($F14>=M$6-90,$F14<M$6),$L14,0) -> 0 | N14: =IF(AND($F14>=N$6-90,$F14<N$6),$L14,0) -> 0 | O14: =IF(AND($F14>=O$6-90,$F14<O$6),$L14,0) -> 0 | P14: =IF(AND($F14>=P$6-90,$F14<P$6),$L14,0) -> 0 | Q14: =IF(AND($F14>=Q$6-90,$F14<Q$6),$L14,0) -> 0 | R14: =IF(AND($F14>=R$6-90,$F14<R$6),$L14,0) -> 0 | S14: =IF(AND($F14>=S$6-90,$F14<S$6),$L14,0) -> 0 | T14: =IF(AND($F14>=T$6-90,$F14<T$6),$L14,0) -> 0 | ... AB14: =IF(AND($F14>=AB$6-90,$F14<AB$6),$L14,0) -> 0
B15: The Skyline Enclave | C15: 50000000 | D15: 46977 | F15: 46977 | G15: 1.2 | H15: 1.1 | I15: 0.08 | J15: 0.08 | K15: =C15-500000 -> 49500000 | L15: =C15-K15 -> 500000 | M15: =IF(AND($F15>=M$6-90,$F15<M$6),$L15,0) -> 0 | N15: =IF(AND($F15>=N$6-90,$F15<N$6),$L15,0) -> 0 | O15: =IF(AND($F15>=O$6-90,$F15<O$6),$L15,0) -> 0 | P15: =IF(AND($F15>=P$6-90,$F15<P$6),$L15,0) -> 0 | Q15: =IF(AND($F15>=Q$6-90,$F15<Q$6),$L15,0) -> 0 | R15: =IF(AND($F15>=R$6-90,$F15<R$6),$L15,0) -> 0 | S15: =IF(AND($F15>=S$6-90,$F15<S$6),$L15,0) -> 0 | T15: =IF(AND($F15>=T$6-90,$F15<T$6),$L15,0) -> 0 | ... AB15: =IF(AND($F15>=AB$6-90,$F15<AB$6),$L15,0) -> 0
B16: The Belmont Edge | C16: 1000000 | D16: 47070 | F16: 47070 | G16: 1.2 | H16: 1.2 | I16: 0.08 | J16: 0.08 | K16: =C16-500000 -> 500000 | L16: =C16-K16 -> 500000 | M16: =IF(AND($F16>=M$6-90,$F16<M$6),$L16,0) -> 0 | N16: =IF(AND($F16>=N$6-90,$F16<N$6),$L16,0) -> 0 | O16: =IF(AND($F16>=O$6-90,$F16<O$6),$L16,0) -> 0 | P16: =IF(AND($F16>=P$6-90,$F16<P$6),$L16,0) -> 0 | Q16: =IF(AND($F16>=Q$6-90,$F16<Q$6),$L16,0) -> 0 | R16: =IF(AND($F16>=R$6-90,$F16<R$6),$L16,0) -> 0 | S16: =IF(AND($F16>=S$6-90,$F16<S$6),$L16,0) -> 0 | T16: =IF(AND($F16>=T$6-90,$F16<T$6),$L16,0) -> 0 | ... AB16: =IF(AND($F16>=AB$6-90,$F16<AB$6),$L16,0) -> 500000
B17: Total Quarterly Exposure | C17: =SUM(C7:C16) -> 441000000 | K17: =SUM(K7:K16) -> 436000000 | L17: =SUM(L7:L16) -> 5000000 | M17: =SUM(M7:M16) -> 0 | N17: =SUM(N7:N16) -> 0 | O17: =SUM(O7:O16) -> 0 | P17: =SUM(P7:P16) -> 0 | Q17: =SUM(Q7:Q16) -> 0 | R17: =SUM(R7:R16) -> 0 | ... AB17: =SUM(AB7:AB16) -> 500000
B18: Total Annual Exposure | P18: =SUM(M17:P17) -> 0 | T18: =SUM(Q17:T17) -> 500000 | X18: =SUM(U17:X17) -> 1000000 | AB18: =SUM(Y17:AB17) -> 3500000

Sheet PERPETUITY MIDDLEMAN INPUT TAB
B2: Model Type | C2: Acquistions
B3: Asset Management Model Start | E3: Senior Loan Terms | H3: Sources and Uses
F4: Asset Mangement | H4: Total Sources
B5: Actuals Through | C5: =C11 -> 45346 | E5: Loan to Cost % | F5: ='Sample Model Tab'!E17 -> 0.6 | H5: Senior Loan | J5: =J19*F5 -> 20872774
B6: Date AM Model Starts | C6: =EOMONTH(C5,1) -> 45382 | E6: Interest Type - Fixed/Floating | F6: ='Sample Model Tab'!E18 -> Floating-Rate | H6: Preferred Equity | J6: =IF(C93="no",0,J19*C94-J5) -> 0
B7: Month AM Model Starts | C7: =ROUNDUP((C5-C11)/30.5,0) -> 0 | E7: Curve | F7: SOFR | H7: Investor Equity | J7: =(J19-J6-J5)*I45 -> 13219424
E8: SOFR Spread | F8: ='Sample Model Tab'!E19 -> 0.03 | H8: Ace Development Equity | J8: =J19-J7-J6-J5 -> 695759.14
B9: Construction and Delivery Schedule | E9: SOFR Floor | F9: 0 | H9: Total Sources | J9: =SUM(J5:J8) -> 34787957
C10: Active Case | E10: SOFR Cap | F10: 1
B11: Transaction Closing Date | C11: ='Sample Model Tab'!B37 -> 45346 | E11: Interest Only Period | F11: 24 | H11: Total Uses
B12: Construction Start Date | C12: =C11 -> 45346 | E12: Amortization Schedule | F12: 30 | H12: Land
B13: Construction Start Month | C13: 1 | E13: Initial Term | F13: ='Sample Model Tab'!E21 -> 24 | H13: Land | J13: ='Sample Model Tab'!I22 -> 10000000
B14: Construction Period | C14: 24 | E14: Loan Maturity | F14: =EOMONTH(C11,F13) -> 46081 | H14: Hard Costs | J14: ='Sample Model Tab'!I24 -> 19350000
B15: Construction Completion | C15: =C13+C14 -> 25 | E15: Origination Fee | F15: ='Sample Model Tab'!E20 -> 0.01 | H15: Soft Costs | J15: ='Sample Model Tab'!I23+'Sample Model Tab'!I25+'Sample Model Tab'!I26 -> 4000347.1
B16: First Units Delivered (Opex Starts) | C16: ='Sample Model Tab'!B27 -> 14 | E16: Rate Stepdown DSCR | F16: 0 | H16: Financing Costs | J16: ='Sample Model Tab'!I29 -> 208727.74
B17: Absorption Start | C17: ='Sample Model Tab'!B27 -> 14 | E17: Rate Stepdown DY | F17: 0 | H17: Operating Reserve | J17: ='Sample Model Tab'!I30 -> 71548.645
B18: Last Units Delivered | C18: =C14 -> 24 | E18: Stepdown Rate | F18: 0 | H18: Senior Interest Reserve | J18: ='Sample Model Tab'!I27 -> 1157333.3
E19: Exit Month | F19: 0 | H19: Total Uses | J19: =SUM(J13:J18) -> 34787957
B20: Revenue and Other Income | E20: Exit Fee | F20: 0
C21: Active Case | H21: Market
B22: Vacancy | C22: ='Sample Model Tab'!P48 -> 0.03 | E22: Exit Assumptions | H22: Unit Type | I22: # of Units | J22: Avg. SF | K22: Rent | L22: PSF
B23: Loss to Lease | C23: 0 | H23: ='Sample Model Tab'!L17 -> 1BR/1BA | I23: ='Sample Model Tab'!K17 -> 50 | J23: ='Sample Model Tab'!M17 -> 600 | K23: ='Sample Model Tab'!N17 -> 1425 | L23: =K23/J23 -> 2.375
B24: Bad Debt | C24: ='Sample Model Tab'!L49 -> 0.01 | E24: Sale Date | F24: =HLOOKUP(F25,'Cash Flow - AM'!$F$3:$DV$5,3) -> 48273 | H24: ='Sample Model Tab'!L18 -> 2BR/1BA | I24: ='Sample Model Tab'!K18 -> 20 | J24: ='Sample Model Tab'!M18 -> 725 | K24: ='Sample Model Tab'!N18 -> 1600 | L24: =K24/J24 -> 2.2068966
B25: Model Units | C25: 0 | E25: Sale Month | F25: ='Sample Model Tab'!I45 -> 96 | H25: ='Sample Model Tab'!L19 -> 2BR/2BA | I25: ='Sample Model Tab'!K19 -> 65 | J25: ='Sample Model Tab'!M19 -> 875 | K25: ='Sample Model Tab'!N19 -> 1875 | L25: =K25/J25 -> 2.1428571
E26: NOI Type | F26: F12 | H26: ='Sample Model Tab'!L20 -> 3BR/2BA | I26: ='Sample Model Tab'!K20 -> 10 | J26: ='Sample Model Tab'!M20 -> 1025 | K26: ='Sample Model Tab'!N20 -> 2100 | L26: =K26/J26 -> 2.0487805
B27: Concessions - Lease Up (New) | C27: 1 | E27: Sale Costs % | F27: ='Sample Model Tab'!I43 -> 0.01
B28: Concessions - Lease Up (Renewal) | C28: 0 | E28: Exit Capitalization Rate (MF) | F28: ='Sample Model Tab'!I44 -> 0.06
B29: Concessions - Stabilized (New) | C29: 0 | E29: Exit Capitalization (Retail) | F29: 0.06 | H29: Total / Avg - Market | I29: =IFERROR(SUM(I23:I28),0) -> 145 | J29: =IFERROR(SUMPRODUCT(I23:I28,J23:J28)/I29,0) -> 769.82759 | K29: =SUMPRODUCT(I23:I26,K23:K26)/I29 -> 1697.4138 | L29: =K29/J29 -> 2.2049272
B30: Concessions - Stabilized (Renewal) | C30: 0
E31: Tax Reassessment at Exit
H32: Inflation Indexes
B33: Absorption Start Month | C33: =C16 -> 14 | E33: Reassess at Sale | F33: Yes | I33: 1 | J33: =I33+1 -> 2 | K33: =J33+1 -> 3 | L33: =K33+1 -> 4 | M33: =L33+1 -> 5 | N33: =M33+1 -> 6 | O33: =N33+1 -> 7 | P33: =O33+1 -> 8
B34: Absorption Start Date | C34: =EOMONTH(C11,C16) -> 45777 | E34: Property Tax Millage Rate | F34: ='Sample Model Tab'!L94 -> 0.012 | I34: =I33 -> 1 | J34: =J33 -> 2 | K34: =K33 -> 3 | L34: =L33 -> 4 | M34: =M33 -> 5 | N34: =N33 -> 6 | O34: =O33 -> 7 | P34: =P33 -> 8
E35: County Assessment % | F35: 1 | H35: Market Rent Growth | I35: ='Sample Model Tab'!L54 -> 0.022 | J35: ='Sample Model Tab'!M54 -> 0.023 | K35: ='Sample Model Tab'!N54 -> 0.024 | L35: ='Sample Model Tab'!O54 -> 0.025 | M35: ='Sample Model Tab'!P54 -> 0.026 | N35: ='Sample Model Tab'!Q54 -> 0 | O35: ='Sample Model Tab'!R54 -> 0 | P35: ='Sample Model Tab'!S54 -> 0
B36: Leased Units Per Month | C36: 25 | E36: Market Value as % of Sale Price | F36: ='Sample Model Tab'!L96 -> 1 | H36: Affordable Rent Growth | I36: =I35 -> 0.022 | J36: =J35 -> 0.023 | K36: =K35 -> 0.024 | L36: =L35 -> 0.025 | M36: =M35 -> 0.026 | N36: =N35 -> 0 | O36: =O35 -> 0 | P36: =P35 -> 0
B37: Renewal Probability | C37: 0.5 | E37: Tax Adjusted Exit Cap Rate (MF) | F37: =F28+(F34*F35*F36) -> 0.072 | H37: Other Income Growth | I37: ='Sample Model Tab'!L55 -> 0.03 | J37: ='Sample Model Tab'!M55 -> 0.03 | K37: ='Sample Model Tab'!N55 -> 0.03 | L37: ='Sample Model Tab'!O55 -> 0.03 | M37: ='Sample Model Tab'!P55 -> 0.03 | N37: ='Sample Model Tab'!Q55 -> 0 | O37: ='Sample Model Tab'!R55 -> 0 | P37: ='Sample Model Tab'!S55 -> 0
B38: Lease Term | C38: 12 | H38: Controllables Growth | I38: ='Sample Model Tab'!$L$75 -> 0.02 | J38: ='Sample Model Tab'!$L$75 -> 0.02 | K38: ='Sample Model Tab'!$L$75 -> 0.02 | L38: ='Sample Model Tab'!$L$75 -> 0.02 | M38: ='Sample Model Tab'!$L$75 -> 0.02 | N38: ='Sample Model Tab'!$L$75 -> 0.02 | O38: ='Sample Model Tab'!$L$75 -> 0.02 | P38: ='Sample Model Tab'!$L$75 -> 0.02
H39: Taxes Growth | I39: ='Sample Model Tab'!$L$75 -> 0.02 | J39: ='Sample Model Tab'!$L$75 -> 0.02 | K39: ='Sample Model Tab'!$L$75 -> 0.02 | L39: ='Sample Model Tab'!$L$75 -> 0.02 | M39: ='Sample Model Tab'!$L$75 -> 0.02 | N39: ='Sample Model Tab'!$L$75 -> 0.02 | O39: ='Sample Model Tab'!$L$75 -> 0.02 | P39: ='Sample Model Tab'!$L$75 -> 0.02
H40: Insurance Growth | I40: ='Sample Model Tab'!$L$75 -> 0.02 | J40: ='Sample Model Tab'!$L$75 -> 0.02 | K40: ='Sample Model Tab'!$L$75 -> 0.02 | L40: ='Sample Model Tab'!$L$75 -> 0.02 | M40: ='Sample Model Tab'!$L$75 -> 0.02 | N40: ='Sample Model Tab'!$L$75 -> 0.02 | O40: ='Sample Model Tab'!$L$75 -> 0.02 | P40: ='Sample Model Tab'!$L$75 -> 0.02
B41: Operating Expenses
C42: Active Case | H42: Market
B44: Fixed Cost Start Month | C44: 30 | K44: Promote | L44: Hurdle | M44: Multiple | N44: $ Amount
H45: Tier 1 - Return of Capital | I45: ='Sample Model Tab'!I62 -> 0.95 | J45: ='Sample Model Tab'!H62 -> 0.05 | K45: 0 | L45: ='Sample Model Tab'!H56 -> 0.08 | M45: 0
C46: Per Unit / Year | H46: Tier 2 | I46: ='Sample Model Tab'!I63 -> 0.8 | J46: =J45 -> 0.05 | K46: =1-I46-J46 -> 0.15 | L46: ='Sample Model Tab'!H57 -> 0.1 | M46: 1
B47: Controllable Expenses | H47: Tier 3 | I47: ='Sample Model Tab'!I64 -> 0.7 | J47: =J46 -> 0.05 | K47: =1-I47-J47 -> 0.25 | L47: ='Sample Model Tab'!H58 -> 0.15 | M47: 1
B48: Payroll | C48: ='Sample Model Tab'!L60 -> 1500 | H48: Tier 4 | I48: ='Sample Model Tab'!I65 -> 0.5 | J48: =J47 -> 0.05 | K48: =1-I48-J48 -> 0.45 | L48: =L47 -> 0.15 | M48: 1
B49: Utilities | C49: ='Sample Model Tab'!L66+'Sample Model Tab'!L67 -> 100 | H49: Tier 5 | I49: =I48 -> 0.5 | J49: =J48 -> 0.05 | K49: =1-I49-J49 -> 0.45
B50: Turnover | C50: ='Sample Model Tab'!L64 -> 300
B51: Contract Services | C51: ='Sample Model Tab'!L65 -> 150
B52: Repairs and Maintenance | C52: ='Sample Model Tab'!L63 -> 500
B53: Leasing and Marketing | C53: ='Sample Model Tab'!L62 -> 250
B54: General and Administrative | C54: ='Sample Model Tab'!L61 -> 300
B55: Other Expenses | C55: 0
B56: Total Controllable Expenses | C56: =SUM(C48:C55) -> 3100
B58: Management Fee | C58: ='Sample Model Tab'!L77 -> 0.03
B59: Insurance | C59: ='Sample Model Tab'!L68 -> 400
B60: Property Taxes | C60: 5250
B61: Other Taxes / Fees | C61: 0
B62: Total Non - Controllable Expenses | C62: =SUM(C58:C61) -> 5650.03
B64: Replacement Reserves | C64: 0
B65: Total Operating Expenses | C65: =C62+C56 -> 8750.03
B67: Other Income
C68: Active Case
C69: # of Units | D69: $ Per Month
B70: Amenity / Trash / Pest
B71: Bulk Wifi
B72: Application Fees / Admin / Other
B73: RUBS
B74: Premiums
B75: Pet Rent - One-Time Fee | C75: =$I$29 -> 145 | D75: ='Sample Model Tab'!M36 -> 5
B76: Pet Rent - Monthly | C76: =$I$29 -> 145 | D76: ='Sample Model Tab'!M35 -> 15
B77: Reserved Parking | C77: =$I$29 -> 145 | D77: ='Sample Model Tab'!M37 -> 50
B78: Garage - First Car
B79: Garage - Second Car
B80: Cable, Phone, Etc
B81: Storage
B82: Other | C82: =$I$29 -> 145 | D82: ='Sample Model Tab'!M33 -> 10
B83: Other | C83: =$I$29 -> 145 | D83: ='Sample Model Tab'!M34 -> 3
B84: Other
B85: Other
C86: =SUM(C70:C85) -> 725 | D86: =SUMPRODUCT(C70:C85,D70:D85)/C86 -> 16.6
B91: Prefered Equity Terms
C92: Asset Mangement
B93: Preferred Equity? | C93: No
B94: Loan to Cost % | C94: ='AIRR Input Tab'!H42 -> 0.9
B95: Initial Term | C95: ='AIRR Input Tab'!H43 -> 48
B96: Interest Type - Fixed/Floating | C96: ='AIRR Input Tab'!H44 -> Fixed
B97: SOFR Spread | C97: ='AIRR Input Tab'!H45 -> 0
B98: SOFR Floor | C98: ='AIRR Input Tab'!H46 -> 0
B99: Total Interest Rate | C99: ='AIRR Input Tab'!H47 -> 0.15
B100: Minimum Multiple | C100: ='AIRR Input Tab'!H48 -> 1.5
B101: Current Pay % | C101: ='AIRR Input Tab'!H49 -> 0.05
B102: Accrual % | C102: ='AIRR Input Tab'!H50 -> 0.1

Sheet Model Sample Mapping-->

Sheet Summary
A1: Executive Summary
A3: Levered IRR of 10.2% | Equity Multiple: 1.89x| Net Profit: $12,501,952
G6: Property Details | K6: Return Metrics
G7: Number of Units | I7: 145 | K7: Unlevered IRR | M7: 0.082008585
G8: Number of Buildings | I8: 10 | K8: Unlevered Equity Multiple | M8: 1.6757444
G9: Net Rentals SF | I9: 111625 | K9: Levered IRR | M9: 0.10224795
G10: Average Unit Size SF | I10: 769.82759 | K10: Levered Equity Multiple | M10: 1.8851549
G11: Net Acres | I11: 9.5 | K11: Net Profit (Levered CF) | M11: 12501952
G12: Units per Acre | I12: 15.263158 | K12: Average Cash-on-Cash Return | M12: 0.046482859
G13: Street Address | I13: 555 Main Street | K13: LP IRR | M13: 0.098957175
G14: City/State/ZIP | I14: Santa Barbara, CA | K14: GP IRR | M14: 0.15388624
K15: LP Equity Multiple | M15: 1.8453206
G16: Sources of Funds (Construction Financing) | K16: GP Equity Multiple | M16: 2.6420068
G17: Equity | H17: 13915183 | I17: 0.4
G18: Mezzanine Loan | H18: 0 | I18: 0 | K18: Optimal Sale Year | M18: IRR
G19: Construction Loan | H19: 20872774 | I19: 0.6 | K19: Unlevered Acquisition | L19: 3 | M19: 0.12260577
G20: Total | H20: 34787957 | I20: 1 | K20: Levered Acquisition | L20: 3 | M20: 0.16055372
G22: Uses of Funds (Construction Period) | K22: Equity Structure
G23: Land Acquisition Costs | H23: 10000000 | I23: 0.2874558 | K23: GP Equity | M23: 0.05
G24: Closing Costs | H24: 100000 | I24: 0.002874558 | K24: LP Equity | M24: 0.95
G25: Hard Costs | H25: 19350000 | I25: 0.55622698
G26: Soft Costs | H26: 1786679.2 | I26: 0.051359129 | K26: LP CF's Distribuitions | L26: CFs | M26: % CF
G27: Contingency | H27: 2113667.9 | I27: 0.06075861 | K27: Prefered Return Hurdle | L27: 21909578 | M27: 0.95
G28: Capitalized Construction Interest | H28: 1157333.3 | I28: 0.033268218 | K28: Hurdle #2 | L28: 2850612.3 | M28: 0.8
G29: Mezzanine capitalized Interest | H29: 0 | I29: 0 | K29: Hurdle #3 | L29: 0
G30: Construction Loan Fees | H30: 208727.74 | I30: 0.006 | K30: Hurdle #4 | L30: 0
G31: Operating Expense Shortfalls | H31: 71548.645 | I31: 0.0020567073 | K31: Total LP CFs | L31: 24760190 | M31: 0.929926
G32: Total | H32: 34787957 | I32: 1
K33: GP CF Distributions | L33: CFs | M33: % CF
G34: Sales Details | K34: Prefered Return Hurdle | L34: 1153135.7 | M34: 0.05
G35: Sales Prices | I35: 41195530 | K35: Hurdle #2 | L35: 712653.08 | M35: 0.2
G36: Sales Price/Unit | I36: 284107.1 | K36: Hurdle #3 | L36: 0
G37: Cost of Sale | I37: 411955.3 | K37: Hurdle #4 | L37: 0
G38: Closing Costs (as % Sale Price) | I38: 0.01 | K38: Total GP CFs | L38: 1865788.7 | M38: 0.070073997
G39: Exist Cap Rate | I39: 0.06
G40: Hold Period | I40: 96
A50: Revenue vs NOI (Millions USD) | G50: Levered IRR per Holding Period (from Stabilization to 10 Years Holding)
A68: Cash Flows (Millions USD) | G68: Levered Cash Flow (Millions USD)
A86: Total Project Cost By Month (millions USD)
A105: Total Project Cost By Month (millions USD)

Sheet Sample Model Tab
A1: Assumptions
A2: 555 Main Street, Santa Barbara, CA
A3: Levered IRR of 14.0% | Equity Multiple: 2.40x| Net Profit: $19,901,814
L6: Carry Costs | N6: Pasted Values | O6: Formula (to be used by a macro)
L7: Capitalized Construction Interest | N7: 1157333.3 | O7: 1157333.3
L8: Mezzanine Loan | N8: 0 | O8: 0
L9: Mezzanine Loan Fees | N9: 0 | O9: 0
A10: Contents | L10: Construction Loan Fees | N10: 208727.74 | O10: 208727.74
A11: Circuit Breaker | L11: Operating Shortfall | N11: 71548.645 | O11: 71548.645
A12: On/Off | B12: Off
Q13: The model is configured to perform automatic calculations, with the exception of the data table.
K14: Revenue Section | Q14: To update the data table, the user must either save the file or manually press F9 for the changes to take effect.
A15: Property Details | D15: Construction Financing Amount | G15: Sources of Funds (Construction Financing) | K15: Stabilized Rents | Q15: Effect of Holding Period & Exit Cap on Levered IRR / Equity Multiple
A16: Number of Units | B16: 145 | D16: Construction Loan Amount | E16: 20872774 | G16: Equity | I16: 13915183 | K16: # of Units | L16: Unit Type | M16: SF | N16: Rent/Month | O16: Rent/SF | Q16: 14.0% / 2.40x | R16: 0.085 | S16: 0.08 | T16: 0.075 | U16: 0.07 | V16: 0.065 | W16: 0.06
A17: Number of Buildings | B17: 10 | D17: Loan to Cost (LTC) | E17: 0.6 | G17: Mezzanine Loan | I17: 0 | K17: 50 | L17: 1BR/1BA | M17: 600 | N17: 1425 | O17: 2.375 | Q17: 36 | R17: -30.8% / 0.41x | S17: -23.4% / 0.51x | T17: -16.7% / 0.63x | U17: -10.3% / 0.75x | V17: -4.1% / 0.89x | W17: 2.1% / 1.06x
A18: Net Rentals SF | B18: 111625 | D18: Fixed or Floating Rate? | E18: Floating-Rate | G18: Construction Loan | I18: 20872774 | K18: 20 | L18: 2BR/1BA | M18: 725 | N18: 1600 | O18: 2.2068966 | Q18: 48 | R18: -18.1% / 0.54x | S18: -12.9% / 0.64x | T18: -8.0% / 0.76x | U18: -3.4% / 0.89x | V18: 1.0% / 1.04x | W18: 5.5% / 1.20x
A19: Average Unit Size SF | B19: 769.82759 | D19: Fixed Rate/Interest Rate Spread | E19: 0.03 | G19: Total | I19: 34787957 | K19: 65 | L19: 2BR/2BA | M19: 875 | N19: 1875 | O19: 2.1428571 | Q19: 60 | R19: -9.4% / 0.69x | S19: -5.7% / 0.79x | T19: -2.2% / 0.91x | U19: 1.2% / 1.05x | V19: 4.4% / 1.20x | W19: 7.7% / 1.37x
A20: Net Acres | B20: 9.5 | D20: Loan Fee (as Percentage of Proceeds | E20: 0.01 | K20: 10 | L20: 3BR/2BA | M20: 1025 | N20: 2100 | O20: 2.0487805 | Q20: 72 | R20: -4.0% / 0.83x | S20: -1.3% / 0.94x | T20: 1.3% / 1.06x | U20: 3.9% / 1.20x | V20: 6.4% / 1.36x | W20: 8.9% / 1.54x
A21: Units per Acre | B21: 15.263158 | D21: Terms | E21: 24 | G21: Uses of Funds (Construction Period) | Q21: 84 | R21: -0.3% / 0.98x | S21: 1.7% / 1.10x | T21: 3.7% / 1.22x | U21: 5.7% / 1.36x | V21: 7.7% / 1.52x | W21: 9.7% / 1.71x
A22: Street Address | B22: 555 Main Street | G22: Land Acquisition Costs | I22: 10000000 | Q22: 96 | R22: 2.2% / 1.14x | S22: 3.8% / 1.26x | T22: 5.4% / 1.39x | U22: 7.0% / 1.53x | V22: 8.6% / 1.70x | W22: 10.2% / 1.89x
A23: City/State/ZIP | B23: Santa Barbara, CA | D23: Permanent Financing Information | G23: Closing Costs | I23: 100000 | Q23: 108 | R23: 4.1% / 1.31x | S23: 5.4% / 1.43x | T23: 6.7% / 1.56x | U23: 8.0% / 1.71x | V23: 9.3% / 1.88x | W23: 10.6% / 2.07x
A24: Currency | B24: USD | D24: Month | E24: 24 | G24: Hard Costs | I24: 19350000 | Q24: 120 | R24: 5.5% / 1.48x | S24: 6.6% / 1.61x | T24: 7.6% / 1.74x | U24: 8.7% / 1.90x | V24: 9.7% / 2.07x | W24: 10.9% / 2.27x
D25: Loan Amount | E25: 23939952 | G25: Soft Costs | I25: 1786679.2
A26: Lease-Up Information | D26: NOI at Permanent Refinancing Month | E26: 2074795.8 | G26: Contingency | I26: 2113667.9
A27: Lease-up Period Begins | B27: 14 | D27: Cap Rate Used for Valuation | E27: 0.065 | G27: Capitalized Construction Interest | I27: 1157333.3
A28: Property Stabilization | B28: 32 | D28: Loan to Value | E28: 0.75 | G28: Mezzanine capitalized Interest | I28: 0
A29: Lease-up Period | B29: 18 | D29: Going Debt Service Cover Ratio | E29: 1.2890971 | G29: Construction Loan Fees | I29: 208727.74 | K29: 145 | M29: 769.82759 | N29: 1697.4138 | O29: 2.2049272
D30: Going-in Debt Yield | E30: 0.086666667 | G30: Operating Expense Shortfalls | I30: 71548.645
A31: Land Acquisition Information | D31: Fixed or Floating Rate? | E31: Floating-Rate | G31: Total | I31: 34787957 | K31: Stabilized Other Income
A32: Land Acquisition Price | B32: 10000000 | D32: Fixed Rate/Interest Rate Spread | E32: 0.02 | K32: Item | M32: $/Unit/Month | N32: $/Month | O32: $/Year
A33: Land Price/Acre | B33: 1052631.6 | D33: Interest-Only Period | E33: 12 | G33: Total Costs Details | K33: Laundry Income | M33: 10 | N33: 1450 | O33: 17400
A34: Land Price/SF | B34: 24.165096 | D34: Loan Fee (as Percentage of Proceeds | E34: 0.01 | G34: Total Project Cost | I34: 34787957 | K34: Late Fees | M34: 3 | N34: 435 | O34: 5220
A35: Closing Costs(% of Land Price) | B35: 0.01 | D35: Amortization | E35: 360 | G35: Total Project Cost/Unit | I35: 239916.94 | K35: Pet Rent | M35: 15 | N35: 2175 | O35: 26100
A36: Closing Costs | B36: 100000 | D36: Term | E36: 96 | G36: Stabilized Return on Cost | I36: 0.069333311 | K36: Pet Fees | M36: 5 | N36: 725 | O36: 8700
A37: Land Closing Date | B37: 45346 | D37: Refince Permanet Debt | E37: N | G37: Cost /SF | I37: 311.65023 | K37: Garage Income | M37: 50 | N37: 7250 | O37: 87000
K38: Storage Income | M38: 0 | N38: 0 | O38: 0
A39: Refinancing debt Information | G39: Sales Details | K39: Other Charges | M39: 0 | N39: 0 | O39: 0
A40: Refinance Month | B40: 60 | D40: Mezzanine Construction Loan: | G40: Sales Prices | I40: 49434636 | K40: Other Charges | M40: 0 | N40: 0 | O40: 0
A41: NOI Used | B41: Trailing 12-month | D41: Mezzanine Debt? | E41: N | G41: Sales Price/Unit | I41: 340928.52 | K41: Other Charges | M41: 0 | N41: 0 | O41: 0
A42: NOI at Permanent Refinancing Month | B42: 2527672.6 | D42: Mezzanine Loan-to-Cost (LTC) Ratio: | E42: 0.1 | G42: Cost of Sale | I42: 494346.36 | K42: Other Charges | M42: 0 | N42: 0 | O42: 0
A43: Loan Amount - Refinance | B43: 25276726 | D43: Mezzanine Cash Interest Rate: | E43: 0.02 | G43: Closing Costs (as % Sale Price) | I43: 0.01 | K43: Other Charges | M43: 0 | N43: 0 | O43: 0
A44: Cap Rate Used for Valuation | B44: 0.065 | D44: Mezzanine PIK Interest Rate: | E44: 0.08 | G44: Exist Cap Rate | I44: 0.06 | K44: Other Charges | M44: 0 | N44: 0 | O44: 0
A45: Loan to Value | B45: 0.65 | D45: Mezzanine Origin Fee | E45: 0.01 | G45: Hold Period | I45: 96 | K45: Total | M45: 83 | N45: 12035 | O45: 144420
A46: Going Debt Service Cover Ratio | B46: 1.3332792 | D46: Mezzanine Amortization Period: | E46: N/A
A47: Going-in Debt Yield | B47: 0.1 | D47: Mezzanine Maturity: | E47: 10 | G47: Equity Structure | L47: 1 | M47: 2 | N47: 3 | O47: 4 | P47: 5
A48: Fixed or Floating Rate? | B48: Floating-Rate | D48: Loan | E48: 3478795.7 | G48: GP Equity | I48: 0.05 | K48: Physical Vacancy | L48: 0 | M48: 0 | N48: 0.03 | O48: 0.03 | P48: 0.03
A49: Fixed Rate/Interest Rate Spread | B49: 0.028 | G49: LP Equity | I49: 0.95 | K49: Bad Debt | L49: 0.01 | M49: 0.01 | N49: 0.01 | O49: 0.01 | P49: 0.01
A50: Interest-Only Period | B50: 6 | K50: Concessions | L50: 0.08 | M50: 0.04 | N50: 0.005 | O50: 0.005 | P50: 0.005
A51: Origination Loan Fee (as Percentage of Proceeds | B51: 0.01 | G51: Waterfall Structure | K51: Other Loss | L51: 0 | M51: 0 | N51: 0 | O51: 0 | P51: 0
A52: Exit Fee | B52: 0.005
A53: Amortization | B53: 360 | G53: No. Tiers | H53: 4 | L53: 1 | M53: 2 | N53: 3 | O53: 4 | P53: 5
A54: Term | B54: 120 | K54: Annual Market Rent Growth | L54: 0.022 | M54: 0.023 | N54: 0.024 | O54: 0.025 | P54: 0.026
H55: Hurdle Return | I55: GP Promote | K55: Other Income Growth | L55: 0.03 | M55: 0.03 | N55: 0.03 | O55: 0.03 | P55: 0.03
G56: Preferred Return | H56: 0.08 | I56: 0
G57: Hurdle #2 | H57: 0.1 | I57: 0.15789474 | K57: Expenses Section
G58: Hurdle #3 | H58: 0.15 | I58: 0.26315789 | K58: Expenses
G59: Hurdle #4 | I59: 0.47368421 | K59: Item | L59: $ Unit/Year | N59: Total | P59: % Fixed
K60: Payroll | L60: 1500 | N60: 217500 | P60: 1
G61: Waterfall CFs Split | H61: GP Cash Flow | I61: LP Cash Flow | K61: General & Administrative | L61: 300 | N61: 43500 | P61: 1
G62: Preferred Return | H62: 0.05 | I62: 0.95 | K62: Marketing Expenses | L62: 250 | N62: 36250 | P62: 1
G63: Hurdle #2 | H63: 0.2 | I63: 0.8 | K63: Repairs & Maintenance | L63: 500 | N63: 72500 | P63: 0.9
G64: Hurdle #3 | H64: 0.3 | I64: 0.7 | K64: Turnover Costs | L64: 300 | N64: 43500 | P64: 0
G65: Hurdle #4 | H65: 0.5 | I65: 0.5 | K65: Contract Services | L65: 150 | N65: 21750 | P65: 1
K66: Utilities | L66: 500 | N66: 72500 | P66: 0.25
G67: Return Metrics | K67: Utility Bill-Back | L67: -400 | N67: -58000 | P67: 0
G68: Unlevered IRR | I68: 0.080379227 | K68: Insurance | L68: 400 | N68: 58000 | P68: 1
G69: Unlevered Equity Multiple | I69: 1.6583956 | K69: Other Costs
G70: Levered IRR | I70: 0.094156423 | K70: Other Costs
G71: Levered Equity Multiple | I71: 1.788036 | K71: Other Costs
G72: Net Profit (Levered CF) | I72: -10699258 | K72: Total | L72: 3500 | N72: 507500 | P72: 0.90714286
G73: LP IRR | I73: 0.094156423
G74: GP IRR | I74: 0.24544801 | K74: Expenses Growth, Mang Fee & Reserve
G75: LP Equity Multiple | I75: 1.788036 | K75: Annual Expense Growth Rate | L75: 0.02
G76: GP Equity Multiple | I76: 4.7799184 | K76: Capital Reserve Expense/Unit | L76: 300
K77: Managment Fee | L77: 0.03
L79: Growth Rates | N79: Amount
K80: Property Taxes | L80: Property Taxes | M80: Fixed charge | N80: Property | O80: Fixed charge
K81: 1 | L81: 0.5 | M81: 0.5 | N81: 50000 | O81: 5000
K82: 2 | L82: 0.5 | M82: 0.5 | N82: 75000 | O82: 7500
K83: 3 | L83: 0.03 | M83: 0.03 | N83: 112500 | O83: 11250
K84: 4 | L84: 0.02 | M84: 0.02 | N84: 115875 | O84: 11587.5
K85: 5 | L85: 0.02 | M85: 0.02 | N85: 118192.5 | O85: 11819.25
K86: 6 | L86: 0.02 | M86: 0.02 | N86: 120556.35 | O86: 12055.635
K87: 7 | L87: 0.02 | M87: 0.02 | N87: 122967.48 | O87: 12296.748
K88: 8 | L88: 0.02 | M88: 0.02 | N88: 125426.83 | O88: 12542.683
K89: 9 | L89: 0.02 | M89: 0.02 | N89: 127935.36 | O89: 12793.536
K90: 10 | L90: 0.02 | M90: 0.02 | N90: 130494.07 | O90: 13049.407
K91: 11 | L91: 0.02 | M91: 0.02 | N91: 133103.95 | O91: 13310.395
K93: Property Tax Information
K94: Millage Rate | L94: 0.012
K95: Tax Reassessed upon sale | L95: 1
K96: Percentage of Value Assessed | L96: 1
A107: End of the Sheet

Sheet Sample AI QUESTIONS
B2: Question | C2: Answer | D2: Source 1 | E2: Source 2 | F2: Source 3
B3: What is the project basis? | C3: =_xlfn.CONCAT("The project basis is ",TEXT(D3,"$0,0")," per unit.") -> The project basis is $239,917 per unit. | D3: ='POC OUTPUT'!I23 -> 239916.94
B4: What is the land basis? | C4: =_xlfn.CONCAT("The land basis is ",TEXT(D4,"$0,0")," per unit.") -> The land basis is $68,966 per unit. | D4: ='POC OUTPUT'!I26 -> 68965.517
B5: When does the senior loan mature? | C5: =_xlfn.CONCAT("The senior loan matures on ",TEXT(D5,"mm/dd/yyy"),".") -> The senior loan matures on 02/28/2026. | D5: ='PERPETUITY MIDDLEMAN INPUT TAB'!F14 -> 46081
B6: When did the transaction close: | C6: =_xlfn.CONCAT("The deal closed on ",TEXT(D6,"mm/dd/yyy"),".") -> The deal closed on 02/24/2024. | D6: ='PERPETUITY MIDDLEMAN INPUT TAB'!C11 -> 45346
B7: What is the expected IRR and MOIC for this investment? | C7: =_xlfn.CONCAT("The expected IRR is ",TEXT(D7,"0.0%")," and MOIC is a ",TEXT(E7,"0.0x"),".") -> The expected IRR is 4.9% and MOIC is a 1.5x. | D7: ='POC OUTPUT'!L29 -> 0.048843762 | E7: ='POC OUTPUT'!L30 -> 1.4622176
B8: What is the expected sale price? | C8: =_xlfn.CONCAT("The expected sale price is ",TEXT(D8,"$0,0")," per unit.") -> The expected sale price is $255,136 per unit. | D8: ='POC OUTPUT'!N23 -> 255135.96
B9: What is the expected sale date? | C9: =_xlfn.CONCAT("The senior loan matures on ",TEXT(D9,"mm/dd/yyy"),".") -> The senior loan matures on 02/29/2032. | D9: ='POC OUTPUT'!N19 -> 48273
B10: What are the senior loan terms? | C10: =_xlfn.CONCAT("The senior loan is ",TEXT(D10,"0.0%")," LTC priced at ",E10," ",TEXT(F10,"0.0%"),".") -> The senior loan is 60.0% LTC priced at SOFR 3.0%. | D10: ='PERPETUITY MIDDLEMAN INPUT TAB'!F5 -> 0.6 | E10: ='PERPETUITY MIDDLEMAN INPUT TAB'!F7 -> SOFR | F10: ='PERPETUITY MIDDLEMAN INPUT TAB'!F8 -> 0.03

Sheet Issues List
B2: Mistakes In Model
B3: Fix concessions driving revenue negative
B4: Fix bad debt for the same problem
B5: These are dupes | C5: ='PERPETUITY MIDDLEMAN INPUT TAB'!C14+'PERPETUITY MIDDLEMAN INPUT TAB'!C18 -> 48
B6: Fixed Pet rent monthly / annua
B7: Built Retail Tab | C7: ='Income Statement - AM'!C67 -> 13451.25
B12: Edge Cases
B13: Cost Recoups in WF | C13: =SUM('AIRR Input Tab'!K21:O26) -> 11.63
B14: Lookbacks
B18: Seasonalized move in
B19: Opex Ramp | C19: ='Income Statement - AM'!D70 -> 0

Sheet Model Variants
B3: AIRR Model Variants by Property Type and Deal Type
B4: Property Type | C4: Residential (Multifamily, Build to Rent, Student Housing) | D4: Commercial (Office, Industrial, Retail) | F4: Self Storage | G4: Hotel | H4: For Sale (Land, Condo, Homes) | I4: Total Models
D5: Excel-Based | E5: Argus - Based
B6: Acquistion Deal | C6: 1 | D6: 1 | E6: 1 | F6: 1 | G6: 1 | H6: 1 | I6: =SUM(C6:H6) -> 6
B7: Development Deal | C7: 1 | D7: 1 | E7: 1 | F7: 1 | G7: 1 | H7: 1 | I7: =SUM(C7:H7) -> 6
B8: Total Models | C8: =SUM(C6:C7) -> 2 | D8: =SUM(D6:D7) -> 2 | E8: =SUM(E6:E7) -> 2 | F8: =SUM(F6:F7) -> 2 | G8: =SUM(G6:G7) -> 2 | H8: =SUM(H6:H7) -> 2 | I8: =SUM(C8:H8) -> 12

Sheet GUIDES FOR GEN AI LABS-->

Sheet MODEL GUIDE
B2: Model Variations Across Property Types
B3: Overview of Model Tabs
B4: Input Tab
B5: Deal Overview | C5: This tab contains all the general details about the transaction - what, where, who.
B6: Assumptions Tab | C6: This is the central nervous system of the model. This tab houses all construction, operating, and sale assumptions.
B7: Unit Mix and Other Income | C7: This tab drives the rent/revenue assumptions for the model.
B9: Actuals
B10: Balance Sheet | C10: These historical financials are sent to the analyst monthly (PDF, excel) and are currently populated by hand. They will need to be automatically ingested / populated into AIRR.
B11: Income Statement | C11: These historical financials are sent to the analyst monthly (PDF, excel) and are currently populated by hand. They will need to be automatically ingested / populated into AIRR.
B12: Draws | C12: These historical financials are sent to the analyst monthly (PDF, excel) and are currently populated by hand. They will need to be automatically ingested / populated into AIRR.
B14: Summary Ouputs | C14: These are the summary dashboards of the model. The will pull data from the inputs tabs as well as the model tabs below.
B16: AIRR Asset Management Model
B17: Income Statement - Revenue / Expenses | C17: These tabs will pull in historical actuals from the tabs above and blend it with a new CF forecast through sale that is driven by the input tabs.
B18: Cash Flow Tab | C18: These tabs will pull in historical actuals from the tabs above and blend it with a new CF forecast through sale that is driven by the input tabs.
B19: Waterfall | C19: These tabs will pull in historical actuals from the tabs above and blend it with a new CF forecast through sale that is driven by the input tabs.
B21: Underwriting
B22: Income Statement - Revenue / Expenses | C22: These tabs will run the assumptions of the original underwriting model and stay static so that the AIRR asset management model can be compared to the original underwriting.
B23: Cash Flow Tab | C23: These tabs will run the assumptions of the original underwriting model and stay static so that the AIRR asset management model can be compared to the original underwriting.
B24: Waterfall | C24: These tabs will run the assumptions of the original underwriting model and stay static so that the AIRR asset management model can be compared to the original underwriting.
B26: Model Variations Across Property Types - The table below details how the model will vary across different property types. This model is for multifamily.
B27: Overview of Model Tabs | C27: AI Populates Data | D27: Multifamily | E27: Build for Rent | F27: Student Housing | G27: Self Storage | H27: Industrial / IOS - Excel | I27: Industrial - Argus | J27: Office - Argus | K27: Retail - Argus | L27: Hotel | M27: For Sale (Land, Condo, Homes)
B28: Input Tab
B29: Deal Overview | C29: Here | D29: Same
B30: Assumptions Tab | C30: Here | D30: Same | H30: Industrial / IOS | I30: Similar | L30: Hotel Excel | M30: For Sale Excel
B32: Actuals
B33: Balance Sheet | C33: Here | D33: Same / Simliar
B34: Income Statement
B35: Draws
B37: Summary Ouputs | D37: Same | H37: Industrial / IOS | J37: Similar | L37: Hotel | M37: For Sale Excel
B39: AIRR Asset Management Model
B40: Income Statement - Revenue / Expenses | D40: Same | H40: Industrial / IOS | I40: Argus Cash Flow | L40: Hotel Excel | M40: For Sale Excel
B41: Cash Flow Tab | D41: Same | M41: For Sale Excel
B42: Waterfall | D42: Same
B44: Underwriting
B45: Income Statement - Revenue / Expenses | D45: Similar | H45: Industrial / IOS | I45: Argus Cash Flow | L45: Hotel Excel | M45: For Sale Excel
B46: Cash Flow Tab | D46: Same | M46: For Sale Excel
B47: Waterfall | D47: Same
B49: Note: Argus is a dominant software platform used to model the operating cash flows of large commercial office buildings and retail. It has limited modeling functionaity beyond the operating cash flows. Users will be able to take the Argus operating cash flow excel tab and drop it into AIRR.

Sheet POC OUTPUT
K8: Property Details
K10: Deal Name | N10: ='AIRR Input Tab'!D17 -> West Village Complexes
K11: Property Type | N11: Multifamily
K12: Closing Date | N12: ='PERPETUITY MIDDLEMAN INPUT TAB'!C11 -> 45346
K13: City | N13: 555 Main Street
K14: State | N14: Santa Barbara, CA
K15: Number of Units | N15: 145
F17: Budget | K17: Exit Assumptions
F19: Sources | G19: $ | H19: % | I19: Per Unit | K19: Sale Date | N19: ='PERPETUITY MIDDLEMAN INPUT TAB'!F24 -> 48273
F20: Senior Loan | G20: ='PERPETUITY MIDDLEMAN INPUT TAB'!J5 -> 20872774 | H20: =G20/$G$23 -> 0.6 | I20: =G20/$N$15 -> 143950.17 | K20: Sale Month | N20: ='PERPETUITY MIDDLEMAN INPUT TAB'!F25 -> 96
F21: LP Equity | G21: ='PERPETUITY MIDDLEMAN INPUT TAB'!J7 -> 13219424 | H21: =$G$23/$G$23 -> 1 | I21: =G21/$N$15 -> 91168.438 | K21: Exit Capitalization (MF) | N21: ='PERPETUITY MIDDLEMAN INPUT TAB'!F28 -> 0.06
F22: GP Equity | G22: ='PERPETUITY MIDDLEMAN INPUT TAB'!J8 -> 695759.14 | H22: =$G$23/$G$23 -> 1 | I22: =G22/$N$15 -> 4798.3389 | K22: Sale Price | N22: ='AIRR Model Summary'!E50 -> 36994714
F23: Total Uses | G23: =SUM(G20:G22) -> 34787957 | H23: =H22 -> 1 | I23: =SUM(I20:I22) -> 239916.94 | K23: Sale Price / Unit | N23: =N22/N15 -> 255135.96
F25: Uses | G25: $ | H25: % | I25: Per Unit | K25: Returns
F26: Land | G26: ='PERPETUITY MIDDLEMAN INPUT TAB'!J13 -> 10000000 | H26: =G26/$G$32 -> 0.2874558 | I26: =G26/$N$15 -> 68965.517
F27: Hard Costs | G27: ='PERPETUITY MIDDLEMAN INPUT TAB'!J14 -> 19350000 | H27: =G27/$G$32 -> 0.55622698 | I27: =G27/$N$15 -> 133448.28 | L27: ='AIRR Model Summary'!J67 -> Levered | M27: ='AIRR Model Summary'!K67 -> Investar | N27: ='AIRR Model Summary'!L67 -> Ace
F28: Soft Costs | G28: ='PERPETUITY MIDDLEMAN INPUT TAB'!J15 -> 4000347.1 | H28: =G28/$G$32 -> 0.1149923 | I28: =G28/$N$15 -> 27588.601 | K28: Investment | L28: ='AIRR Model Summary'!J68 -> 14850077 | M28: ='AIRR Model Summary'!K68 -> 14107573 | N28: ='AIRR Model Summary'!L68 -> 742503.86
F29: Financing Costs | G29: ='PERPETUITY MIDDLEMAN INPUT TAB'!J16 -> 208727.74 | H29: =G29/$G$32 -> 0.006 | I29: =G29/$N$15 -> 1439.5017 | K29: IRR | L29: ='AIRR Model Summary'!J69 -> 0.048843762 | M29: ='AIRR Model Summary'!K69 -> 0.046859661 | N29: ='AIRR Model Summary'!L69 -> 0.082324043
F30: Operating Reserve | G30: ='PERPETUITY MIDDLEMAN INPUT TAB'!J17 -> 71548.645 | H30: =G30/$G$32 -> 0.0020567073 | I30: =G30/$N$15 -> 493.43893 | K30: MOIC | L30: ='AIRR Model Summary'!J70 -> 1.4622176 | M30: ='AIRR Model Summary'!K70 -> 1.440323 | N30: ='AIRR Model Summary'!L70 -> 1.8782134
F31: Senior Interest Reserve | G31: ='PERPETUITY MIDDLEMAN INPUT TAB'!J18 -> 1157333.3 | H31: =G31/$G$32 -> 0.033268218 | I31: =G31/$N$15 -> 7981.6091 | K31: Net Profit | L31: ='AIRR Model Summary'!J71 -> 6863967.6 | M31: ='AIRR Model Summary'!K71 -> 6211890.8 | N31: ='AIRR Model Summary'!L71 -> 652076.88
F32: Total Uses | G32: =SUM(G26:G31) -> 34787957 | H32: =SUM(H26:H31) -> 1 | I32: =SUM(I26:I31) -> 239916.94 | K32: Exit / Unit | L32: ='AIRR Model Summary'!J72 -> 255135.96 | M32: ='AIRR Model Summary'!K72 -> 255135.96 | N32: ='AIRR Model Summary'!L72 -> 255135.96
K46: Exit Assumptions
K50: NOI Type | L50: F12
K51: Sale Costs % | L51: 0.02
K52: Exit Capitalization Rate (MF) | L52: 0.0475

Sheet Trailing Financial Statements->

Sheet Actuals Income Statement
B2: Income Statement
B3: Month | D3: ='Income Statement - AM'!D3 -> 0 | E3: ='Income Statement - AM'!E3 -> 1 | F3: ='Income Statement - AM'!F3 -> 2 | G3: ='Income Statement - AM'!G3 -> 3 | H3: ='Income Statement - AM'!H3 -> 4 | I3: ='Income Statement - AM'!I3 -> 5 | J3: ='Income Statement - AM'!J3 -> 6 | K3: ='Income Statement - AM'!K3 -> 7 | ... DT3: ='Income Statement - AM'!DT3 -> 120
B4: Year | D4: ='Income Statement - AM'!D4 -> 0 | E4: ='Income Statement - AM'!E4 -> 1 | F4: ='Income Statement - AM'!F4 -> 1 | G4: ='Income Statement - AM'!G4 -> 1 | H4: ='Income Statement - AM'!H4 -> 1 | I4: ='Income Statement - AM'!I4 -> 1 | J4: ='Income Statement - AM'!J4 -> 1 | K4: ='Income Statement - AM'!K4 -> 1 | ... DT4: ='Income Statement - AM'!DT4 -> 10
B5: Date | D5: ='Income Statement - AM'!D5 -> 45346 | E5: ='Income Statement - AM'!E5 -> 45382 | F5: ='Income Statement - AM'!F5 -> 45412 | G5: ='Income Statement - AM'!G5 -> 45443 | H5: ='Income Statement - AM'!H5 -> 45473 | I5: ='Income Statement - AM'!I5 -> 45504 | J5: ='Income Statement - AM'!J5 -> 45535 | K5: ='Income Statement - AM'!K5 -> 45565 | ... DT5: ='Income Statement - AM'!DT5 -> 49003
B7: Rental Income
B8: 400000 | C8: Gross Potential Rent | D8: 232800 | E8: 232800 | F8: 232758 | G8: 212640 | H8: 212640 | I8: 270720 | J8: 270720 | K8: 270720 | L8: 270720 | M8: 270720 | N8: 270720 | O8: 270720
B9: 401000 | C9: Vacancy | D9: -106215 | E9: -107670 | F9: -100395 | G9: -96205 | H9: -108589 | I9: -138799 | J9: -137877 | K9: -133066 | L9: -129720 | M9: -126502 | N9: -124201 | O9: -140506
B10: 401200 | C10: Vacancy Loss - Model | D10: -1940 | E10: -1940 | F10: -1940 | G10: -1772 | H10: -1772 | I10: -2256 | J10: -2256 | K10: -2256 | L10: -2256 | M10: -2256 | N10: -2256 | O10: -2256
B11: 401500 | C11: No-Prorate Credits | D11: 0 | E11: 0 | F11: 0 | G11: 0 | H11: 0 | I11: 0 | J11: 0 | K11: 0 | L11: 0 | M11: 0 | N11: 0 | O11: -100
B12: 401600 | C12: Gain/Loss to Lease | D12: 21952 | E12: -8763 | F12: -5615.21 | G12: 6317.3 | H12: 16132.3 | I12: -3834 | J12: -2401 | K12: -6937 | L12: -6994 | M12: -5875 | N12: -6484 | O12: 1422
B13: 401700 | C13: Staff/Employee Accommodations | D13: -5335 | E13: -5380 | F13: -7275 | G13: -6249.3 | H13: -6249.3 | I13: -5494 | J13: -5993 | K13: -5993 | L13: -5993 | M13: -5993 | N13: -5993 | O13: -6798.32
B14: 402800 | C14: Bad Debt | D14: -28217.9 | E14: -11342.78 | F14: 6216.16 | G14: -14109.32 | H14: -52409.86 | I14: -35395.06 | J14: -30726.85 | K14: -37481.54 | L14: -18926.83 | M14: -29778.06 | N14: -16636.49 | O14: -28882.9
B15: 403000 | C15: Bad Debt Recovered | D15: 0 | E15: 1464 | F15: 0 | G15: 0 | H15: 2530.02 | I15: 0 | J15: 8071.3 | K15: 0 | L15: 0 | M15: 0 | N15: 0 | O15: 0
B16: 403200 | C16: Concessions-Recurring | D16: 0 | E16: -45 | F16: 90 | G16: 0 | H16: 0 | I16: -6899 | J16: -7339 | K16: -8069 | L16: -8129 | M16: -8449 | N16: -8161 | O16: -9417
B17: 403300 | C17: Concessions-One Time | D17: -1299 | E17: 0 | F17: 0 | G17: -500 | H17: -1098.36 | I17: -1640 | J17: 0 | K17: 0 | L17: 0 | M17: 0 | N17: 0 | O17: 0
B24: Total Rental Income | D24: =SUM(D8:D23) -> 111745.1 | E24: =SUM(E8:E23) -> 99123.22 | F24: =SUM(F8:F23) -> 123838.95 | G24: =SUM(G8:G23) -> 100121.68 | H24: =SUM(H8:H23) -> 61183.8 | I24: =SUM(I8:I23) -> 76402.94 | J24: =SUM(J8:J23) -> 92198.45 | K24: =SUM(K8:K23) -> 76917.46 | ... DT24: =SUM(DT8:DT23) -> 0
B27: Other Income
B28: 403500 | C28: Parking Permit-Contract | D28: 0 | E28: 0 | F28: 0 | G28: 1125 | H28: 0 | I28: 0 | J28: 0 | K28: 0 | L28: 0 | M28: 0 | N28: 0 | O28: 0
B29: 407500 | C29: Utility Income | D29: 8560.1 | E29: 23907.52 | F29: 17724.9 | G29: 11987.72 | H29: 12067.49 | I29: 58340.65 | J29: 12665.53 | K29: 12876.35 | L29: 17356.81 | M29: 24665.91 | N29: 20998.29 | O29: 20788.5
B30: 412100 | C30: Damages/Resident Bill Backs | D30: 925 | E30: 3070.73 | F30: 8.29 | G30: 0 | H30: 8825 | I30: 4410 | J30: 3030 | K30: 5045 | L30: 990 | M30: 3850 | N30: 895 | O30: 2790
B31: 412300 | C31: Lease Charges | D31: 0 | E31: 2001 | F31: 0 | G31: 0 | H31: 0 | I31: 0 | J31: 0 | K31: 0 | L31: 0 | M31: 0 | N31: 804.47 | O31: 500
B32: 412700 | C32: Insurance Waiver Program Income | D32: 3196.07 | E32: 2984 | F32: 2116.46 | G32: 3090 | H32: 3495 | I32: 2655 | J32: 2820 | K32: 3105 | L32: 2640 | M32: 2820 | N32: 2745 | O32: 2850
B33: 412800 | C33: Guarantor Waiver Program Income | D33: 690 | E33: 828 | F33: 930 | G33: 864 | H33: 972 | I33: 0 | J33: 0 | K33: 0 | L33: 0 | M33: 0 | N33: 0 | O33: 0
B34: 412900 | C34: Credit Reporting Program Income | D34: 0 | E34: 0 | F34: -7 | G34: 7 | H34: 7 | I34: -147 | J34: 49 | K34: 42 | L34: 35 | M34: 21 | N34: 0 | O34: 0
B35: 413000 | C35: Late Fees | D35: 5499.06 | E35: 4966.95 | F35: 4650.73 | G35: -162.5 | H35: 2535 | I35: 4057.08 | J35: 3645.42 | K35: 3315 | L35: 3282.5 | M35: 2795 | N35: 3380 | O35: 4030
B36: 413500 | C36: NSF Fees | D36: 20 | E36: -10 | F36: 100 | G36: 20 | H36: 50 | I36: 50 | J36: 0 | K36: 0 | L36: 0 | M36: -50 | N36: 50 | O36: 0
B37: 414000 | C37: Miscellaneous Income | D37: 235.34 | E37: 1589.7 | F37: 480 | G37: -330 | H37: 2640 | I37: 390 | J37: 156.32 | K37: 0 | L37: 120 | M37: 120 | N37: 120 | O37: 365.06
B38: 415500 | C38: Application Fees | D38: -319 | E38: 380.45 | F38: 258 | G38: 4300 | H38: 100 | I38: 0 | J38: 0 | K38: 0 | L38: 0 | M38: 0 | N38: 0 | O38: 0
B39: 415700 | C39: Lease Termination Fees | D39: 0 | E39: 0 | F39: 0 | G39: 0 | H39: 5000 | I39: 5250 | J39: 2250 | K39: 3750 | L39: 750 | M39: 2585 | N39: 849 | O39: 750
B50: Total Other Income | D50: =SUM(D28:D49) -> 18806.57 | E50: =SUM(E28:E49) -> 39718.35 | F50: =SUM(F28:F49) -> 26261.38 | G50: =SUM(G28:G49) -> 20901.22 | H50: =SUM(H28:H49) -> 35691.49 | I50: =SUM(I28:I49) -> 75005.73 | J50: =SUM(J28:J49) -> 24616.27 | K50: =SUM(K28:K49) -> 28133.35 | ... DT50: =SUM(DT28:DT49) -> 0
B52: Effective Gross Income (Total) | D52: =D24+D50 -> 130551.67 | E52: =E24+E50 -> 138841.57 | F52: =F24+F50 -> 150100.33 | G52: =G24+G50 -> 121022.9 | H52: =H24+H50 -> 96875.29 | I52: =I24+I50 -> 151408.67 | J52: =J24+J50 -> 116814.72 | K52: =K24+K50 -> 105050.81 | ... DT52: =DT24+DT50 -> 0
B55: Payroll and Benefits
B56: 650100 | C56: Admin Salaries | D56: 8242.86 | E56: 7047.96 | F56: 8618.36 | G56: 7310.54 | H56: 8458.26 | I56: 8797.51 | J56: 9461.46 | K56: 6272 | L56: 5261 | M56: 7081.5 | N56: 5665 | O56: 6271
B57: 650200 | C57: Maintenance Salaries | D57: 4366.53 | E57: 4560.67 | F57: 4112.2 | G57: 3634.79 | H57: 3499.23 | I57: 4052.6 | J57: 4994.7 | K57: 5815.71 | L57: 2754.98 | M57: 3688.93 | N57: 2812.36 | O57: 3921.78
B58: 650300 | C58: Leasing Salaries | D58: 2221.2 | E58: 2228.44 | F58: 4065 | G58: 3621.5 | H58: 2859.3 | I58: 2616 | J58: 2734.45 | K58: 2908.35 | L58: 2181.5 | M58: 3104.4 | N58: 2255.3 | O58: 3666.55
B59: 650400 | C59: Res Life Salaries | D59: 939.91 | E59: 871.35 | F59: 0 | G59: -440.33 | H59: 1403.54 | I59: 630.49 | J59: 1002.03 | K59: 486.85 | L59: 752 | M59: 1100.42 | N59: 2438.55 | O59: 1364.25
B60: 650700 | C60: Overtime | D60: 62.37 | E60: 339.58 | F60: 651.21 | G60: 375.27 | H60: 2450.72 | I60: 1192.37 | J60: 470.93 | K60: 910.32 | L60: 1026.29 | M60: 583.41 | N60: 746.41 | O60: 800.19
B61: 653100 | C61: Admin Taxes and Benefits | D61: 3861.69 | E61: 2242 | F61: 2398.49 | G61: 1730.56 | H61: 2437.4 | I61: 2708.83 | J61: 2848.96 | K61: 1805.99 | L61: 1752.47 | M61: 1879.57 | N61: 1719.85 | O61: 1978.4
B62: 653200 | C62: Maintenance Taxes and Benefits | D62: 1651.99 | E62: 1763.62 | F62: 1493.09 | G62: 1025.59 | H62: 1780.05 | I62: 1703.37 | J62: 1763.17 | K62: 1769.59 | L62: 1440.13 | M62: 1235.76 | N62: 1405.01 | O62: 1503.15
B63: 653300 | C63: Leasing Taxes and Benefits | D63: 382.89 | E63: 349.32 | F63: 685.81 | G63: 571.49 | H63: 557 | I63: 795.77 | J63: 522.01 | K63: 581.61 | L63: 543.77 | M63: 484.83 | N63: 459.02 | O63: 658.8
B64: 653400 | C64: Res Life Taxes and Benefits | D64: 215.04 | E64: 188.89 | F64: 0 | G64: -95.5 | H64: 286.77 | I64: 216.57 | J64: 217.91 | K64: 142.19 | L64: 181.74 | M64: 346.65 | N64: 452.58 | O64: 446.62
B65: 654500 | C65: Staff Accommodations | D65: 0 | E65: 0 | F65: 0 | G65: 0 | H65: 0 | I65: 0 | J65: 0 | K65: 0 | L65: 0 | M65: 0 | N65: 0 | O65: 208.93
B66: 655100 | C66: Admin Bonuses | D66: 8000 | E66: 358.65 | F66: 0 | G66: 0 | H66: 0 | I66: 0 | J66: 0 | K66: 0 | L66: 0 | M66: 0 | N66: 0 | O66: 0
B67: 657000 | C67: Professional Development/Training | D67: 40.14 | E67: 128.61 | F67: 2074.34 | G67: 74.34 | H67: 81.03 | I67: 87.72 | J67: 87.72 | K67: 123.19 | L67: 157.37 | M67: 52.01 | N67: 136.01 | O67: 92.22
... B69: 658000 | C69: Recruiting and Reloc Expense | D69: 260.23 | E69: 376.92 | F69: 1580.13 | G69: 20.13 | H69: 20.13 | I69: 20.13 | J69: 1223.27 | K69: 154.82 | L69: 649 | M69: 120.75 | N69: 263.06 | O69: 0
B71: Total Payroll and Benefits | D71: =SUM(D56:D70) -> 30494.85 | E71: =SUM(E56:E70) -> 20456.01 | F71: =SUM(F56:F70) -> 25553.63 | G71: =SUM(G56:G70) -> 16978.38 | H71: =SUM(H56:H70) -> 25533.43 | I71: =SUM(I56:I70) -> 27246.36 | J71: =SUM(J56:J70) -> 23076.61 | K71: =SUM(K56:K70) -> 23220.62 | ... DT71: =SUM(DT56:DT70) -> 0
B74: Utilities
B76: 680500 | C76: Electricity - Common Area | D76: 971.23 | E76: 1081.71 | F76: 657.22 | G76: 657.22 | H76: 932.7 | I76: 1029.09 | J76: 971.23 | K76: 825.61 | L76: 1007.5 | M76: 1295.13 | N76: 1333.29 | O76: 1308.6
B77: 681000 | C77: Water/Sewer - Common Area | D77: 1184.18 | E77: 2214.75 | F77: 1996.35 | G77: 664.35 | H77: 300.35 | I77: 717.39 | J77: 1184.18 | K77: 1711.71 | L77: 123.35 | M77: 114.95 | N77: 207.35 | O77: 182.15
B78: 690500 | C78: Electricity - Units | D78: 23178.16 | E78: 19189.66 | F78: 20739.43 | G78: 20730.5 | H78: 18635.24 | I78: 27863.26 | J78: 23135.43 | K78: 14100.51 | L78: 20163.17 | M78: 26927.04 | N78: 22615.05 | O78: 21098.37
B79: 691000 | C79: Electricity - Vacant Units | D79: 935.71 | E79: 1827.41 | F79: 3183.13 | G79: 3183.13 | H79: 2612.74 | I79: 1445.69 | J79: 935.71 | K79: 1160.55 | L79: 1521.66 | M79: 2932.05 | N79: 3888.25 | O79: 2435.85
B80: 691500 | C80: Water/Sewer - Units | D80: 16225.73 | E80: 31619.85 | F80: 13744.73 | G80: 15084.54 | H80: 11443.77 | I80: 17065.94 | J80: 16150.39 | K80: 8725.56 | L80: 8641.34 | M80: 10083.84 | N80: 10144.7 | O80: 10195.63
B81: 693500 | C81: Internet Service | D81: 2712.08 | E81: 2636.52 | F81: 2413.95 | G81: 2338.53 | H81: 2712.52 | I81: 2715.2 | J81: 2413.95 | K81: 2413.95 | L81: 2413.95 | M81: 2413.95 | N81: 2413.95 | O81: 2413.95
B83: Total Utilities | D83: =SUM(D76:D82) -> 45207.09 | E83: =SUM(E76:E82) -> 58569.9 | F83: =SUM(F76:F82) -> 42734.81 | G83: =SUM(G76:G82) -> 42658.27 | H83: =SUM(H76:H82) -> 36637.32 | I83: =SUM(I76:I82) -> 50836.57 | J83: =SUM(J76:J82) -> 44790.89 | K83: =SUM(K76:K82) -> 28937.89 | ... DT83: =SUM(DT76:DT82) -> 0
B86: Turnover
B88: 670000 | C88: Turn - Interior Paint | D88: 0 | E88: 79.64 | F88: -14537.66 | G88: 0 | H88: 27222.71 | I88: 5800 | J88: 0 | K88: 0 | L88: 0 | M88: 0 | N88: 0 | O88: 0
B89: 670300 | C89: Turn - Interior Paint Supplies | D89: 0 | E89: 0 | F89: 0 | G89: 0 | H89: 0 | I89: 2070.81 | J89: 0 | K89: 0 | L89: 0 | M89: 0 | N89: 0 | O89: 0
B90: 670500 | C90: Turn - Locks/Keys | D90: 0 | E90: 488.37 | F90: 0 | G90: 0 | H90: 356.49 | I90: 0 | J90: 0 | K90: 0 | L90: 0 | M90: 0 | N90: 0 | O90: 0
B91: 671000 | C91: Turn - Carpet/Tile Clean/Replace | D91: 0 | E91: 10239.31 | F91: 202.4 | G91: 0 | H91: 0 | I91: 27607.02 | J91: 0 | K91: 0 | L91: 0 | M91: 0 | N91: 0 | O91: 0
B92: 671500 | C92: Turn - Interior Repairs | D92: 0 | E92: 0 | F92: 1502.17 | G92: 0 | H92: 1149.47 | I92: 0 | J92: 0 | K92: 0 | L92: 0 | M92: 0 | N92: 0 | O92: 0
B93: 672000 | C93: Turn - Interior Cleaning | D93: 0 | E93: -6900 | F93: -940 | G93: 0 | H93: 29260 | I93: 1960 | J93: 0 | K93: 0 | L93: 0 | M93: 0 | N93: 0 | O93: 0
B94: 673000 | C94: Turn - Flooring Replacement | D94: 0 | E94: 0 | F94: 0 | G94: 0 | H94: 0 | I94: 1484.33 | J94: 0 | K94: 0 | L94: 0 | M94: 0 | N94: 0 | O94: 0
B95: 673500 | C95: Turn - Temporary Labor Costs | D95: 0 | E95: 1630 | F95: -19 | G95: 0 | H95: 4968 | I95: 195.5 | J95: 0 | K95: 0 | L95: 0 | M95: 0 | N95: 0 | O95: 0
B96: 674000 | C96: Turn - Window Coverings | D96: 0 | E96: 0 | F96: 0 | G96: 0 | H96: 4120.65 | I96: 0 | J96: 0 | K96: 0 | L96: 0 | M96: 0 | N96: 0 | O96: 0
B98: Total Turnover | D98: =SUM(D88:D97) -> 0 | E98: =SUM(E88:E97) -> 5537.32 | F98: =SUM(F88:F97) -> -13792.09 | G98: =SUM(G88:G97) -> 0 | H98: =SUM(H88:H97) -> 67077.32 | I98: =SUM(I88:I97) -> 39117.66 | J98: =SUM(J88:J97) -> 0 | K98: =SUM(K88:K97) -> 0 | ... DT98: =SUM(DT88:DT97) -> 0
B101: Contract Services
B102: 675000 | C102: Landscaping - Contract | D102: 1775 | E102: 3550 | F102: 1450 | G102: 1775 | H102: 1775 | I102: 325 | J102: 1775 | K102: 1775 | L102: 1775 | M102: 1775 | N102: 1775 | O102: 1775
B103: 676500 | C103: Unit Furniture Rental Contract | D103: 43.64 | E103: 107.3 | F103: 107.3 | G103: 63.66 | H103: 63.66 | I103: 63.66 | J103: 63.66 | K103: 63.66 | L103: 63.66 | M103: 63.66 | N103: 63.66 | O103: 63.66
B104: 675400 | C104: Security Services - Contract | D104: 10650 | E104: 770 | F104: 12190 | G104: 0 | H104: 0 | I104: 0 | J104: 0 | K104: 0 | L104: 0 | M104: 0 | N104: 0 | O104: 0
B105: 675800 | C105: Garbage Service Contract | D105: 5134.01 | E105: 4003.1 | F105: 2907.68 | G105: 2907.68 | H105: 2610.1 | I105: 4759 | J105: 5122.66 | K105: 2557.7 | L105: 2572.84 | M105: 2636.31 | N105: 2716.6 | O105: 2678.77
B106: 676000 | C106: Exterminating Contract | D106: 699.98 | E106: 25.94 | F106: 700 | G106: 62.94 | H106: 362.97 | I106: 438 | J106: 587.97 | K106: 762.97 | L106: 583.95 | M106: 351.98 | N106: 588 | O106: 438
B107: 676200 | C107: Life Safety Systems Contract | D107: 0 | E107: 31 | F107: -3469 | G107: 31 | H107: 31 | I107: 31 | J107: 1031 | K107: -119 | L107: 0 | M107: 2681 | N107: 61.1 | O107: 62
B109: Total Contract Services | D109: =SUM(D102:D108) -> 18302.63 | E109: =SUM(E102:E108) -> 8487.34 | F109: =SUM(F102:F108) -> 13885.98 | G109: =SUM(G102:G108) -> 4840.28 | H109: =SUM(H102:H108) -> 4842.73 | I109: =SUM(I102:I108) -> 5616.66 | J109: =SUM(J102:J108) -> 8580.29 | K109: =SUM(K102:K108) -> 5040.33 | ... DT109: =SUM(DT102:DT108) -> 0
B112: Repairs and Maintenance
B113: 660000 | C113: Pool/Hot Tub | D113: 120 | E113: 1243.95 | F113: 0 | G113: 0 | H113: 0 | I113: 332.8 | J113: 177.01 | K113: 46.41 | L113: 111.99 | M113: 331.57 | N113: 0 | O113: 0
B114: 660400 | C114: Cleaning | D114: 0 | E114: 0 | F114: 0 | G114: 0 | H114: 0 | I114: 0 | J114: 0 | K114: 20.13 | L114: 0 | M114: 0 | N114: 0 | O114: 0
B115: 660500 | C115: Building Repairs and Supplies | D115: 0 | E115: 266.85 | F115: 0 | G115: 0 | H115: 816.23 | I115: 423.18 | J115: 0 | K115: 0 | L115: 130.42 | M115: 0 | N115: 107.75 | O115: 112.4
B116: 660600 | C116: General Cleaning Supplies | D116: 0 | E116: 346.47 | F116: 0 | G116: 0 | H116: 171.57 | I116: 0 | J116: 163.32 | K116: 81.16 | L116: 0 | M116: 39.97 | N116: 115.71 | O116: 0
B117: 661000 | C117: Parking Lot, Gate, Fence | D117: 0 | E117: 875 | F117: 450 | G117: 0 | H117: 0 | I117: 0 | J117: 0 | K117: 375 | L117: 147.28 | M117: 0 | N117: 0 | O117: 0
B118: 662000 | C118: R&M Landscaping | D118: 0 | E118: 0 | F118: 0 | G118: 0 | H118: 0 | I118: -1300 | J118: 250 | K118: 0 | L118: 0 | M118: 2500 | N118: 0 | O118: 0
B119: 663000 | C119: Electrical Supplies | D119: 0 | E119: 156.6 | F119: 0 | G119: 0 | H119: 237.96 | I119: 0 | J119: 272.59 | K119: 38.57 | L119: 0 | M119: 0 | N119: 0 | O119: 0
B120: 663100 | C120: Lighting | D120: 239.39 | E120: 933.51 | F120: 21.54 | G120: 0 | H120: 130.05 | I120: 305.31 | J120: 163.15 | K120: 55.5 | L120: 180.25 | M120: 15.37 | N120: 0 | O120: 0
B121: 663300 | C121: Ceiling Fans & Fixture Replacement | D121: 0 | E121: 44.2 | F121: 0 | G121: 0 | H121: 643.54 | I121: 0 | J121: 0 | K121: 0 | L121: 0 | M121: 161.25 | N121: 0 | O121: 0
B122: 663500 | C122: Plumbing | D122: 1028.03 | E122: 1869.79 | F122: 572.44 | G122: 1047.25 | H122: 506.48 | I122: 1061.84 | J122: 2258 | K122: 51.1 | L122: 240 | M122: 160 | N122: 241.22 | O122: 0
B123: 663700 | C123: Hot Water Heater & Boiler Repairs | D123: 0 | E123: 0 | F123: 0 | G123: 0 | H123: 139.85 | I123: 0 | J123: 0 | K123: 560.35 | L123: 0 | M123: 0 | N123: 0 | O123: 0
B124: 664500 | C124: Exterior Paint-Supplies & Labr | D124: 0 | E124: 0 | F124: 0 | G124: 0 | H124: 362.78 | I124: 0 | J124: 141.07 | K124: 0 | L124: 0 | M124: 0 | N124: 862.15 | O124: 66.59
... B135: 668900 | C135: Electrical Repair | D135: 0 | E135: 147.5 | F135: 0 | G135: 0 | H135: 0 | I135: 0 | J135: 0 | K135: 0 | L135: 0 | M135: 0 | N135: 0 | O135: 0
B138: Total Repairs and Maintenance | D138: =SUM(D113:D137) -> 1651.06 | E138: =SUM(E113:E137) -> 8703.15 | F138: =SUM(F113:F137) -> 9865.79 | G138: =SUM(G113:G137) -> 5378.66 | H138: =SUM(H113:H137) -> 10515.86 | I138: =SUM(I113:I137) -> 4050.12 | J138: =SUM(J113:J137) -> 1089.04 | K138: =SUM(K113:K137) -> 4270.1 | ... DT138: =SUM(DT113:DT137) -> 0
B141: Leasing and Marketing
B142: 700000 | C142: Print Ads | D142: 0 | E142: 0 | F142: 770 | G142: 0 | H142: 0 | I142: 0 | J142: 0 | K142: 0 | L142: 0 | M142: 0 | N142: 0 | O142: 0
B143: 701200 | C143: Model Unit | D143: 0 | E143: 0 | F143: 0 | G143: 0 | H143: 0 | I143: 0 | J143: 0 | K143: 229.16 | L143: 0 | M143: 0 | N143: 0 | O143: 0
B144: 701500 | C144: Brochures & Letterhead | D144: 0 | E144: 0 | F144: 0 | G144: 0 | H144: 257.1 | I144: 0 | J144: 0 | K144: 0 | L144: 0 | M144: 0 | N144: 0 | O144: 0
B145: 701800 | C145: Marketing Incentives (Gift Cards) | D145: 62.61 | E145: 0 | F145: 0 | G145: 0 | H145: 0 | I145: 0 | J145: 0 | K145: 0 | L145: 0 | M145: 218.25 | N145: 0 | O145: 0
B146: 702000 | C146: Promotional and Collateral Items | D146: 0 | E146: 0 | F146: 0 | G146: 0 | H146: 0 | I146: 0 | J146: 0 | K146: 81.19 | L146: 71.48 | M146: 77.88 | N146: 0 | O146: 462.77
B147: 702200 | C147: Referrals & Locator Fees | D147: 0 | E147: 0 | F147: 0 | G147: 0 | H147: 0 | I147: 265.21 | J147: 0 | K147: 0 | L147: 0 | M147: 0 | N147: 0 | O147: 0
B148: 702500 | C148: Signage / Flags / Banners | D148: 0 | E148: 0 | F148: 0 | G148: 185.92 | H148: 0 | I148: 0 | J148: 0 | K148: 0 | L148: 0 | M148: 0 | N148: 0 | O148: 0
B149: 702600 | C149: Event & Sponsorship Marketing | D149: 0 | E149: 0 | F149: 0 | G149: 0 | H149: 0 | I149: -2500 | J149: 0 | K149: 0 | L149: 0 | M149: 0 | N149: 1250 | O149: 0
B150: 703100 | C150: Text Messaging/Phone Advertising | D150: 523 | E150: 0 | F150: 274 | G150: 0 | H150: 499.61 | I150: 374.28 | J150: 495 | K150: 216 | L150: 155 | M150: 371 | N150: 371 | O150: 371
B151: 703300 | C151: Website Design, Hosting, & SEO | D151: 1567.66 | E151: 854.46 | F151: 1502.04 | G151: 56.46 | H151: 1006.46 | I151: 1291.25 | J151: 979.34 | K151: 1580.11 | L151: 893 | M151: 773.65 | N151: 1547.3 | O151: 1325.32
B152: 703800 | C152: Online Listing Services | D152: 798 | E152: 700 | F152: 600 | G152: 1097 | H152: 300 | I152: 789 | J152: 793 | K152: 1193 | L152: 1093 | M152: 1093 | N152: 1044.61 | O152: 712
...

Sheet Actual Rent Roll
B2: Rent Roll
L3: Scheduled Charges
B4: Unit # | C4: Floorplan | D4: Occupied | E4: Market/Affordable | F4: Classic / Renovated | G4: Name | H4: Lease Start | I4: Lease End | J4: SF | K4: Market Rent | L4: Rent | M4: CONC-RECURRIN | N4: RENTERS INS | O4: EMETSCHOLAR | P4: EMPLCREDLOSS | Q4: PET RENT | R4: Total Billing
B5: 111A | C5: 4x4 | D5: ='Sample RR'!K4 -> Occupied | E5: N/A | F5: N/A | G5: ='Sample RR'!M4 -> Coutee, Gabriel | H5: 45048 | I5: 45777 | J5: 325 | K5: 564 | L5: 544 | M5: -45 | N5: 15 | O5: 0 | P5: 0 | Q5: 0 | R5: =SUM(L5:Q5) -> 514 | S5: ='Sample RR'!AK4-R5 -> 0
B6: ='Sample RR'!A7 -> 111B | C6: ='Sample RR'!C7 -> 4x4 | D6: ='Sample RR'!K7 -> Occupied | E6: N/A | F6: N/A | G6: ='Sample RR'!M7 -> Brown, Ceasar | H6: ='Sample RR'!T7 -> 44775 | I6: ='Sample RR'!V7 -> 45138 | J6: ='Sample RR'!I7 -> 325 | K6: ='Sample RR'!Y7 -> 564 | L6: ='Sample RR'!AF8 -> 519 | M6: ='Sample RR'!AH7 -> -10 | N6: 0 | O6: 0 | P6: 0 | Q6: 0 | R6: =SUM(L6:Q6) -> 509 | S6: ='Sample RR'!AK7-R6 -> 0
B7: ='Sample RR'!A9 -> 111C | C7: ='Sample RR'!C9 -> 4x4 | D7: ='Sample RR'!K9 -> Occupied | E7: N/A | F7: N/A | G7: ='Sample RR'!M9 -> Walker, Taliayah | H7: ='Sample RR'!T9 -> 44775 | I7: ='Sample RR'!V9 -> 45138 | J7: ='Sample RR'!I9 -> 325 | K7: ='Sample RR'!Y9 -> 564 | L7: ='Sample RR'!AF10 -> 534 | M7: ='Sample RR'!AH9 -> -35 | N7: 0 | O7: 0 | P7: 0 | Q7: 0 | R7: =SUM(L7:Q7) -> 499 | S7: ='Sample RR'!AK9-R7 -> 0
B8: ='Sample RR'!A11 -> 111D | C8: ='Sample RR'!C11 -> 4x4 | D8: ='Sample RR'!K11 -> Occupied | E8: N/A | F8: N/A | G8: ='Sample RR'!M11 -> Jones, Travonn | H8: ='Sample RR'!T11 -> 44783 | I8: ='Sample RR'!V11 -> 45138 | J8: ='Sample RR'!I11 -> 325 | K8: ='Sample RR'!Y11 -> 564 | L8: ='Sample RR'!AF12 -> 544 | M8: ='Sample RR'!AH11 -> -45 | N8: ='Sample RR'!AH13 -> 15 | O8: 0 | P8: 0 | Q8: 0 | R8: =SUM(L8:Q8) -> 514 | S8: ='Sample RR'!AK11-R8 -> 0
B9: ='Sample RR'!A14 -> 112A | C9: ='Sample RR'!C14 -> 4x4 | D9: ='Sample RR'!K14 -> Occupied | E9: N/A | F9: N/A | G9: ='Sample RR'!M14 -> Smith, Tyeryka | H9: ='Sample RR'!T14 -> 44776 | I9: ='Sample RR'!V14 -> 45138 | J9: ='Sample RR'!I14 -> 325 | K9: ='Sample RR'!Y14 -> 564 | L9: ='Sample RR'!AF15 -> 544 | M9: ='Sample RR'!AH14 -> -45 | N9: ='Sample RR'!AH16 -> 15 | O9: 0 | P9: 0 | Q9: 0 | R9: =SUM(L9:Q9) -> 514 | S9: ='Sample RR'!AK14-R9 -> 0
B10: ='Sample RR'!A17 -> 112B | C10: ='Sample RR'!C17 -> 4x4 | D10: ='Sample RR'!K17 -> Occupied | E10: N/A | F10: N/A | G10: ='Sample RR'!M17 -> Brown, ShaRron | H10: ='Sample RR'!T17 -> 44774 | I10: ='Sample RR'!V17 -> 45138 | J10: ='Sample RR'!I17 -> 325 | K10: ='Sample RR'!Y17 -> 564 | L10: ='Sample RR'!AF18 -> 549 | M10: ='Sample RR'!AH17 -> -50 | N10: ='Sample RR'!AH19 -> 15 | O10: 0 | P10: 0 | Q10: 0 | R10: =SUM(L10:Q10) -> 514 | S10: ='Sample RR'!AK17-R10 -> 0
B11: ='Sample RR'!A20 -> 112C | C11: ='Sample RR'!C20 -> 4x4 | D11: ='Sample RR'!K20 -> Occupied | E11: N/A | F11: N/A | G11: ='Sample RR'!M20 -> Carter, Kyla | H11: ='Sample RR'!T20 -> 44805 | I11: ='Sample RR'!V20 -> 45138 | J11: ='Sample RR'!I20 -> 325 | K11: ='Sample RR'!Y20 -> 564 | L11: ='Sample RR'!AF21 -> 549 | M11: ='Sample RR'!AH20 -> -50 | N11: 0 | O11: 0 | P11: 0 | Q11: 0 | R11: =SUM(L11:Q11) -> 499 | S11: ='Sample RR'!AK20-R11 -> 0
B12: ='Sample RR'!A22 -> 112D | C12: ='Sample RR'!C22 -> 4x4 | D12: ='Sample RR'!K22 -> Occupied | E12: N/A | F12: N/A | G12: ='Sample RR'!M22 -> Norton, Daysia | H12: ='Sample RR'!T22 -> 44866 | I12: ='Sample RR'!V22 -> 45138 | J12: ='Sample RR'!I22 -> 325 | K12: ='Sample RR'!Y22 -> 564 | L12: ='Sample RR'!AF23 -> 534 | M12: ='Sample RR'!AH22 -> -35 | N12: ='Sample RR'!AH24 -> 15 | O12: 0 | P12: 0 | Q12: 0 | R12: =SUM(L12:Q12) -> 514 | S12: ='Sample RR'!AK22-R12 -> 0
B13: ='Sample RR'!A25 -> 113A | C13: ='Sample RR'!C25 -> 4x4 | D13: ='Sample RR'!K25 -> Vacant | E13: N/A | F13: N/A | G13: ='Sample RR'!M25 -> VACANT | H13: ='Sample RR'!T25 -> 0 | I13: ='Sample RR'!V25 -> 0 | J13: ='Sample RR'!I25 -> 325 | K13: ='Sample RR'!Y25 -> 564 | L13: ='Sample RR'!AF26 -> 0 | M13: ='Sample RR'!AH25 -> 0 | N13: 0 | O13: 0 | P13: 0 | Q13: 0 | R13: =SUM(L13:Q13) -> 0 | S13: ='Sample RR'!AK25-R13 -> 0
B14: ='Sample RR'!A26 -> 113B | C14: ='Sample RR'!C26 -> 4x4 | D14: ='Sample RR'!K26 -> Vacant | E14: N/A | F14: N/A | G14: ='Sample RR'!M26 -> VACANT | H14: ='Sample RR'!T26 -> 0 | I14: ='Sample RR'!V26 -> 0 | J14: ='Sample RR'!I26 -> 325 | K14: ='Sample RR'!Y26 -> 564 | L14: ='Sample RR'!AF27 -> 0 | M14: ='Sample RR'!AH26 -> 0 | N14: ='Sample RR'!AH28 -> 0 | O14: 0 | P14: 0 | Q14: 0 | R14: =SUM(L14:Q14) -> 0 | S14: ='Sample RR'!AK26-R14 -> 0
B15: ='Sample RR'!A27 -> 113C | C15: ='Sample RR'!C27 -> 4x4 | D15: ='Sample RR'!K27 -> Occupied | E15: N/A | F15: N/A | G15: ='Sample RR'!M27 -> Gibson $, Raykivus | H15: ='Sample RR'!T27 -> 44774 | I15: ='Sample RR'!V27 -> 45138 | J15: ='Sample RR'!I27 -> 325 | K15: ='Sample RR'!Y27 -> 564 | L15: ='Sample RR'!AF28 -> 534 | M15: ='Sample RR'!AH27 -> -35 | N15: ='Sample RR'!AH29 -> 15 | O15: 0 | P15: 0 | Q15: 0 | R15: =SUM(L15:Q15) -> 514 | S15: ='Sample RR'!AK27-R15 -> 0
B16: ='Sample RR'!A30 -> 113D | C16: ='Sample RR'!C30 -> 4x4 | D16: ='Sample RR'!K30 -> Occupied | E16: N/A | F16: N/A | G16: ='Sample RR'!M30 -> Caldwell, Ronald | H16: ='Sample RR'!T30 -> 44774 | I16: ='Sample RR'!V30 -> 45138 | J16: ='Sample RR'!I30 -> 325 | K16: ='Sample RR'!Y30 -> 564 | L16: ='Sample RR'!AF36 -> 544 | M16: ='Sample RR'!AH30 -> -45 | N16: ='Sample RR'!AH37 -> 15 | O16: ='Sample RR'!AH31 -> -249 | P16: 0 | Q16: ='Sample RR'!AH32 -> 30 | R16: =SUM(L16:Q16) -> 295 | S16: ='Sample RR'!AK30-R16 -> 0
B17: ='Sample RR'!A38 -> 114A | C17: ='Sample RR'!C38 -> 4x4 | D17: ='Sample RR'!K38 -> Occupied | E17: N/A | F17: N/A | G17: ='Sample RR'!M38 -> Thomas, Christian | H17: ='Sample RR'!T38 -> 44776 | I17: ='Sample RR'!V38 -> 45138 | J17: ='Sample RR'!I38 -> 325 | K17: ='Sample RR'!Y38 -> 564 | L17: ='Sample RR'!AF39 -> 544 | M17: ='Sample RR'!AH38 -> -45 | N17: ='Sample RR'!AH40 -> 15 | O17: 0 | P17: 0 | Q17: 0 | R17: =SUM(L17:Q17) -> 514 | S17: ='Sample RR'!AK38-R17 -> 0
B18: ='Sample RR'!A41 -> 114B | C18: ='Sample RR'!C41 -> 4x4 | D18: ='Sample RR'!K41 -> Occupied | E18: N/A | F18: N/A | G18: ='Sample RR'!M41 -> Fegans $, Antwon | H18: ='Sample RR'!T41 -> 44805 | I18: ='Sample RR'!V41 -> 45138 | J18: ='Sample RR'!I41 -> 325 | K18: ='Sample RR'!Y41 -> 564 | L18: ='Sample RR'!AF42 -> 544 | M18: ='Sample RR'!AH41 -> -45 | N18: ='Sample RR'!AH43 -> 15 | O18: 0 | P18: 0 | Q18: 0 | R18: =SUM(L18:Q18) -> 514 | S18: ='Sample RR'!AK41-R18 -> 0
B19: ='Sample RR'!A44 -> 114C | C19: ='Sample RR'!C44 -> 4x4 | D19: ='Sample RR'!K44 -> Vacant | E19: N/A | F19: N/A | G19: ='Sample RR'!M44 -> VACANT | H19: ='Sample RR'!T44 -> 0 | I19: ='Sample RR'!V44 -> 0 | J19: ='Sample RR'!I44 -> 325 | K19: ='Sample RR'!Y44 -> 564 | L19: ='Sample RR'!AF45 -> 0 | M19: ='Sample RR'!AH44 -> 0 | N19: 0 | O19: 0 | P19: 0 | Q19: 0 | R19: =SUM(L19:Q19) -> 0 | S19: ='Sample RR'!AK44-R19 -> 0
B20: ='Sample RR'!A45 -> 114D | C20: ='Sample RR'!C45 -> 4x4 | D20: ='Sample RR'!K45 -> Vacant | E20: N/A | F20: N/A | G20: ='Sample RR'!M45 -> VACANT | H20: ='Sample RR'!T45 -> 0 | I20: ='Sample RR'!V45 -> 0 | J20: ='Sample RR'!I45 -> 325 | K20: ='Sample RR'!Y45 -> 564 | L20: ='Sample RR'!AF46 -> 0 | M20: ='Sample RR'!AH45 -> 0 | N20: ='Sample RR'!AH47 -> 0 | O20: 0 | P20: 0 | Q20: 0 | R20: =SUM(L20:Q20) -> 0 | S20: ='Sample RR'!AK45-R20 -> 0
B21: ='Sample RR'!A46 -> 121A | C21: ='Sample RR'!C46 -> 4x4 | D21: ='Sample RR'!K46 -> Occupied | E21: N/A | F21: N/A | G21: ='Sample RR'!M46 -> McGuire, Chanquavion | H21: ='Sample RR'!T46 -> 44799 | I21: ='Sample RR'!V46 -> 45138 | J21: ='Sample RR'!I46 -> 325 | K21: ='Sample RR'!Y46 -> 564 | L21: ='Sample RR'!AF47 -> 544 | M21: ='Sample RR'!AH46 -> -45 | N21: ='Sample RR'!AH48 -> 15 | O21: 0 | P21: 0 | Q21: 0 | R21: =SUM(L21:Q21) -> 514 | S21: ='Sample RR'!AK46-R21 -> 0
B22: ='Sample RR'!A49 -> 121B | C22: ='Sample RR'!C49 -> 4x4 | D22: ='Sample RR'!K49 -> Occupied | E22: N/A | F22: N/A | G22: ='Sample RR'!M49 -> Webb, Dagan | H22: ='Sample RR'!T49 -> 44774 | I22: ='Sample RR'!V49 -> 45138 | J22: ='Sample RR'!I49 -> 325 | K22: ='Sample RR'!Y49 -> 564 | L22: ='Sample RR'!AF51 -> 544 | M22: ='Sample RR'!AH49 -> -45 | N22: ='Sample RR'!AH52 -> 15 | O22: ='Sample RR'!AH50 -> -249 | P22: 0 | Q22: 0 | R22: =SUM(L22:Q22) -> 265 | S22: ='Sample RR'!AK49-R22 -> 0
B23: ='Sample RR'!A53 -> 121C | C23: ='Sample RR'!C53 -> 4x4 | D23: ='Sample RR'!K53 -> Occupied | E23: N/A | F23: N/A | G23: ='Sample RR'!M53 -> Ikechukwu, Jeffrey | H23: ='Sample RR'!T53 -> 44774 | I23: ='Sample RR'!V53 -> 45138 | J23: ='Sample RR'!I53 -> 325 | K23: ='Sample RR'!Y53 -> 564 | L23: ='Sample RR'!AF54 -> 534 | M23: ='Sample RR'!AH53 -> -35 | N23: ='Sample RR'!AH55 -> 15 | O23: 0 | P23: 0 | Q23: 0 | R23: =SUM(L23:Q23) -> 514 | S23: ='Sample RR'!AK53-R23 -> 0
B24: ='Sample RR'!A56 -> 121D | C24: ='Sample RR'!C56 -> 4x4 | D24: ='Sample RR'!K56 -> Vacant | E24: N/A | F24: N/A | G24: ='Sample RR'!M56 -> VACANT | H24: ='Sample RR'!T56 -> 0 | I24: ='Sample RR'!V56 -> 0 | J24: ='Sample RR'!I56 -> 325 | K24: ='Sample RR'!Y56 -> 564 | L24: ='Sample RR'!AF57 -> 0 | M24: ='Sample RR'!AH56 -> 0 | N24: ='Sample RR'!AH58 -> 0 | O24: 0 | P24: 0 | Q24: 0 | R24: =SUM(L24:Q24) -> 0 | S24: ='Sample RR'!AK56-R24 -> 0
B25: ='Sample RR'!A57 -> 122A | C25: ='Sample RR'!C57 -> 4x4 | D25: ='Sample RR'!K57 -> Occupied | E25: N/A | F25: N/A | G25: ='Sample RR'!M57 -> Jones, Erica | H25: ='Sample RR'!T57 -> 44774 | I25: ='Sample RR'!V57 -> 45138 | J25: ='Sample RR'!I57 -> 325 | K25: ='Sample RR'!Y57 -> 564 | L25: ='Sample RR'!AF58 -> 519 | M25: ='Sample RR'!AH57 -> -25 | N25: ='Sample RR'!AH59 -> 15 | O25: 0 | P25: 0 | Q25: 0 | R25: =SUM(L25:Q25) -> 509 | S25: ='Sample RR'!AK57-R25 -> 0
B26: ='Sample RR'!A60 -> 122B | C26: ='Sample RR'!C60 -> 4x4 | D26: ='Sample RR'!K60 -> Vacant | E26: N/A | F26: N/A | G26: ='Sample RR'!M60 -> VACANT | H26: ='Sample RR'!T60 -> 0 | I26: ='Sample RR'!V60 -> 0 | J26: ='Sample RR'!I60 -> 325 | K26: ='Sample RR'!Y60 -> 564 | L26: ='Sample RR'!AF61 -> 0 | M26: ='Sample RR'!AH60 -> 0 | N26: ='Sample RR'!AH62 -> 0 | O26: 0 | P26: 0 | Q26: 0 | R26: =SUM(L26:Q26) -> 0 | S26: ='Sample RR'!AK60-R26 -> 0
B27: ='Sample RR'!A61 -> 122C | C27: ='Sample RR'!C61 -> 4x4 | D27: ='Sample RR'!K61 -> Occupied | E27: N/A | F27: N/A | G27: ='Sample RR'!M61 -> Calais, Tristan | H27: ='Sample RR'!T61 -> 44774 | I27: ='Sample RR'!V61 -> 45138 | J27: ='Sample RR'!I61 -> 325 | K27: ='Sample RR'!Y61 -> 564 | L27: ='Sample RR'!AF62 -> 544 | M27: ='Sample RR'!AH61 -> -45 | N27: ='Sample RR'!AH63 -> 15 | O27: 0 | P27: 0 | Q27: 0 | R27: =SUM(L27:Q27) -> 514 | S27: ='Sample RR'!AK61-R27 -> 0
B28: ='Sample RR'!A67 -> 122D | C28: ='Sample RR'!C67 -> 4x4 | D28: ='Sample RR'!K67 -> Occupied | E28: N/A | F28: N/A | G28: ='Sample RR'!M67 -> Hughes, Kierra | H28: ='Sample RR'!T67 -> 44805 | I28: ='Sample RR'!V67 -> 45138 | J28: ='Sample RR'!I67 -> 325 | K28: ='Sample RR'!Y67 -> 564 | L28: ='Sample RR'!AF68 -> 544 | M28: ='Sample RR'!AH67 -> -45 | N28: ='Sample RR'!AH69 -> 15 | O28: 0 | P28: 0 | Q28: 0 | R28: =SUM(L28:Q28) -> 514 | S28: ='Sample RR'!AK67-R28 -> 0
B29: ='Sample RR'!A70 -> 123A | C29: ='Sample RR'!C70 -> 4x4 | D29: ='Sample RR'!K70 -> Vacant | E29: N/A | F29: N/A | G29: ='Sample RR'!M70 -> VACANT | H29: ='Sample RR'!T70 -> 0 | I29: ='Sample RR'!V70 -> 0 | J29: ='Sample RR'!I70 -> 325 | K29: ='Sample RR'!Y70 -> 564 | L29: ='Sample RR'!AF71 -> 0 | M29: ='Sample RR'!AH70 -> 0 | N29: 0 | O29: 0 | P29: 0 | Q29: 0 | R29: =SUM(L29:Q29) -> 0 | S29: ='Sample RR'!AK70-R29 -> 0
B30: ='Sample RR'!A71 -> 123B | C30: ='Sample RR'!C71 -> 4x4 | D30: ='Sample RR'!K71 -> Vacant | E30: N/A | F30: N/A | G30: ='Sample RR'!M71 -> VACANT | H30: ='Sample RR'!T71 -> 0 | I30: ='Sample RR'!V71 -> 0 | J30: ='Sample RR'!I71 -> 325 | K30: ='Sample RR'!Y71 -> 564 | L30: ='Sample RR'!AF72 -> 0 | M30: ='Sample RR'!AH71 -> 0 | N30: ='Sample RR'!AH73 -> 0 | O30: 0 | P30: 0 | Q30: 0 | R30: =SUM(L30:Q30) -> 0 | S30: ='Sample RR'!AK71-R30 -> 0
B31: ='Sample RR'!A72 -> 123C | C31: ='Sample RR'!C72 -> 4x4 | D31: ='Sample RR'!K72 -> Occupied | E31: N/A | F31: N/A | G31: ='Sample RR'!M72 -> Valsin $, Jomard | H31: ='Sample RR'!T72 -> 44781 | I31: ='Sample RR'!V72 -> 45138 | J31: ='Sample RR'!I72 -> 325 | K31: ='Sample RR'!Y72 -> 564 | L31: ='Sample RR'!AF73 -> 549 | M31: ='Sample RR'!AH72 -> -50 | N31: ='Sample RR'!AH74 -> 15 | O31: 0 | P31: 0 | Q31: 0 | R31: =SUM(L31:Q31) -> 514 | S31: ='Sample RR'!AK72-R31 -> 0
B32: ='Sample RR'!A75 -> 123D | C32: ='Sample RR'!C75 -> 4x4 | D32: ='Sample RR'!K75 -> Vacant | E32: N/A | F32: N/A | G32: ='Sample RR'!M75 -> VACANT | H32: ='Sample RR'!T75 -> 0 | I32: ='Sample RR'!V75 -> 0 | J32: ='Sample RR'!I75 -> 325 | K32: ='Sample RR'!Y75 -> 564 | L32: ='Sample RR'!AF76 -> 0 | M32: ='Sample RR'!AH75 -> 0 | N32: ='Sample RR'!AH77 -> 0 | O32: 0 | P32: 0 | Q32: 0 | R32: =SUM(L32:Q32) -> 0 | S32: ='Sample RR'!AK75-R32 -> 0
B33: ='Sample RR'!A76 -> 124A | C33: ='Sample RR'!C76 -> 4x4 | D33: ='Sample RR'!K76 -> Occupied | E33: N/A | F33: N/A | G33: ='Sample RR'!M76 -> Ward, Hallie | H33: ='Sample RR'!T76 -> 44786 | I33: ='Sample RR'!V76 -> 45138 | J33: ='Sample RR'!I76 -> 325 | K33: ='Sample RR'!Y76 -> 564 | L33: ='Sample RR'!AF77 -> 544 | M33: ='Sample RR'!AH76 -> -45 | N33: ='Sample RR'!AH78 -> 15 | O33: 0 | P33: 0 | Q33: 0 | R33: =SUM(L33:Q33) -> 514 | S33: ='Sample RR'!AK76-R33 -> 0
B34: ='Sample RR'!A79 -> 124B | C34: ='Sample RR'!C79 -> 4x4 | D34: ='Sample RR'!K79 -> Occupied | E34: N/A | F34: N/A | G34: ='Sample RR'!M79 -> Tremie $, Elizabeth | H34: ='Sample RR'!T79 -> 44786 | I34: ='Sample RR'!V79 -> 45138 | J34: ='Sample RR'!I79 -> 325 | K34: ='Sample RR'!Y79 -> 564 | L34: ='Sample RR'!AF80 -> 544 | M34: ='Sample RR'!AH79 -> -45 | N34: ='Sample RR'!AH81 -> 15 | O34: 0 | P34: 0 | Q34: 0 | R34: =SUM(L34:Q34) -> 514 | S34: ='Sample RR'!AK79-R34 -> 0
B35: ='Sample RR'!A82 -> 124C | C35: ='Sample RR'!C82 -> 4x4 | D35: ='Sample RR'!K82 -> Occupied | E35: N/A | F35: N/A | G35: ='Sample RR'!M82 -> Lewis, Santana-Lin | H35: ='Sample RR'!T82 -> 44786 | I35: ='Sample RR'!V82 -> 45138 | J35: ='Sample RR'!I82 -> 325 | K35: ='Sample RR'!Y82 -> 564 | L35: ='Sample RR'!AF83 -> 519 | M35: ='Sample RR'!AH82 -> -25 | N35: ='Sample RR'!AH84 -> 15 | O35: 0 | P35: 0 | Q35: 0 | R35: =SUM(L35:Q35) -> 509 | S35: ='Sample RR'!AK82-R35 -> 0
B36: ='Sample RR'!A86 -> 124D | C36: ='Sample RR'!C86 -> 4x4 | D36: ='Sample RR'!K86 -> Vacant | E36: N/A | F36: N/A | G36: ='Sample RR'!M86 -> VACANT | H36: ='Sample RR'!T86 -> 0 | I36: ='Sample RR'!V86 -> 0 | J36: ='Sample RR'!I86 -> 325 | K36: ='Sample RR'!Y86 -> 564 | L36: ='Sample RR'!AF87 -> 0 | M36: ='Sample RR'!AH86 -> 0 | N36: ='Sample RR'!AH88 -> 0 | O36: 0 | P36: 0 | Q36: 0 | R36: =SUM(L36:Q36) -> 0 | S36: ='Sample RR'!AK86-R36 -> 0
B37: ='Sample RR'!A87 -> 131A | C37: ='Sample RR'!C87 -> 4x4 | D37: ='Sample RR'!K87 -> Vacant | E37: N/A | F37: N/A | G37: ='Sample RR'!M87 -> VACANT | H37: ='Sample RR'!T87 -> 0 | I37: ='Sample RR'!V87 -> 0 | J37: ='Sample RR'!I87 -> 325 | K37: ='Sample RR'!Y87 -> 564 | L37: ='Sample RR'!AF88 -> 0 | M37: ='Sample RR'!AH87 -> 0 | N37: ='Sample RR'!AH89 -> 0 | O37: 0 | P37: 0 | Q37: 0 | R37: =SUM(L37:Q37) -> 0 | S37: ='Sample RR'!AK87-R37 -> 0
B38: ='Sample RR'!A88 -> 131B | C38: ='Sample RR'!C88 -> 4x4 | D38: ='Sample RR'!K88 -> Vacant | E38: N/A | F38: N/A | G38: ='Sample RR'!M88 -> VACANT | H38: ='Sample RR'!T88 -> 0 | I38: ='Sample RR'!V88 -> 0 | J38: ='Sample RR'!I88 -> 325 | K38: ='Sample RR'!Y88 -> 564 | L38: ='Sample RR'!AF89 -> 0 | M38: ='Sample RR'!AH88 -> 0 | N38: ='Sample RR'!AH90 -> 0 | O38: 0 | P38: 0 | Q38: 0 | R38: =SUM(L38:Q38) -> 0 | S38: ='Sample RR'!AK88-R38 -> 0
B39: ='Sample RR'!A89 -> 131C | C39: ='Sample RR'!C89 -> 4x4 | D39: ='Sample RR'!K89 -> Vacant | E39: N/A | F39: N/A | G39: ='Sample RR'!M89 -> VACANT | H39: ='Sample RR'!T89 -> 0 | I39: ='Sample RR'!V89 -> 0 | J39: ='Sample RR'!I89 -> 325 | K39: ='Sample RR'!Y89 -> 564 | L39: ='Sample RR'!AF90 -> 0 | M39: ='Sample RR'!AH89 -> 0 | N39: ='Sample RR'!AH91 -> 0 | O39: 0 | P39: 0 | Q39: 0 | R39: =SUM(L39:Q39) -> 0 | S39: ='Sample RR'!AK89-R39 -> 0
B40: ='Sample RR'!A90 -> 131D | C40: ='Sample RR'!C90 -> 4x4 | D40: ='Sample RR'!K90 -> Vacant | E40: N/A | F40: N/A | G40: ='Sample RR'!M90 -> VACANT | H40: ='Sample RR'!T90 -> 0 | I40: ='Sample RR'!V90 -> 0 | J40: ='Sample RR'!I90 -> 325 | K40: ='Sample RR'!Y90 -> 564 | L40: ='Sample RR'!AF91 -> 0 | M40: ='Sample RR'!AH90 -> 0 | N40: ='Sample RR'!AH92 -> 0 | O40: 0 | P40: 0 | Q40: 0 | R40: =SUM(L40:Q40) -> 0 | S40: ='Sample RR'!AK90-R40 -> 0
B41: ='Sample RR'!A91 -> 132A | C41: ='Sample RR'!C91 -> 4x4 | D41: ='Sample RR'!K91 -> Vacant | E41: N/A | F41: N/A | G41: ='Sample RR'!M91 -> VACANT | H41: ='Sample RR'!T91 -> 0 | I41: ='Sample RR'!V91 -> 0 | J41: ='Sample RR'!I91 -> 325 | K41: ='Sample RR'!Y91 -> 564 | L41: ='Sample RR'!AF92 -> 0 | M41: ='Sample RR'!AH91 -> 0 | N41: 0 | O41: 0 | P41: 0 | Q41: 0 | R41: =SUM(L41:Q41) -> 0 | S41: ='Sample RR'!AK91-R41 -> 0
B42: ='Sample RR'!A92 -> 132B | C42: ='Sample RR'!C92 -> 4x4 | D42: ='Sample RR'!K92 -> Vacant | E42: N/A | F42: N/A | G42: ='Sample RR'!M92 -> VACANT | H42: ='Sample RR'!T92 -> 0 | I42: ='Sample RR'!V92 -> 0 | J42: ='Sample RR'!I92 -> 325 | K42: ='Sample RR'!Y92 -> 564 | L42: ='Sample RR'!AF93 -> 0 | M42: ='Sample RR'!AH92 -> 0 | N42: ='Sample RR'!AH94 -> 0 | O42: 0 | P42: 0 | Q42: 0 | R42: =SUM(L42:Q42) -> 0 | S42: ='Sample RR'!AK92-R42 -> 0

Sheet Actuals Balance Sheet
B2: Balance Sheet
B3: Month | D3: ='Income Statement - AM'!D3 -> 0 | E3: ='Income Statement - AM'!E3 -> 1 | F3: ='Income Statement - AM'!F3 -> 2 | G3: ='Income Statement - AM'!G3 -> 3 | H3: ='Income Statement - AM'!H3 -> 4 | I3: ='Income Statement - AM'!I3 -> 5 | J3: ='Income Statement - AM'!J3 -> 6 | K3: ='Income Statement - AM'!K3 -> 7 | ... DT3: ='Income Statement - AM'!DT3 -> 120
B4: Year | D4: ='Income Statement - AM'!D4 -> 0 | E4: ='Income Statement - AM'!E4 -> 1 | F4: ='Income Statement - AM'!F4 -> 1 | G4: ='Income Statement - AM'!G4 -> 1 | H4: ='Income Statement - AM'!H4 -> 1 | I4: ='Income Statement - AM'!I4 -> 1 | J4: ='Income Statement - AM'!J4 -> 1 | K4: ='Income Statement - AM'!K4 -> 1 | ... DT4: ='Income Statement - AM'!DT4 -> 10
B5: Date | D5: ='Income Statement - AM'!D5 -> 45346 | E5: ='Income Statement - AM'!E5 -> 45382 | F5: ='Income Statement - AM'!F5 -> 45412 | G5: ='Income Statement - AM'!G5 -> 45443 | H5: ='Income Statement - AM'!H5 -> 45473 | I5: ='Income Statement - AM'!I5 -> 45504 | J5: ='Income Statement - AM'!J5 -> 45535 | K5: ='Income Statement - AM'!K5 -> 45565 | ... DT5: ='Income Statement - AM'!DT5 -> 49003
B7: Assets
B9: Cash
B11: 100000 | C11: Operating Account | D11: 65663.67
B12: 100500 | C12: Revenue Account | D12: 4431.07
B13: 101000 | C13: Money Market Investment | D13: 2150
B14: 101500 | C14: Petty Cash | D14: 1000
B15: 102500 | C15: Security Deposits | D15: 1615
B16: 102600 | C16: Undeposited Funds | D16: 2249.7
B18: Total Cash | D18: =SUM(D11:D17) -> 77109.44 | E18: =SUM(E11:E17) -> 0 | F18: =SUM(F11:F17) -> 0 | G18: =SUM(G11:G17) -> 0 | H18: =SUM(H11:H17) -> 0 | I18: =SUM(I11:I17) -> 0 | J18: =SUM(J11:J17) -> 0 | K18: =SUM(K11:K17) -> 0 | ... DT18: =SUM(DT11:DT17) -> 0
B20: Escrows
B22: 103500 | C22: Replacement Reserve Fund | D22: 138000.02
B23: 104000 | C23: Tax Escrow Fund | D23: 11297.68
B24: 104500 | C24: Insurance Escrow Fund | D24: 25659.81
B27: Total Escrows | D27: =SUM(D22:D26) -> 174957.51 | E27: =SUM(E22:E26) -> 0 | F27: =SUM(F22:F26) -> 0 | G27: =SUM(G22:G26) -> 0 | H27: =SUM(H22:H26) -> 0 | I27: =SUM(I22:I26) -> 0 | J27: =SUM(J22:J26) -> 0 | K27: =SUM(K22:K26) -> 0 | ... DT27: =SUM(DT22:DT26) -> 0
B30: Accounts Receivable
B32: 110000 | C32: A/R Tenants | D32: 148813.13
B33: 110500 | C33: A/R ACLR | D33: 18627
B34: 111500 | C34: Other Receivables 1 | D34: 33126.5
B35: 112000 | C35: Allowance for Doubtful Accounts | D35: -57610.9
B38: Total Accounts Receivable | D38: =SUM(D32:D37) -> 142955.73 | E38: =SUM(E32:E37) -> 0 | F38: =SUM(F32:F37) -> 0 | G38: =SUM(G32:G37) -> 0 | H38: =SUM(H32:H37) -> 0 | I38: =SUM(I32:I37) -> 0 | J38: =SUM(J32:J37) -> 0 | K38: =SUM(K32:K37) -> 0 | ... DT38: =SUM(DT32:DT37) -> 0
B41: Prepaids
B43: 115000 | C43: Prepaid Insurance | D43: 63515.89
B44: 116000 | C44: Prepaid Other | D44: 3612.75
B48: Total Prepaids | D48: =SUM(D43:D47) -> 67128.64 | E48: =SUM(E43:E47) -> 0 | F48: =SUM(F43:F47) -> 0 | G48: =SUM(G43:G47) -> 0 | H48: =SUM(H43:H47) -> 0 | I48: =SUM(I43:I47) -> 0 | J48: =SUM(J43:J47) -> 0 | K48: =SUM(K43:K47) -> 0 | ... DT48: =SUM(DT43:DT47) -> 0
B50: Total Current Assets | D50: =D48++D38+D27+D18 -> 462151.32 | E50: =E48++E38+E27+E18 -> 0 | F50: =F48++F38+F27+F18 -> 0 | G50: =G48++G38+G27+G18 -> 0 | H50: =H48++H38+H27+H18 -> 0 | I50: =I48++I38+I27+I18 -> 0 | J50: =J48++J38+J27+J18 -> 0 | K50: =K48++K38+K27+K18 -> 0 | ... DT50: =DT48++DT38+DT27+DT18 -> 0
B52: Property, Plant & Equipment
B54: 120000 | C54: Land | D54: 1664000
B55: 120500 | C55: Land Improvements | D55: 261395.05
B56: 121000 | C56: Building | D56: 8736000
B57: 121500 | C57: Building Improvement | D57: 2068191.6
B58: 122000 | C58: Tenant Improvement | D58: 150063.37
B59: 123000 | C59: Furniture, Fixtures & Equipment | D59: 1028540.4
B60: 126000 | C60: Accumulated Depreciation | D60: -3094399.4
B62: Total Turnover | D62: =SUM(D54:D61) -> 10813791 | E62: =SUM(E54:E61) -> 0 | F62: =SUM(F54:F61) -> 0 | G62: =SUM(G54:G61) -> 0 | H62: =SUM(H54:H61) -> 0 | I62: =SUM(I54:I61) -> 0 | J62: =SUM(J54:J61) -> 0 | K62: =SUM(K54:K61) -> 0 | ... DT62: =SUM(DT54:DT61) -> 0
B65: Other Assets
B67: 126700 | C67: Accum Amortization - Cap Leas Comm | D67: 7350
B68: 130000 | C68: Deposits | D68: 25350
B69: 130500 | C69: Loan Fees | D69: 1428437.5
B70: 131000 | C70: Amortization Loan Fees | D70: -505546.97
B71: 132500 | C71: Intangible Assets | D71: 2945.25
B72: 132600 | C72: Amortization Intangible Assets | D72: -883.62
B74: Total Contract Services | D74: =SUM(D67:D73) -> 957652.16 | E74: =SUM(E67:E73) -> 0 | F74: =SUM(F67:F73) -> 0 | G74: =SUM(G67:G73) -> 0 | H74: =SUM(H67:H73) -> 0 | I74: =SUM(I67:I73) -> 0 | J74: =SUM(J67:J73) -> 0 | K74: =SUM(K67:K73) -> 0 | ... DT74: =SUM(DT67:DT73) -> 0
B76: Total Assets | D76: =D50+D62+D74 -> 12233594 | E76: =E50+E62+E74 -> 0 | F76: =F50+F62+F74 -> 0 | G76: =G50+G62+G74 -> 0 | H76: =H50+H62+H74 -> 0 | I76: =I50+I62+I74 -> 0 | J76: =J50+J62+J74 -> 0 | K76: =K50+K62+K74 -> 0 | ... DT76: =DT50+DT62+DT74 -> 0
B79: Liabilities
B81: Security Deposits
B83: 208000 | C83: Security Deposits | D83: 300
B85: Total Security Deposits | D85: =SUM(D83:D84) -> 300 | E85: =SUM(E83:E84) -> 0 | F85: =SUM(F83:F84) -> 0 | G85: =SUM(G83:G84) -> 0 | H85: =SUM(H83:H84) -> 0 | I85: =SUM(I83:I84) -> 0 | J85: =SUM(J83:J84) -> 0 | K85: =SUM(K83:K84) -> 0 | ... DT85: =SUM(DT83:DT84) -> 0
B87: Deferred Revenue Tenant
B89: 208500 | C89: Deferred Revenue Tenant | D89: 1099
B92: Total Deferred Revenue | D92: =SUM(D89:D91) -> 1099 | E92: =SUM(E89:E91) -> 0 | F92: =SUM(F89:F91) -> 0 | G92: =SUM(G89:G91) -> 0 | H92: =SUM(H89:H91) -> 0 | I92: =SUM(I89:I91) -> 0 | J92: =SUM(J89:J91) -> 0 | K92: =SUM(K89:K91) -> 0 | ... DT92: =SUM(DT89:DT91) -> 0
B95: Tenant Prepaid Rent
B97: 209000 | C97: Tenant Prepaid Rent | D97: 18795.32
B100: Total Prepaid Rent | D100: =SUM(D97:D99) -> 18795.32 | E100: =SUM(E97:E99) -> 0 | F100: =SUM(F97:F99) -> 0 | G100: =SUM(G97:G99) -> 0 | H100: =SUM(H97:H99) -> 0 | I100: =SUM(I97:I99) -> 0 | J100: =SUM(J97:J99) -> 0 | K100: =SUM(K97:K99) -> 0 | ... DT100: =SUM(DT97:DT99) -> 0
B103: Accounts Payable
B105: 209500 | C105: A/P Trade | D105: 61238.5
B108: Total Accounts Payable | D108: =SUM(D105:D107) -> 61238.5 | E108: =SUM(E105:E107) -> 0 | F108: =SUM(F105:F107) -> 0 | G108: =SUM(G105:G107) -> 0 | H108: =SUM(H105:H107) -> 0 | I108: =SUM(I105:I107) -> 0 | J108: =SUM(J105:J107) -> 0 | K108: =SUM(K105:K107) -> 0 | ... DT108: =SUM(DT105:DT107) -> 0
B110: Accounts Payable
B112: 203000 | C112: Management Fees | D112: 7500
B113: 210000 | C113: Payroll and Related | D113: 7394.52
B114: 210500 | C114: Accrued Interest | D114: 55811.92
B115: 210600 | C115: Accrued Property Taxes | D115: 3647.69
B116: 212000 | C116: Accrued Other | D116: 82312.48
B121: Total Accounts Payable | D121: =SUM(D112:D120) -> 156666.61 | E121: =SUM(E112:E120) -> 0 | F121: =SUM(F112:F120) -> 0 | G121: =SUM(G112:G120) -> 0 | H121: =SUM(H112:H120) -> 0 | I121: =SUM(I112:I120) -> 0 | J121: =SUM(J112:J120) -> 0 | K121: =SUM(K112:K120) -> 0 | ... DT121: =SUM(DT112:DT120) -> 0
B123: Other Current Liabilities
B125: 203500 | C125: Other Current Liabilities 1 | D125: 4923.51
B126: 203600 | C126: Other Current Liabilities 2 | D126: 14727.1
B127: 205000 | C127: Unclaimed Property | D127: 31.42
B130: Total Other Current Liabilities | D130: =SUM(D125:D129) -> 19682.03 | E130: =SUM(E125:E129) -> 0 | F130: =SUM(F125:F129) -> 0 | G130: =SUM(G125:G129) -> 0 | H130: =SUM(H125:H129) -> 0 | I130: =SUM(I125:I129) -> 0 | J130: =SUM(J125:J129) -> 0 | K130: =SUM(K125:K129) -> 0 | ... DT130: =SUM(DT125:DT129) -> 0
B132: Total Current Liabilities | D132: =D130+D121+D108+D100+D92+D85 -> 257781.46 | E132: =E130+E121+E108+E100+E92+E85 -> 0 | F132: =F130+F121+F108+F100+F92+F85 -> 0 | G132: =G130+G121+G108+G100+G92+G85 -> 0 | H132: =H130+H121+H108+H100+H92+H85 -> 0 | I132: =I130+I121+I108+I100+I92+I85 -> 0 | J132: =J130+J121+J108+J100+J92+J85 -> 0 | K132: =K130+K121+K108+K100+K92+K85 -> 0 | ... DT132: =DT130+DT121+DT108+DT100+DT92+DT85 -> 0
B136: Long Term Liabilities
B138: 221500 | C138: Mortgage Payable LT | D138: 9250000
B146: Total Long Term Liabilities | D146: =SUM(D138:D145) -> 9250000 | E146: =SUM(E138:E145) -> 0 | F146: =SUM(F138:F145) -> 0 | G146: =SUM(G138:G145) -> 0 | H146: =SUM(H138:H145) -> 0 | I146: =SUM(I138:I145) -> 0 | J146: =SUM(J138:J145) -> 0 | K146: =SUM(K138:K145) -> 0 | ... DT146: =SUM(DT138:DT145) -> 0
B148: Total Liabilities | D148: =D132+D146 -> 9507781.5 | E148: =E132+E146 -> 0 | F148: =F132+F146 -> 0 | G148: =G132+G146 -> 0 | H148: =H132+H146 -> 0 | I148: =I132+I146 -> 0 | J148: =J132+J146 -> 0 | K148: =K132+K146 -> 0 | ... DT148: =DT132+DT146 -> 0
B152: Equity
B154: 300000 | C154: Owner Contributions | D154: 23553332
B155: 300600 | C155: Owner Distributions | D155: -16626168
B156: 302000 | C156: Retained Earnings | D156: -4201350.3
B161: Total Equity | D161: =SUM(D154:D160) -> 2725813 | E161: =SUM(E154:E160) -> 0 | F161: =SUM(F154:F160) -> 0 | G161: =SUM(G154:G160) -> 0 | H161: =SUM(H154:H160) -> 0 | I161: =SUM(I154:I160) -> 0 | J161: =SUM(J154:J160) -> 0 | K161: =SUM(K154:K160) -> 0 | ... DT161: =SUM(DT154:DT160) -> 0
B163: Total Liabilities and Equity | D163: =D161+D148 -> 12233594 | E163: =E161+E148 -> 0 | F163: =F161+F148 -> 0 | G163: =G161+G148 -> 0 | H163: =H161+H148 -> 0 | I163: =I161+I148 -> 0 | J163: =J161+J148 -> 0 | K163: =K161+K148 -> 0 | ... DT163: =DT161+DT148 -> 0

Sheet AI Insights Tab
C2: AI Recommendations | D2: Impact to Returns
B3: Rent | C3: 1 bedroom rents are $100 below the competitive set. Increase rents by $100 on 1 bedroom units. | D3: + 1.5% IRR / +0.7x MOIC
B4: Concessions | C4: Offer an additional 0.5 months of concessions could save $1,000,000 of interest reserve expense if the leasing velocity increases by 5 units per month. | D4: + 1.5% IRR / +0.7x MOIC
B5: Other Income | C5: Charge an additional [$x] for other income | D5: + 1.5% IRR / +0.7x MOIC
B6: Controllable Expenses
B7: Property Taxes
B8: Financing | C8: The property could qualify for a $100m refinancing, distriubtiong $20 million to the equity in Month 48. | D8: + 1.5% IRR / +0.7x MOIC
B9: Sale | C9: The property is stabilizing 6 months in advance of the current assumed sale. Selling [x] months early could increase the IRR / MOIC. | D9: + 1.5% IRR / +0.7x MOIC

Sheet COMPLETED DEAL OUPTUTS-->

Sheet Deal Landing Dashboard
B2: =_xlfn.CONCAT('AIRR Input Tab'!D17," - ",D11," - ",D14) -> West Village Complexes - Multifamily - New York
C9: Deal Summary | F9: Capital Structure
G10: Name
C11: Property Type | D11: Multifamily | F11: Senior Lender | G11: ='AIRR Input Tab'!D12 -> West Bank
C12: Units / SF | D12: ='Unit Mix '!E84 -> 145 | F12: Senior Lender LTC | G12: ='AIRR Input Tab'!D42 -> 0.6
C13: Year Build / Renovated | D13: =CONCATENATE('AIRR Input Tab'!D24," / ",'AIRR Input Tab'!D25) -> 2025 / N/A | F13: Mezzanine / Preferred Equity Lender | G13: ='AIRR Input Tab'!D13 -> NA
C14: Market | D14: ='AIRR Input Tab'!D21 -> New York | F14: Mezzanine / Preferred LTC
C15: Submarket | D15: ='AIRR Input Tab'!D22 -> West Village | F15: GP Partner | G15: ='AIRR Input Tab'!D11 -> Ace
C16: Current Status | D16: ='AIRR Input Tab'!H11 -> Development | F16: GP Ownership % | G16: ='AIRR Input Tab'!L21 -> 0.05
C18: Investment Details | F18: Deal Team
G19: Name
C20: Closing Date | D20: ='PERPETUITY MIDDLEMAN INPUT TAB'!#REF! -> #REF! | F20: Acquistions - Lead | G20: Maya Patel
C21: Fund | D21: ='AIRR Input Tab'!D9 -> Fund 1 | F21: Acquistions - Support
C22: Investment Type | D22: ='AIRR Input Tab'!H13 -> LP Equity | F22: Asset Management - Lead | G22: Sophia Nguyen
C23: Ownership % | D23: ='AIRR Input Tab'!K21 -> 0.95 | F23: Asset Management - Support | G23: Carlos Ramirez
C24: Investment Amount | D24: ='AIRR Model Summary'!J38 -> 14107573 | F24: Accountant - Lead
C25: Total Capitalization | D25: ='AIRR Model Summary'!J53 -> 37125192 | F25: Accountant - Support | G25: Layla Hassan
B48: Returns
B50: Investment
B51: IRR
B52: MOIC
B53: Net Profit
B54: Exit / Unit

Sheet Performance Dashboard
B3: ='Deal Landing Dashboard'!$B$2 -> West Village Complexes - Multifamily - New York
G6: Budget | L6: Key Dates
H7: Closing | I7: AIRR | J7: Overruns | M7: Underwriting | N7: AIRR | O7: Variance
G8: Land | H8: =Budget!C13 -> 10000000 | I8: =Budget!E13 -> 10000000 | J8: =I8-H8 -> 0 | L8: ='AIRR Model Summary'!B32 -> Land and JV Closing | M8: ='AIRR Model Summary'!D32 -> 0 | N8: 0 | O8: =N8-M8 -> 0
G9: Hard Costs | H9: =Budget!C20 -> 19350000 | I9: =Budget!E20 -> 19350000 | J9: =I9-H9 -> 0 | L9: ='AIRR Model Summary'!B33 -> Construction Start | M9: ='AIRR Model Summary'!D33 -> 0 | N9: 0 | O9: =N9-M9 -> 0
G10: Softs Costs | H10: =Budget!C36 -> 4000347.1 | I10: =Budget!E36 -> 4000347.1 | J10: =I10-H10 -> 0 | L10: ='AIRR Model Summary'!B34 -> Construction Completion | M10: ='AIRR Model Summary'!D34 -> 25 | N10: 27 | O10: =N10-M10 -> 2
G11: Interest and Operating Reserves | H11: =Budget!C54 -> 1228882 | I11: =Budget!E54 -> 3566117.2 | J11: =I11-H11 -> 2337235.2 | L11: ='AIRR Model Summary'!B35 -> First Units Delivered (Opex Starts) | M11: ='AIRR Model Summary'!D35 -> 14 | N11: 29 | O11: =N11-M11 -> 15
G12: Total Uses | H12: =SUM(H8:H11) -> 34579229 | I12: =SUM(I8:I11) -> 36916464 | J12: =I12-H12 -> 2337235.2 | L12: ='AIRR Model Summary'!B36 -> Absorption Start | M12: ='AIRR Model Summary'!D36 -> 14 | N12: 34 | O12: =N12-M12 -> 20
L13: ='AIRR Model Summary'!B37 -> NOI Breakeven | M13: ='AIRR Model Summary'!D37 -> 36 | N13: 38 | O13: =N13-M13 -> 2
G14: Senior Loan | H14: =Budget!C61 -> 20872774 | I14: =Budget!E61 -> 20872774 | J14: =I14-H14 -> 0 | L14: ='AIRR Model Summary'!B38 -> Senior Debt Service Breakeven | M14: ='AIRR Model Summary'!D38 -> 40 | N14: 42 | O14: =N14-M14 -> 2
G15: Preferred Equity | H15: =Budget!C62 -> 0 | I15: =Budget!E62 -> 0 | J15: =I15-H15 -> 0 | L15: ='AIRR Model Summary'!B39 -> Stabilization | M15: ='AIRR Model Summary'!D39 -> 46 | N15: 48 | O15: =N15-M15 -> 2
G16: LP - Investar Equity | H16: =Budget!C63 -> 13219424 | I16: =Budget!E63+Budget!E68 -> 13219424 | J16: =I16-H16 -> 0 | L16: Loan Maturity | M16: =M17 -> 96 | N16: =M16 -> 96 | O16: =N16-M16 -> 0
G17: GP - Ace Development Equity | H17: =Budget!C64 -> 695759.14 | I17: =Budget!E64+Budget!D69 -> 695759.14 | J17: =I17-H17 -> 0 | L17: ='AIRR Model Summary'!B40 -> Sale Month | M17: ='AIRR Model Summary'!D40 -> 96 | N17: 52 | O17: =N17-M17 -> -44
B18: Senior Loan | G18: Total Sources | H18: =SUM(H14:H17) -> 34787957 | I18: =SUM(I14:I17) -> 34787957 | J18: =I18-H18 -> 0
L19: Exit
B20: Lender | C20: Bank OZK | D20: Maturity Date | E20: 45659 | G20: Net Operating Income | I20: As of | J20: Stabilized | M20: Underwriting | N20: AIRR | O20: Variance
B21: Loan Amount | C21: =I14 -> 20872774 | D21: Debt Yield at Maturity | E21: =C24 -> 0.08 | H21: Underwriting | I21: AIRR | J21: Variance | L21: Exit Date | M21: =M17 -> 96 | N21: =N17 -> 52 | O21: =O17 -> -44
G22: Occupancy | H22: 0.8 | I22: 0.85 | J22: =I22-H22 -> 0.05 | L22: NOI | M22: 12000000 | N22: 12500000 | O22: =N22-M22 -> 500000
B23: Performance Tests | C23: AIRR Model | D23: Test | E23: Pass / Fail | G23: Rents | H23: 2500 | I23: 2750 | J23: =I23-H23 -> 250 | L23: Cap Rate | M23: 0.055 | N23: 0.0525 | O23: =N23-M23 -> -0.0025
B24: Debt Yield | C24: 0.08 | D24: 0.07 | E24: Pass | G24: Concessions | H24: 1 | I24: 1 | J24: =I24-H24 -> 0 | L24: Sale Price | M24: 225000000 | N24: ='AIRR Model Summary'!E53 -> 36624767 | O24: =N24-M24 -> -1.8837523e+08
B25: DSCR | C25: 1.5 | D25: 1.25 | E25: Pass | G25: Net Effective Rents | H25: 2200 | I25: 2500 | J25: =I25-H25 -> 300 | L25: Sale Price / Unit | M25: =M24/'AIRR Model Summary'!$I$13 -> 1551724.1 | N25: =N24/'AIRR Model Summary'!$I$13 -> 252584.6 | O25: =N25-M25 -> -1299139.5
G26: Other Income (Unit / Month) | H26: 125 | I26: 175 | J26: =I26-H26 -> 50
B27: Refinance | G27: Total Effective Income | H27: 20500000 | I27: 23500000 | J27: =I27-H27 -> 3000000 | L27: Returns
B28: Refinance Surplus / Shortfall | J28: =I28-H28 -> 0 | M28: Underwriting | N28: AIRR | O28: Variance
G29: Controllable Expenses | H29: 2500000 | I29: 4000000 | J29: =I29-H29 -> 1500000 | L29: Investment | M29: ='AIRR Model Summary'!K68 -> 14107573 | N29: =M29+J16 -> 14107573 | O29: =N29-M29 -> 0
B30: Guarantees | C30: Risk? | D30: $ Risk | E30: Responsible | G30: Non-Controllable Expenses | H30: 6000000 | I30: 7000000 | J30: =I30-H30 -> 1000000 | L30: IRR | M30: 0.2 | N30: ='AIRR Model Summary'!K69 -> 0.046859661 | O30: =N30-M30 -> -0.15314034
B31: Interest and Carry | C31: Yes | D31: =J11 -> 2337235.2 | E31: GP | G31: Total Expenses | H31: =SUM(H29:H30) -> 8500000 | I31: =SUM(I29:I30) -> 11000000 | J31: =I31-H31 -> 2500000 | L31: MOIC | M31: 2 | N31: ='AIRR Model Summary'!K70 -> 1.440323 | O31: =N31-M31 -> -0.55967697
B32: Hard Cost / Completion | C32: Yes | D32: =J9+J10 -> 0 | E32: GP | J32: =I32-H32 -> 0 | L32: Net Profit | M32: ='AIRR Model Summary'!K71 -> 6211890.8 | N32: ='AIRR Model Summary'!K71-J16 -> 6211890.8 | O32: =N32-M32 -> 0
B33: Repayment | C33: Unlikely | D33: 0 | E33: GP | G33: NOI | H33: =H27-H31 -> 12000000 | I33: =I27-I31 -> 12500000 | J33: =I33-H33 -> 500000 | L33: Exit / Unit | M33: =M25 -> 1551724.1 | N33: =N25 -> 252584.6 | O33: =N33-M33 -> -1299139.5

Sheet AIRR Model Summary_v1
B2: ='Deal Landing Dashboard'!B2 -> West Village Complexes - Multifamily - New York
B5: Property Details | F5: Unit Mix | M5: Pro Forma
B7: Deal Name | D7: West Village Complexes | F7: Unit Type | H7: # of Units | I7: SF | J7: Rent | K7: Rent PSF | M7: Face Rents | N7: ='Income Statement - AM'!DW24 -> 1717.7779 | O7: ='Income Statement - AM'!DX24 -> 1756.9053 | P7: ='Income Statement - AM'!DY24 -> 1798.7185 | Q7: ='Income Statement - AM'!DZ24 -> 1843.3656 | R7: ='Income Statement - AM'!EA24 -> 1891.0073 | S7: ='Income Statement - AM'!EB24 -> 1913.5986 | T7: ='Income Statement - AM'!EC24 -> 1913.5986 | U7: ='Income Statement - AM'!ED24 -> 1913.5986 | ... W7: ='Income Statement - AM'!EF24 -> 1913.5986
B8: Number of Units | D8: ='Unit Mix '!E84 -> 145 | F8: Studio | H8: 50 | I8: 600 | J8: 1425 | K8: =J8/I8 -> 2.375 | M8: Effective Rents | N8: ='Income Statement - AM'!DW32 -> 0 | O8: ='Income Statement - AM'!DX32 -> 1490.027 | P8: ='Income Statement - AM'!DY32 -> 2474.0368 | Q8: ='Income Statement - AM'!DZ32 -> 1691.5041 | R8: ='Income Statement - AM'!EA32 -> 1735.2925 | S8: ='Income Statement - AM'!EB32 -> 1754.132 | T8: ='Income Statement - AM'!EC32 -> 1754.132 | U8: ='Income Statement - AM'!ED32 -> 1754.132 | ... W8: ='Income Statement - AM'!EF32 -> 1754.132
B9: Property Type | D9: Multifamily | F9: 1BR/1BA | H9: 250 | I9: 600 | J9: 1425 | K9: =J9/I9 -> 2.375 | M9: Occupancy | N9: ='Income Statement - AM'!DW15 -> 0 | O9: ='Income Statement - AM'!DX15 -> 1 | P9: ='Income Statement - AM'!DY15 -> 1 | Q9: ='Income Statement - AM'!DZ15 -> 1 | R9: ='Income Statement - AM'!EA15 -> 1 | S9: ='Income Statement - AM'!EB15 -> 1 | T9: ='Income Statement - AM'!EC15 -> 1 | U9: ='Income Statement - AM'!ED15 -> 1 | ... W9: ='Income Statement - AM'!EF15 -> 1
B10: Construction Type | D10: Type 1 | F10: 2BR/1BA | H10: 225 | I10: 725 | J10: 1600 | K10: =J10/I10 -> 2.2068966 | M10: Rent Growth | N10: 0.05 | O10: 0.05 | P10: 0.05 | Q10: 0.05 | R10: 0.05
B11: Stories | D11: Midrise | F11: 2BR/2BA | H11: 25 | I11: 875 | J11: 1875 | K11: =J11/I11 -> 2.1428571 | S11: =R13+1 -> 6 | T11: =S11+1 -> 7 | U11: =T11+1 -> 8 | V11: =U11+1 -> 9 | W11: =V11+1 -> 10
B12: Number of Buildings | D12: 2 | H12: 0 | I12: 1025 | J12: 2100 | K12: =J12/I12 -> 2.0487805 | M12: Actual / Forecast | N12: ACTUAL | O12: ACTUAL | P12: ACTUAL | Q12: FORECAST | R12: FORECAST | S12: ='Income Statement - AM'!EB34 -> 3329661.5 | T12: ='Income Statement - AM'!EC34 -> 3329661.5 | U12: ='Income Statement - AM'!ED34 -> 3329661.5 | V12: ='Income Statement - AM'!EE34 -> 3329661.5 | W12: ='Income Statement - AM'!EF34 -> 3329661.5
B13: Gross Square Feet | D13: ='AIRR Input Tab'!D29 -> 450000 | F13: Total / Average | H13: =SUM(H8:H12) -> 550 | I13: =SUMPRODUCT(H8:H12,I8:I12)/H13 -> 663.63636 | J13: =SUMPRODUCT(H8:H12,J8:J12)/H13 -> 1517.0455 | K13: =J13/I13 -> 2.2859589 | M13: Year | N13: 1 | O13: =N13+1 -> 2 | P13: =O13+1 -> 3 | Q13: =P13+1 -> 4 | R13: =Q13+1 -> 5 | S13: ='Income Statement - AM'!EB35 -> 0 | T13: ='Income Statement - AM'!EC35 -> 0 | U13: ='Income Statement - AM'!ED35 -> 0 | V13: ='Income Statement - AM'!EE35 -> 0 | W13: ='Income Statement - AM'!EF35 -> 0
B14: Net Rentable SF | D14: =I13*H13 -> 365000 | M14: Date | N14: =D32 -> 45346 | O14: =EOMONTH(N14,12) -> 45716 | P14: =EOMONTH(O14,12) -> 46081 | Q14: =EOMONTH(P14,12) -> 46446 | R14: =EOMONTH(Q14,12) -> 46812 | S14: =SUM(S12:S13) -> 3329661.5 | T14: =SUM(T12:T13) -> 3329661.5 | U14: =SUM(U12:U13) -> 3329661.5 | V14: =SUM(V12:V13) -> 3329661.5 | W14: =SUM(W12:W13) -> 3329661.5
B15: Acres | D15: ='AIRR Input Tab'!D27 -> 2 | F15: General Asumptions | M15: Gross Potential Rent | N15: ='Income Statement - AM'!DW34 -> 2988933.6 | O15: ='Income Statement - AM'!DX34 -> 3057015.2 | P15: ='Income Statement - AM'!DY34 -> 3129770.1 | Q15: ='Income Statement - AM'!DZ34 -> 3207456.2 | R15: ='Income Statement - AM'!EA34 -> 3290352.8 | S15: ='Income Statement - AM'!EB55 -> 167760.7 | T15: ='Income Statement - AM'!EC55 -> 167760.7 | U15: ='Income Statement - AM'!ED55 -> 167760.7 | V15: ='Income Statement - AM'!EE55 -> 167760.7 | W15: ='Income Statement - AM'!EF55 -> 167760.7
B16: Units / Acre | D16: =H13/D15 -> 275 | M16: Loss to Lease | N16: ='Income Statement - AM'!DW35 -> 0 | O16: ='Income Statement - AM'!DX35 -> 0 | P16: ='Income Statement - AM'!DY35 -> 0 | Q16: ='Income Statement - AM'!DZ35 -> 0 | R16: ='Income Statement - AM'!EA35 -> 0 | S16: =S15+S14 -> 3497422.2 | T16: =T15+T14 -> 3497422.2 | U16: =U15+U14 -> 3497422.2 | V16: =V15+V14 -> 3497422.2 | W16: =W15+W14 -> 3497422.2
B17: Parking Spaces | D17: ='AIRR Input Tab'!D30 -> 200 | F17: Vacancy | H17: ='PERPETUITY MIDDLEMAN INPUT TAB'!#REF! -> #REF! | I17: Concessions - Lease Up (New) | K17: ='PERPETUITY MIDDLEMAN INPUT TAB'!#REF! -> #REF! | M17: Gross Potential Rent | N17: =SUM(N15:N16) -> 2988933.6 | O17: =SUM(O15:O16) -> 3057015.2 | P17: =SUM(P15:P16) -> 3129770.1 | Q17: =SUM(Q15:Q16) -> 3207456.2 | R17: =SUM(R15:R16) -> 3290352.8 | S17: ='Income Statement - AM'!EB59 -> -104922.67 | T17: ='Income Statement - AM'!EC59 -> -104922.67 | U17: ='Income Statement - AM'!ED59 -> -104922.67 | V17: ='Income Statement - AM'!EE59 -> -104922.67 | W17: ='Income Statement - AM'!EF59 -> -104922.67
F18: Loss to Lease | H18: ='PERPETUITY MIDDLEMAN INPUT TAB'!#REF! -> #REF! | I18: Concessions - Lease Up (Renewal) | K18: ='PERPETUITY MIDDLEMAN INPUT TAB'!#REF! -> #REF! | M18: Other Income | N18: ='Income Statement - AM'!DW55 -> 146788.47 | O18: ='Income Statement - AM'!DX55 -> 151253.18 | P18: ='Income Statement - AM'!DY55 -> 155853.69 | Q18: ='Income Statement - AM'!DZ55 -> 160594.13 | R18: ='Income Statement - AM'!EA55 -> 165478.76 | S18: ='Income Statement - AM'!EB60 -> 0 | T18: ='Income Statement - AM'!EC60 -> 0 | U18: ='Income Statement - AM'!ED60 -> 0 | V18: ='Income Statement - AM'!EE60 -> 0 | W18: ='Income Statement - AM'!EF60 -> 0
B19: Senior Loan Terms | F19: Bad Debt | H19: ='PERPETUITY MIDDLEMAN INPUT TAB'!#REF! -> #REF! | I19: Concessions - Stabilized (New) | K19: ='PERPETUITY MIDDLEMAN INPUT TAB'!#REF! -> #REF! | M19: Net Potential Income | N19: =N18+N17 -> 3135722 | O19: =O18+O17 -> 3208268.4 | P19: =P18+P17 -> 3285623.8 | Q19: =Q18+Q17 -> 3368050.4 | R19: =R18+R17 -> 3455831.5 | S19: ='Income Statement - AM'!EB61 -> 0 | T19: ='Income Statement - AM'!EC61 -> 0 | U19: ='Income Statement - AM'!ED61 -> 0 | V19: ='Income Statement - AM'!EE61 -> 0 | W19: ='Income Statement - AM'!EF61 -> 0
F20: Model Units | H20: ='PERPETUITY MIDDLEMAN INPUT TAB'!#REF! -> #REF! | I20: Concessions - Stabilized (Renewal) | K20: ='PERPETUITY MIDDLEMAN INPUT TAB'!#REF! -> #REF! | M20: Vacancy | N20: ='Income Statement - AM'!DW59 -> -3135722 | O20: ='Income Statement - AM'!DX59 -> -1605490.3 | P20: ='Income Statement - AM'!DY59 -> -98568.714 | Q20: ='Income Statement - AM'!DZ59 -> -101041.51 | R20: ='Income Statement - AM'!EA59 -> -103674.95 | S20: ='Income Statement - AM'!EB62 -> 0 | T20: ='Income Statement - AM'!EC62 -> 0 | U20: ='Income Statement - AM'!ED62 -> 0 | V20: ='Income Statement - AM'!EE62 -> 0 | W20: ='Income Statement - AM'!EF62 -> 0
B21: Loan to Cost % | D21: ='AIRR Input Tab'!D42 -> 0.6 | F21: Leased Units Per Month | H21: ='PERPETUITY MIDDLEMAN INPUT TAB'!#REF! -> #REF! | M21: Model Units | N21: ='Income Statement - AM'!DW60 -> 0 | O21: ='Income Statement - AM'!DX60 -> 0 | P21: ='Income Statement - AM'!DY60 -> 0 | Q21: ='Income Statement - AM'!DZ60 -> 0 | R21: ='Income Statement - AM'!EA60 -> 0 | S21: ='Income Statement - AM'!EB63 -> 0 | T21: ='Income Statement - AM'!EC63 -> 0 | U21: ='Income Statement - AM'!ED63 -> 0 | V21: ='Income Statement - AM'!EE63 -> 0 | W21: ='Income Statement - AM'!EF63 -> 0
B22: Initial Term | D22: ='AIRR Input Tab'!D50 -> 48 | F22: Renewal Probability | H22: ='PERPETUITY MIDDLEMAN INPUT TAB'!#REF! -> #REF! | M22: Concessions - Lease Up (New) | N22: ='Income Statement - AM'!DW61 -> 0 | O22: ='Income Statement - AM'!DX61 -> -231590.51 | P22: ='Income Statement - AM'!DY61 -> 0 | Q22: ='Income Statement - AM'!DZ61 -> 0 | R22: ='Income Statement - AM'!EA61 -> 0 | S22: ='Income Statement - AM'!EB64 -> 0 | T22: ='Income Statement - AM'!EC64 -> 0 | U22: ='Income Statement - AM'!ED64 -> 0 | V22: ='Income Statement - AM'!EE64 -> 0 | W22: ='Income Statement - AM'!EF64 -> 0
B23: Interest Type - Fixed/Floating | D23: ='AIRR Input Tab'!D43 -> Floating | F23: Lease Term | H23: ='PERPETUITY MIDDLEMAN INPUT TAB'!#REF! -> #REF! | M23: Concessions - Lease Up (Renewal) | N23: ='Income Statement - AM'!DW62 -> 0 | O23: ='Income Statement - AM'!DX62 -> 0 | P23: ='Income Statement - AM'!DY62 -> 0 | Q23: ='Income Statement - AM'!DZ62 -> 0 | R23: ='Income Statement - AM'!EA62 -> 0 | S23: ='Income Statement - AM'!EB65 -> -33924.995 | T23: ='Income Statement - AM'!EC65 -> -33924.995 | U23: ='Income Statement - AM'!ED65 -> -33924.995 | V23: ='Income Statement - AM'!EE65 -> -33924.995 | W23: ='Income Statement - AM'!EF65 -> -33924.995 | AA23: Absorption Start Month
B24: SOFR Spread | D24: ='AIRR Input Tab'!D45 -> 0.025 | M24: Concessions - Stabilized (New) | N24: ='Income Statement - AM'!DW63 -> 0 | O24: ='Income Statement - AM'!DX63 -> 0 | P24: ='Income Statement - AM'!DY63 -> 0 | Q24: ='Income Statement - AM'!DZ63 -> 0 | R24: ='Income Statement - AM'!EA63 -> 0 | S24: =SUM(S16:S23) -> 3358574.6 | T24: =SUM(T16:T23) -> 3358574.6 | U24: =SUM(U16:U23) -> 3358574.6 | V24: =SUM(V16:V23) -> 3358574.6 | W24: =SUM(W16:W23) -> 3358574.6 | AA24: Absorption Start Date
B25: SOFR Floor | D25: ='AIRR Input Tab'!D46 -> 0 | F25: Budget | M25: Concessions - Stabilized (Renewal) | N25: ='Income Statement - AM'!DW64 -> 0 | O25: ='Income Statement - AM'!DX64 -> 0 | P25: ='Income Statement - AM'!DY64 -> 0 | Q25: ='Income Statement - AM'!DZ64 -> 0 | R25: ='Income Statement - AM'!EA64 -> 0 | S25: ='Income Statement - AM'!EB67 -> 0 | T25: ='Income Statement - AM'!EC67 -> 0 | U25: ='Income Statement - AM'!ED67 -> 0 | V25: ='Income Statement - AM'!EE67 -> 0 | W25: ='Income Statement - AM'!EF67 -> 0
B26: Interest Only Period | D26: ='AIRR Input Tab'!D48 -> 36 | M26: Bad Debt | N26: ='Income Statement - AM'!DW65 -> 0 | O26: ='Income Statement - AM'!DX65 -> -13711.876 | P26: ='Income Statement - AM'!DY65 -> -31870.551 | Q26: ='Income Statement - AM'!DZ65 -> -32670.089 | R26: ='Income Statement - AM'!EA65 -> -33521.566 | S26: =S25+S24 -> 3358574.6 | T26: =T25+T24 -> 3358574.6 | U26: =U25+U24 -> 3358574.6 | V26: =V25+V24 -> 3358574.6 | W26: =W25+W24 -> 3358574.6
B27: Amortization Schedule | D27: ='AIRR Input Tab'!D49 -> 30 | F27: Sources | I27: Closing Budget | J27: % | K27: Per Unit | M27: Effective Gross Income (Multi) | N27: =SUM(N19:N26) -> -4.6566129e-10 | O27: =SUM(O19:O26) -> 1357475.7 | P27: =SUM(P19:P26) -> 3155184.5 | Q27: =SUM(Q19:Q26) -> 3234338.8 | R27: =SUM(R19:R26) -> 3318635
F28: Senior Loan | I28: =I45*D21 -> 132810000 | J28: =I28/$I$32 -> 0.6 | K28: =I28/$D$8 -> 915931.03 | M28: Retail | N28: ='Income Statement - AM'!DW67 -> 0 | O28: ='Income Statement - AM'!DX67 -> 0 | P28: ='Income Statement - AM'!DY67 -> 0 | Q28: ='Income Statement - AM'!DZ67 -> 0 | R28: ='Income Statement - AM'!EA67 -> 0
B29: Key Dates | F29: Preferred Equity | I29: 0 | J29: =I29/$I$32 -> 0 | K29: =I29/$D$8 -> 0 | M29: Effective Gross Income (Total) | N29: =N28+N27 -> -4.6566129e-10 | O29: =O28+O27 -> 1357475.7 | P29: =P28+P27 -> 3155184.5 | Q29: =Q28+Q27 -> 3234338.8 | R29: =R28+R27 -> 3318635 | S29: ='Income Statement - AM'!EB77 -> 241606.25 | T29: ='Income Statement - AM'!EC77 -> 245956.25 | U29: ='Income Statement - AM'!ED77 -> 250306.25 | V29: ='Income Statement - AM'!EE77 -> 254656.25 | W29: ='Income Statement - AM'!EF77 -> 259006.25
F30: =CONCATENATE("LP - ",'AIRR Input Tab'!D10, " Equity") -> LP - Investar Equity | I30: =(I32-I28)*G50 -> 84113000 | J30: =I30/$I$32 -> 0.38 | K30: =I30/$D$8 -> 580089.66 | S30: ='Income Statement - AM'!EB78 -> 16107.083 | T30: ='Income Statement - AM'!EC78 -> 16397.083 | U30: ='Income Statement - AM'!ED78 -> 16687.083 | V30: ='Income Statement - AM'!EE78 -> 16977.083 | W30: ='Income Statement - AM'!EF78 -> 17267.083
C31: Month | D31: Date | F31: =CONCATENATE("GP - ", 'AIRR Input Tab'!D11, " Equity") -> GP - Ace Equity | I31: =(I32-I28)*H50 -> 4427000 | J31: =I31/$I$32 -> 0.02 | K31: =I31/$D$8 -> 30531.034 | M31: Controllable Expenses | S31: ='Income Statement - AM'!EB79 -> 48321.25 | T31: ='Income Statement - AM'!EC79 -> 49191.25 | U31: ='Income Statement - AM'!ED79 -> 50061.25 | V31: ='Income Statement - AM'!EE79 -> 50931.25 | W31: ='Income Statement - AM'!EF79 -> 51801.25
B32: Land and JV Closing | C32: 0 | D32: =D33 -> 45346 | F32: Total Uses | I32: =I45 -> 221350000 | J32: =SUM(J28:J31) -> 1 | K32: =SUM(K28:K31) -> 1526551.7 | M32: Payroll | N32: ='Income Statement - AM'!DW77 -> 0 | O32: ='Income Statement - AM'!DX77 -> 0 | P32: ='Income Statement - AM'!DY77 -> 133853.12 | Q32: ='Income Statement - AM'!DZ77 -> 232906.25 | R32: ='Income Statement - AM'!EA77 -> 237256.25 | S32: ='Income Statement - AM'!EB80 -> 24160.625 | T32: ='Income Statement - AM'!EC80 -> 24595.625 | U32: ='Income Statement - AM'!ED80 -> 25030.625 | V32: ='Income Statement - AM'!EE80 -> 25465.625 | W32: ='Income Statement - AM'!EF80 -> 25900.625
B33: Construction Start | C33: 0 | D33: ='PERPETUITY MIDDLEMAN INPUT TAB'!C11 -> 45346 | M33: Utilities | N33: ='Income Statement - AM'!DW78 -> 0 | O33: ='Income Statement - AM'!DX78 -> 7499.7222 | P33: ='Income Statement - AM'!DY78 -> 15237.083 | Q33: ='Income Statement - AM'!DZ78 -> 15527.083 | R33: ='Income Statement - AM'!EA78 -> 15817.083 | S33: ='Income Statement - AM'!EB81 -> 80535.417 | T33: ='Income Statement - AM'!EC81 -> 81985.417 | U33: ='Income Statement - AM'!ED81 -> 83435.417 | V33: ='Income Statement - AM'!EE81 -> 84885.417 | W33: ='Income Statement - AM'!EF81 -> 86335.417
B34: Construction Completion | C34: ='PERPETUITY MIDDLEMAN INPUT TAB'!#REF! -> #REF! | D34: =EOMONTH($D$32,C34) -> #REF! | F34: Uses | I34: Closing Budget | J34: % | K34: Per Unit | M34: Turnover | N34: ='Income Statement - AM'!DW79 -> 0 | O34: ='Income Statement - AM'!DX79 -> 22499.167 | P34: ='Income Statement - AM'!DY79 -> 45711.25 | Q34: ='Income Statement - AM'!DZ79 -> 46581.25 | R34: ='Income Statement - AM'!EA79 -> 47451.25 | S34: ='Income Statement - AM'!EB82 -> 40267.708 | T34: ='Income Statement - AM'!EC82 -> 40992.708 | U34: ='Income Statement - AM'!ED82 -> 41717.708 | V34: ='Income Statement - AM'!EE82 -> 42442.708 | W34: ='Income Statement - AM'!EF82 -> 43167.708
B35: ='PERPETUITY MIDDLEMAN INPUT TAB'!B16 -> First Units Delivered (Opex Starts) | C35: ='PERPETUITY MIDDLEMAN INPUT TAB'!#REF! -> #REF! | D35: =EOMONTH($D$32,C35) -> #REF! | F35: Land Acquisition Costs | I35: ='Draw Schedule'!C9 -> 15000000 | J35: =I35/$I$45 -> 0.067765981 | K35: =I35/$D$8 -> 103448.28 | M35: Contract Services | N35: ='Income Statement - AM'!DW80 -> 0 | O35: ='Income Statement - AM'!DX80 -> 0 | P35: ='Income Statement - AM'!DY80 -> 13385.312 | Q35: ='Income Statement - AM'!DZ80 -> 23290.625 | R35: ='Income Statement - AM'!EA80 -> 23725.625 | S35: ='Income Statement - AM'!EB83 -> 48321.25 | T35: ='Income Statement - AM'!EC83 -> 49191.25 | U35: ='Income Statement - AM'!ED83 -> 50061.25 | V35: ='Income Statement - AM'!EE83 -> 50931.25 | W35: ='Income Statement - AM'!EF83 -> 51801.25
B36: ='PERPETUITY MIDDLEMAN INPUT TAB'!B17 -> Absorption Start | C36: ='PERPETUITY MIDDLEMAN INPUT TAB'!#REF! -> #REF! | D36: =EOMONTH($D$32,C36) -> #REF! | F36: Closing Costs | I36: ='Draw Schedule'!C10 -> 0 | J36: =I36/$I$45 -> 0 | K36: =I36/$D$8 -> 0 | M36: Repairs and Maintenance | N36: ='Income Statement - AM'!DW81 -> 0 | O36: ='Income Statement - AM'!DX81 -> 37498.611 | P36: ='Income Statement - AM'!DY81 -> 76185.417 | Q36: ='Income Statement - AM'!DZ81 -> 77635.417 | R36: ='Income Statement - AM'!EA81 -> 79085.417 | S36: ='Income Statement - AM'!EB84 -> 0 | T36: ='Income Statement - AM'!EC84 -> 0 | U36: ='Income Statement - AM'!ED84 -> 0 | V36: ='Income Statement - AM'!EE84 -> 0 | W36: ='Income Statement - AM'!EF84 -> 0
B37: NOI Breakeven | C37: 36 | D37: =EOMONTH($D$32,C37) -> 46446 | F37: Hard Cost | I37: ='Draw Schedule'!C14+'Draw Schedule'!C15+'Draw Schedule'!C16 -> 175000000 | J37: =I37/$I$45 -> 0.79060312 | K37: =I37/$D$8 -> 1206896.6 | M37: Leasing and Marketing | N37: ='Income Statement - AM'!DW82 -> 0 | O37: ='Income Statement - AM'!DX82 -> 0 | P37: ='Income Statement - AM'!DY82 -> 22308.854 | Q37: ='Income Statement - AM'!DZ82 -> 38817.708 | R37: ='Income Statement - AM'!EA82 -> 39542.708 | S37: =SUM(S29:S36) -> 499319.58 | T37: =SUM(T29:T36) -> 508309.58 | U37: =SUM(U29:U36) -> 517299.58 | V37: =SUM(V29:V36) -> 526289.58 | W37: =SUM(W29:W36) -> 535279.58
B38: Senior Debt Service Breakeven | C38: 40 | D38: =EOMONTH($D$32,C38) -> 46568 | F38: Hard Cost Contingency | I38: ='Draw Schedule'!C17 -> 0 | J38: =I38/$I$45 -> 0 | K38: =I38/$D$8 -> 0 | M38: General and Administrative | N38: ='Income Statement - AM'!DW83 -> 0 | O38: ='Income Statement - AM'!DX83 -> 0 | P38: ='Income Statement - AM'!DY83 -> 26770.625 | Q38: ='Income Statement - AM'!DZ83 -> 46581.25 | R38: ='Income Statement - AM'!EA83 -> 47451.25
B39: Stabilization | C39: 46 | D39: =EOMONTH($D$32,C39) -> 46752 | F39: Soft Costs | I39: ='Draw Schedule'!C32-'Draw Schedule'!C31 -> 22000000 | J39: =I39/$I$45 -> 0.099390106 | K39: =I39/$D$8 -> 151724.14 | M39: Other Expenses | N39: ='Income Statement - AM'!DW84 -> 0 | O39: ='Income Statement - AM'!DX84 -> 0 | P39: ='Income Statement - AM'!DY84 -> 0 | Q39: ='Income Statement - AM'!DZ84 -> 0 | R39: ='Income Statement - AM'!EA84 -> 0 | S39: ='Income Statement - AM'!EB87 -> 100757.24 | T39: ='Income Statement - AM'!EC87 -> 100757.24 | U39: ='Income Statement - AM'!ED87 -> 100757.24 | V39: ='Income Statement - AM'!EE87 -> 100757.24 | W39: ='Income Statement - AM'!EF87 -> 100757.24
B40: Sale Month | C40: =D44 -> #REF! | D40: =EOMONTH($D$32,C40) -> #REF! | F40: Soft Cost Contingency | I40: ='Draw Schedule'!C31 -> 0 | J40: =I40/$I$45 -> 0 | K40: =I40/$D$8 -> 0 | M40: Total Controllable Expenses | N40: =SUM(N32:N39) -> 0 | O40: =SUM(O32:O39) -> 67497.5 | P40: =SUM(P32:P39) -> 333451.67 | Q40: =SUM(Q32:Q39) -> 481339.58 | R40: =SUM(R32:R39) -> 490329.58 | S40: ='Income Statement - AM'!EB88 -> 64428.333 | T40: ='Income Statement - AM'!EC88 -> 65588.333 | U40: ='Income Statement - AM'!ED88 -> 66748.333 | V40: ='Income Statement - AM'!EE88 -> 67908.333 | W40: ='Income Statement - AM'!EF88 -> 69068.333
F41: Financing Costs | I41: ='Draw Schedule'!C45 -> 0 | J41: =I41/$I$45 -> 0 | K41: =I41/$D$8 -> 0 | S41: ='Income Statement - AM'!EB89 -> 845621.88 | T41: ='Income Statement - AM'!EC89 -> 860846.88 | U41: ='Income Statement - AM'!ED89 -> 876071.88 | V41: ='Income Statement - AM'!EE89 -> 891296.88 | W41: ='Income Statement - AM'!EF89 -> 906521.88
B42: Exit Assumptions | F42: Senior Interest Reserve | I42: ='Draw Schedule'!C49 -> 8500000 | J42: =I42/$I$45 -> 0.038400723 | K42: =I42/$D$8 -> 58620.69 | M42: Management Fee | N42: ='Income Statement - AM'!DW87 -> 0 | O42: ='Income Statement - AM'!DX87 -> 40724.272 | P42: ='Income Statement - AM'!DY87 -> 94655.536 | Q42: ='Income Statement - AM'!DZ87 -> 97030.163 | R42: ='Income Statement - AM'!EA87 -> 99559.051 | S42: ='Income Statement - AM'!EB90 -> 0 | T42: ='Income Statement - AM'!EC90 -> 0 | U42: ='Income Statement - AM'!ED90 -> 0 | V42: ='Income Statement - AM'!EE90 -> 0 | W42: ='Income Statement - AM'!EF90 -> 0
F43: Preferred Equity Interest Reserve | I43: 0 | J43: =I43/$I$45 -> 0 | K43: =I43/$D$8 -> 0 | M43: Insurance | N43: ='Income Statement - AM'!DW88 -> 0 | O43: ='Income Statement - AM'!DX88 -> 0 | P43: ='Income Statement - AM'!DY88 -> 35694.167 | Q43: ='Income Statement - AM'!DZ88 -> 62108.333 | R43: ='Income Statement - AM'!EA88 -> 63268.333 | S43: =SUM(S39:S42) -> 1010807.4 | T43: =SUM(T39:T42) -> 1027192.4 | U43: =SUM(U39:U42) -> 1043577.4 | V43: =SUM(V39:V42) -> 1059962.4 | W43: =SUM(W39:W42) -> 1076347.4
B44: Sale Month | D44: ='PERPETUITY MIDDLEMAN INPUT TAB'!#REF! -> #REF! | F44: Operating Reserve | I44: ='Draw Schedule'!C48 -> 850000 | J44: =I44/$I$45 -> 0.0038400723 | K44: =I44/$D$8 -> 5862.069 | M44: Property Taxes | N44: ='Income Statement - AM'!DW89 -> 0 | O44: ='Income Statement - AM'!DX89 -> 0 | P44: ='Income Statement - AM'!DY89 -> 468485.94 | Q44: ='Income Statement - AM'!DZ89 -> 815171.88 | R44: ='Income Statement - AM'!EA89 -> 830396.88
B45: Sale Date | D45: ='PERPETUITY MIDDLEMAN INPUT TAB'!#REF! -> #REF! | F45: Total Uses | I45: =SUM(I35:I44) -> 221350000 | J45: =SUM(J35:J44) -> 1 | K45: =SUM(K35:K44) -> 1526551.7 | M45: Other Taxes / Fees | N45: ='Income Statement - AM'!DW90 -> 0 | O45: ='Income Statement - AM'!DX90 -> 0 | P45: ='Income Statement - AM'!DY90 -> 0 | Q45: ='Income Statement - AM'!DZ90 -> 0 | R45: ='Income Statement - AM'!EA90 -> 0 | S45: ='Income Statement - AM'!EB97 -> 0 | T45: ='Income Statement - AM'!EC97 -> 0 | U45: ='Income Statement - AM'!ED97 -> 0 | V45: ='Income Statement - AM'!EE97 -> 0 | W45: ='Income Statement - AM'!EF97 -> 0
B46: NOI at Exit | D46: =D47*D50 -> #REF! | M46: Total Non-Controllable Expenses | N46: =SUM(N42:N45) -> 0 | O46: =SUM(O42:O45) -> 40724.272 | P46: =SUM(P42:P45) -> 598835.64 | Q46: =SUM(Q42:Q45) -> 974310.37 | R46: =SUM(R42:R45) -> 993224.26 | S46: =S45+S43+S37 -> 1510127 | T46: =T45+T43+T37 -> 1535502 | U46: =U45+U43+U37 -> 1560877 | V46: =V45+V43+V37 -> 1586252 | W46: =W45+W43+W37 -> 1611627
B47: Exit Cap Rate (Multifamily) | D47: ='PERPETUITY MIDDLEMAN INPUT TAB'!#REF! -> #REF! | F47: Joint Venture Waterfall
B48: Exit Cap Rate (Retail) | D48: ='PERPETUITY MIDDLEMAN INPUT TAB'!#REF! -> #REF! | M48: Replacement Reserves | N48: ='Income Statement - AM'!DW97 -> 0 | O48: ='Income Statement - AM'!DX97 -> 0 | P48: ='Income Statement - AM'!DY97 -> 0 | Q48: ='Income Statement - AM'!DZ97 -> 0 | R48: ='Income Statement - AM'!EA97 -> 0 | S48: =S26-S46 -> 1848447.5 | T48: =T26-T46 -> 1823072.5 | U48: =U26-U46 -> 1797697.5 | V48: =V26-V46 -> 1772322.5 | W48: =W26-W46 -> 1746947.5
F49: Waterfall | G49: ='AIRR Input Tab'!K18 -> Investar | H49: ='AIRR Input Tab'!L18 -> Ace | I49: ='AIRR Input Tab'!N18 -> Hurdle | J49: ='AIRR Input Tab'!O18 -> Multiple | K49: ='AIRR Input Tab'!P18 -> $ Amount | M49: Total Operating Expenses | N49: =N48+N46+N40 -> 0 | O49: =O48+O46+O40 -> 108221.77 | P49: =P48+P46+P40 -> 932287.31 | Q49: =Q48+Q46+Q40 -> 1455650 | R49: =R48+R46+R40 -> 1483553.8
B50: Gross Sale Price | D50: 250000000 | F50: Tier 1: | G50: ='AIRR Input Tab'!K21 -> 0.95 | H50: ='AIRR Input Tab'!L21 -> 0.05 | I50: ='AIRR Input Tab'!N21 -> 0 | J50: ='AIRR Input Tab'!O21 -> 0 | K50: ='AIRR Input Tab'!P21 -> 0 | S50: =S28-S48 -> -1848447.5 | T50: =T28-T48 -> -1823072.5 | U50: =U28-U48 -> -1797697.5 | V50: =V28-V48 -> -1772322.5 | W50: =W28-W48 -> -1746947.5
B51: Gross Sale Price / Unit | D51: =D50/H13 -> 454545.45 | F51: Tier 2: | G51: ='AIRR Input Tab'!K22 -> 0.8 | H51: ='AIRR Input Tab'!L22 -> 0.05 | I51: ='AIRR Input Tab'!N22 -> 0.08 | J51: ='AIRR Input Tab'!O22 -> 1 | K51: ='AIRR Input Tab'!P22 -> 0 | M51: Net Operating Income | N51: =N29-N49 -> -4.6566129e-10 | O51: =O29-O49 -> 1249254 | P51: =P29-P49 -> 2222897.2 | Q51: =Q29-Q49 -> 1778688.8 | R51: =R29-R49 -> 1835081.2
B52: Cost of Sale | C52: ='PERPETUITY MIDDLEMAN INPUT TAB'!#REF! -> #REF! | D52: =C52*D50 -> #REF! | F52: Tier 3: | G52: ='AIRR Input Tab'!K23 -> 0.7 | H52: ='AIRR Input Tab'!L23 -> 0.05 | I52: ='AIRR Input Tab'!N23 -> 0.1 | J52: ='AIRR Input Tab'!O23 -> 1 | K52: ='AIRR Input Tab'!P23 -> 0
B53: Net Sale Proceeds | D53: =D50-D52 -> #REF! | F53: Tier 4: | G53: ='AIRR Input Tab'!K24 -> 0.5 | H53: ='AIRR Input Tab'!L24 -> 0.05 | I53: ='AIRR Input Tab'!N24 -> 0.15 | J53: ='AIRR Input Tab'!O24 -> 1 | K53: ='AIRR Input Tab'!P24 -> 0 | M53: Return on Cost | N53: =N51/$I$45 -> -2.1037329e-18 | O53: =O51/$I$45 -> 0.0056437947 | P53: =P51/$I$45 -> 0.010042454 | Q53: =Q51/$I$45 -> 0.0080356395 | R53: =R51/$I$45 -> 0.0082904052
F54: Tier 5: | G54: ='AIRR Input Tab'!K25 -> 0.5 | H54: ='AIRR Input Tab'!L25 -> 0.05 | I54: ='AIRR Input Tab'!N25 -> 0.15 | J54: ='AIRR Input Tab'!O25 -> 1 | K54: ='AIRR Input Tab'!P25 -> 0
F55: Tier 6: | G55: ='AIRR Input Tab'!K26 -> 0.5 | H55: ='AIRR Input Tab'!L26 -> 0.05 | I55: ='AIRR Input Tab'!N26 -> 0.15 | J55: ='AIRR Input Tab'!O26 -> 1 | K55: ='AIRR Input Tab'!P26 -> 0
F57: Returns
H59: Unlevered | I59: Levered | J59: =G49 -> Investar | K59: =H49 -> Ace
F60: Investment | H60: =I45-I41-I42-I43 -> 212850000 | I60: =SUM(I29:I31) -> 88540000 | J60: =I30 -> 84113000 | K60: =I31 -> 4427000
F61: IRR | H61: 0.14 | I61: 0.2 | J61: 0.18 | K61: 0.3
F62: MOIC | H62: =(H60+H63)/H60 -> 1.1661153 | I62: =(I60+I63)/I60 -> 1.3993409 | J62: =(J60+J63)/J60 -> 1.4203588 | K62: =(K60+K63)/K60 -> 8.9868177
F63: Net Profit | H63: 35357642 | I63: 35357642 | J63: 35357642 | K63: 35357642
S66: Unlevered IRR
S77: Unlevered Equity Multiple
S78: Levered IRR
S79: Levered Equity Multiple
S80: Net Profit (Levered CF)
S108: Average Cash-on-Cash Return
S109: LP IRR
S110: LP MOIC
S111: GP IRR
S112: GP MOIC

Sheet Underwriting Model Summary
B2: ='Deal Landing Dashboard'!B2 -> West Village Complexes - Multifamily - New York
B5: Property Details | F5: Unit Mix | M5: Pro Forma
B7: Deal Name | D7: West Village Complexes | F7: Unit Type | H7: # of Units | I7: SF | J7: Rent | K7: Rent PSF | M7: Face Rents | N7: ='Income Statement - AM'!DW24 -> 1717.7779 | O7: ='Income Statement - AM'!DX24 -> 1756.9053 | P7: ='Income Statement - AM'!DY24 -> 1798.7185 | Q7: ='Income Statement - AM'!DZ24 -> 1843.3656 | R7: ='Income Statement - AM'!EA24 -> 1891.0073 | S7: ='Income Statement - AM'!EB24 -> 1913.5986 | T7: ='Income Statement - AM'!EC24 -> 1913.5986 | U7: ='Income Statement - AM'!ED24 -> 1913.5986 | ... W7: ='Income Statement - AM'!EF24 -> 1913.5986
B8: Number of Units | D8: ='Unit Mix '!E84 -> 145 | F8: Studio | H8: 50 | I8: 600 | J8: 1425 | K8: =J8/I8 -> 2.375 | M8: Effective Rents | N8: ='Income Statement - AM'!DW32 -> 0 | O8: ='Income Statement - AM'!DX32 -> 1490.027 | P8: ='Income Statement - AM'!DY32 -> 2474.0368 | Q8: ='Income Statement - AM'!DZ32 -> 1691.5041 | R8: ='Income Statement - AM'!EA32 -> 1735.2925 | S8: ='Income Statement - AM'!EB32 -> 1754.132 | T8: ='Income Statement - AM'!EC32 -> 1754.132 | U8: ='Income Statement - AM'!ED32 -> 1754.132 | ... W8: ='Income Statement - AM'!EF32 -> 1754.132
B9: Property Type | D9: Multifamily | F9: 1BR/1BA | H9: 250 | I9: 600 | J9: 1425 | K9: =J9/I9 -> 2.375 | M9: Occupancy | N9: ='Income Statement - AM'!DW15 -> 0 | O9: ='Income Statement - AM'!DX15 -> 1 | P9: ='Income Statement - AM'!DY15 -> 1 | Q9: ='Income Statement - AM'!DZ15 -> 1 | R9: ='Income Statement - AM'!EA15 -> 1 | S9: ='Income Statement - AM'!EB15 -> 1 | T9: ='Income Statement - AM'!EC15 -> 1 | U9: ='Income Statement - AM'!ED15 -> 1 | ... W9: ='Income Statement - AM'!EF15 -> 1
B10: Construction Type | D10: Type 1 | F10: 2BR/1BA | H10: 225 | I10: 725 | J10: 1600 | K10: =J10/I10 -> 2.2068966 | M10: Rent Growth | N10: 0.05 | O10: 0.05 | P10: 0.05 | Q10: 0.05 | R10: 0.05
B11: Stories | D11: Midrise | F11: 2BR/2BA | H11: 25 | I11: 875 | J11: 1875 | K11: =J11/I11 -> 2.1428571 | S11: =R13+1 -> 6 | T11: =S11+1 -> 7 | U11: =T11+1 -> 8 | V11: =U11+1 -> 9 | W11: =V11+1 -> 10
B12: Number of Buildings | D12: 2 | H12: 0 | I12: 1025 | J12: 2100 | K12: =J12/I12 -> 2.0487805 | M12: Actual / Forecast | N12: ACTUAL | O12: ACTUAL | P12: ACTUAL | Q12: FORECAST | R12: FORECAST | S12: ='Income Statement - AM'!EB34 -> 3329661.5 | T12: ='Income Statement - AM'!EC34 -> 3329661.5 | U12: ='Income Statement - AM'!ED34 -> 3329661.5 | V12: ='Income Statement - AM'!EE34 -> 3329661.5 | W12: ='Income Statement - AM'!EF34 -> 3329661.5
B13: Gross Square Feet | D13: ='AIRR Input Tab'!D29 -> 450000 | F13: Total / Average | H13: =SUM(H8:H12) -> 550 | I13: =SUMPRODUCT(H8:H12,I8:I12)/H13 -> 663.63636 | J13: =SUMPRODUCT(H8:H12,J8:J12)/H13 -> 1517.0455 | K13: =J13/I13 -> 2.2859589 | M13: Year | N13: 1 | O13: =N13+1 -> 2 | P13: =O13+1 -> 3 | Q13: =P13+1 -> 4 | R13: =Q13+1 -> 5 | S13: ='Income Statement - AM'!EB35 -> 0 | T13: ='Income Statement - AM'!EC35 -> 0 | U13: ='Income Statement - AM'!ED35 -> 0 | V13: ='Income Statement - AM'!EE35 -> 0 | W13: ='Income Statement - AM'!EF35 -> 0
B14: Net Rentable SF | D14: =I13*H13 -> 365000 | M14: Date | N14: =D32 -> 45346 | O14: =EOMONTH(N14,12) -> 45716 | P14: =EOMONTH(O14,12) -> 46081 | Q14: =EOMONTH(P14,12) -> 46446 | R14: =EOMONTH(Q14,12) -> 46812 | S14: =SUM(S12:S13) -> 3329661.5 | T14: =SUM(T12:T13) -> 3329661.5 | U14: =SUM(U12:U13) -> 3329661.5 | V14: =SUM(V12:V13) -> 3329661.5 | W14: =SUM(W12:W13) -> 3329661.5
B15: Acres | D15: ='AIRR Input Tab'!D27 -> 2 | F15: General Asumptions | M15: Gross Potential Rent | N15: ='Income Statement - AM'!DW34 -> 2988933.6 | O15: ='Income Statement - AM'!DX34 -> 3057015.2 | P15: ='Income Statement - AM'!DY34 -> 3129770.1 | Q15: ='Income Statement - AM'!DZ34 -> 3207456.2 | R15: ='Income Statement - AM'!EA34 -> 3290352.8 | S15: ='Income Statement - AM'!EB55 -> 167760.7 | T15: ='Income Statement - AM'!EC55 -> 167760.7 | U15: ='Income Statement - AM'!ED55 -> 167760.7 | V15: ='Income Statement - AM'!EE55 -> 167760.7 | W15: ='Income Statement - AM'!EF55 -> 167760.7
B16: Units / Acre | D16: =H13/D15 -> 275 | M16: Loss to Lease | N16: ='Income Statement - AM'!DW35 -> 0 | O16: ='Income Statement - AM'!DX35 -> 0 | P16: ='Income Statement - AM'!DY35 -> 0 | Q16: ='Income Statement - AM'!DZ35 -> 0 | R16: ='Income Statement - AM'!EA35 -> 0 | S16: =S15+S14 -> 3497422.2 | T16: =T15+T14 -> 3497422.2 | U16: =U15+U14 -> 3497422.2 | V16: =V15+V14 -> 3497422.2 | W16: =W15+W14 -> 3497422.2
B17: Parking Spaces | D17: ='AIRR Input Tab'!D30 -> 200 | F17: Vacancy | H17: ='PERPETUITY MIDDLEMAN INPUT TAB'!#REF! -> #REF! | I17: Concessions - Lease Up (New) | K17: ='PERPETUITY MIDDLEMAN INPUT TAB'!#REF! -> #REF! | M17: Gross Potential Rent | N17: =SUM(N15:N16) -> 2988933.6 | O17: =SUM(O15:O16) -> 3057015.2 | P17: =SUM(P15:P16) -> 3129770.1 | Q17: =SUM(Q15:Q16) -> 3207456.2 | R17: =SUM(R15:R16) -> 3290352.8 | S17: ='Income Statement - AM'!EB59 -> -104922.67 | T17: ='Income Statement - AM'!EC59 -> -104922.67 | U17: ='Income Statement - AM'!ED59 -> -104922.67 | V17: ='Income Statement - AM'!EE59 -> -104922.67 | W17: ='Income Statement - AM'!EF59 -> -104922.67
F18: Loss to Lease | H18: ='PERPETUITY MIDDLEMAN INPUT TAB'!#REF! -> #REF! | I18: Concessions - Lease Up (Renewal) | K18: ='PERPETUITY MIDDLEMAN INPUT TAB'!#REF! -> #REF! | M18: Other Income | N18: ='Income Statement - AM'!DW55 -> 146788.47 | O18: ='Income Statement - AM'!DX55 -> 151253.18 | P18: ='Income Statement - AM'!DY55 -> 155853.69 | Q18: ='Income Statement - AM'!DZ55 -> 160594.13 | R18: ='Income Statement - AM'!EA55 -> 165478.76 | S18: ='Income Statement - AM'!EB60 -> 0 | T18: ='Income Statement - AM'!EC60 -> 0 | U18: ='Income Statement - AM'!ED60 -> 0 | V18: ='Income Statement - AM'!EE60 -> 0 | W18: ='Income Statement - AM'!EF60 -> 0
B19: Senior Loan Terms | F19: Bad Debt | H19: ='PERPETUITY MIDDLEMAN INPUT TAB'!#REF! -> #REF! | I19: Concessions - Stabilized (New) | K19: ='PERPETUITY MIDDLEMAN INPUT TAB'!#REF! -> #REF! | M19: Net Potential Income | N19: =N18+N17 -> 3135722 | O19: =O18+O17 -> 3208268.4 | P19: =P18+P17 -> 3285623.8 | Q19: =Q18+Q17 -> 3368050.4 | R19: =R18+R17 -> 3455831.5 | S19: ='Income Statement - AM'!EB61 -> 0 | T19: ='Income Statement - AM'!EC61 -> 0 | U19: ='Income Statement - AM'!ED61 -> 0 | V19: ='Income Statement - AM'!EE61 -> 0 | W19: ='Income Statement - AM'!EF61 -> 0
F20: Model Units | H20: ='PERPETUITY MIDDLEMAN INPUT TAB'!#REF! -> #REF! | I20: Concessions - Stabilized (Renewal) | K20: ='PERPETUITY MIDDLEMAN INPUT TAB'!#REF! -> #REF! | M20: Vacancy | N20: ='Income Statement - AM'!DW59 -> -3135722 | O20: ='Income Statement - AM'!DX59 -> -1605490.3 | P20: ='Income Statement - AM'!DY59 -> -98568.714 | Q20: ='Income Statement - AM'!DZ59 -> -101041.51 | R20: ='Income Statement - AM'!EA59 -> -103674.95 | S20: ='Income Statement - AM'!EB62 -> 0 | T20: ='Income Statement - AM'!EC62 -> 0 | U20: ='Income Statement - AM'!ED62 -> 0 | V20: ='Income Statement - AM'!EE62 -> 0 | W20: ='Income Statement - AM'!EF62 -> 0
B21: Loan to Cost % | D21: ='AIRR Input Tab'!D42 -> 0.6 | F21: Leased Units Per Month | H21: ='PERPETUITY MIDDLEMAN INPUT TAB'!#REF! -> #REF! | M21: Model Units | N21: ='Income Statement - AM'!DW60 -> 0 | O21: ='Income Statement - AM'!DX60 -> 0 | P21: ='Income Statement - AM'!DY60 -> 0 | Q21: ='Income Statement - AM'!DZ60 -> 0 | R21: ='Income Statement - AM'!EA60 -> 0 | S21: ='Income Statement - AM'!EB63 -> 0 | T21: ='Income Statement - AM'!EC63 -> 0 | U21: ='Income Statement - AM'!ED63 -> 0 | V21: ='Income Statement - AM'!EE63 -> 0 | W21: ='Income Statement - AM'!EF63 -> 0
B22: Initial Term | D22: ='AIRR Input Tab'!D50 -> 48 | F22: Renewal Probability | H22: ='PERPETUITY MIDDLEMAN INPUT TAB'!#REF! -> #REF! | M22: Concessions - Lease Up (New) | N22: ='Income Statement - AM'!DW61 -> 0 | O22: ='Income Statement - AM'!DX61 -> -231590.51 | P22: ='Income Statement - AM'!DY61 -> 0 | Q22: ='Income Statement - AM'!DZ61 -> 0 | R22: ='Income Statement - AM'!EA61 -> 0 | S22: ='Income Statement - AM'!EB64 -> 0 | T22: ='Income Statement - AM'!EC64 -> 0 | U22: ='Income Statement - AM'!ED64 -> 0 | V22: ='Income Statement - AM'!EE64 -> 0 | W22: ='Income Statement - AM'!EF64 -> 0
B23: Interest Type - Fixed/Floating | D23: ='AIRR Input Tab'!D43 -> Floating | F23: Lease Term | H23: ='PERPETUITY MIDDLEMAN INPUT TAB'!#REF! -> #REF! | M23: Concessions - Lease Up (Renewal) | N23: ='Income Statement - AM'!DW62 -> 0 | O23: ='Income Statement - AM'!DX62 -> 0 | P23: ='Income Statement - AM'!DY62 -> 0 | Q23: ='Income Statement - AM'!DZ62 -> 0 | R23: ='Income Statement - AM'!EA62 -> 0 | S23: ='Income Statement - AM'!EB65 -> -33924.995 | T23: ='Income Statement - AM'!EC65 -> -33924.995 | U23: ='Income Statement - AM'!ED65 -> -33924.995 | V23: ='Income Statement - AM'!EE65 -> -33924.995 | W23: ='Income Statement - AM'!EF65 -> -33924.995 | AA23: Absorption Start Month
B24: SOFR Spread | D24: ='AIRR Input Tab'!D45 -> 0.025 | M24: Concessions - Stabilized (New) | N24: ='Income Statement - AM'!DW63 -> 0 | O24: ='Income Statement - AM'!DX63 -> 0 | P24: ='Income Statement - AM'!DY63 -> 0 | Q24: ='Income Statement - AM'!DZ63 -> 0 | R24: ='Income Statement - AM'!EA63 -> 0 | S24: =SUM(S16:S23) -> 3358574.6 | T24: =SUM(T16:T23) -> 3358574.6 | U24: =SUM(U16:U23) -> 3358574.6 | V24: =SUM(V16:V23) -> 3358574.6 | W24: =SUM(W16:W23) -> 3358574.6 | AA24: Absorption Start Date
B25: SOFR Floor | D25: ='AIRR Input Tab'!D46 -> 0 | F25: Budget | M25: Concessions - Stabilized (Renewal) | N25: ='Income Statement - AM'!DW64 -> 0 | O25: ='Income Statement - AM'!DX64 -> 0 | P25: ='Income Statement - AM'!DY64 -> 0 | Q25: ='Income Statement - AM'!DZ64 -> 0 | R25: ='Income Statement - AM'!EA64 -> 0 | S25: ='Income Statement - AM'!EB67 -> 0 | T25: ='Income Statement - AM'!EC67 -> 0 | U25: ='Income Statement - AM'!ED67 -> 0 | V25: ='Income Statement - AM'!EE67 -> 0 | W25: ='Income Statement - AM'!EF67 -> 0
B26: Interest Only Period | D26: ='AIRR Input Tab'!D48 -> 36 | M26: Bad Debt | N26: ='Income Statement - AM'!DW65 -> 0 | O26: ='Income Statement - AM'!DX65 -> -13711.876 | P26: ='Income Statement - AM'!DY65 -> -31870.551 | Q26: ='Income Statement - AM'!DZ65 -> -32670.089 | R26: ='Income Statement - AM'!EA65 -> -33521.566 | S26: =S25+S24 -> 3358574.6 | T26: =T25+T24 -> 3358574.6 | U26: =U25+U24 -> 3358574.6 | V26: =V25+V24 -> 3358574.6 | W26: =W25+W24 -> 3358574.6
B27: Amortization Schedule | D27: ='AIRR Input Tab'!D49 -> 30 | F27: Sources | I27: Closing Budget | J27: % | K27: Per Unit | M27: Effective Gross Income (Multi) | N27: =SUM(N19:N26) -> -4.6566129e-10 | O27: =SUM(O19:O26) -> 1357475.7 | P27: =SUM(P19:P26) -> 3155184.5 | Q27: =SUM(Q19:Q26) -> 3234338.8 | R27: =SUM(R19:R26) -> 3318635
F28: Senior Loan | I28: =I45*D21 -> 132810000 | J28: =I28/$I$32 -> 0.6 | K28: =I28/$D$8 -> 915931.03 | M28: Retail | N28: ='Income Statement - AM'!DW67 -> 0 | O28: ='Income Statement - AM'!DX67 -> 0 | P28: ='Income Statement - AM'!DY67 -> 0 | Q28: ='Income Statement - AM'!DZ67 -> 0 | R28: ='Income Statement - AM'!EA67 -> 0
B29: Key Dates | F29: Preferred Equity | I29: 0 | J29: =I29/$I$32 -> 0 | K29: =I29/$D$8 -> 0 | M29: Effective Gross Income (Total) | N29: =N28+N27 -> -4.6566129e-10 | O29: =O28+O27 -> 1357475.7 | P29: =P28+P27 -> 3155184.5 | Q29: =Q28+Q27 -> 3234338.8 | R29: =R28+R27 -> 3318635 | S29: ='Income Statement - AM'!EB77 -> 241606.25 | T29: ='Income Statement - AM'!EC77 -> 245956.25 | U29: ='Income Statement - AM'!ED77 -> 250306.25 | V29: ='Income Statement - AM'!EE77 -> 254656.25 | W29: ='Income Statement - AM'!EF77 -> 259006.25
F30: =CONCATENATE("LP - ",'AIRR Input Tab'!D10, " Equity") -> LP - Investar Equity | I30: =(I32-I28)*G50 -> 84113000 | J30: =I30/$I$32 -> 0.38 | K30: =I30/$D$8 -> 580089.66 | S30: ='Income Statement - AM'!EB78 -> 16107.083 | T30: ='Income Statement - AM'!EC78 -> 16397.083 | U30: ='Income Statement - AM'!ED78 -> 16687.083 | V30: ='Income Statement - AM'!EE78 -> 16977.083 | W30: ='Income Statement - AM'!EF78 -> 17267.083
C31: Month | D31: Date | F31: =CONCATENATE("GP - ", 'AIRR Input Tab'!D11, " Equity") -> GP - Ace Equity | I31: =(I32-I28)*H50 -> 4427000 | J31: =I31/$I$32 -> 0.02 | K31: =I31/$D$8 -> 30531.034 | M31: Controllable Expenses | S31: ='Income Statement - AM'!EB79 -> 48321.25 | T31: ='Income Statement - AM'!EC79 -> 49191.25 | U31: ='Income Statement - AM'!ED79 -> 50061.25 | V31: ='Income Statement - AM'!EE79 -> 50931.25 | W31: ='Income Statement - AM'!EF79 -> 51801.25
B32: Land and JV Closing | C32: 0 | D32: =D33 -> 45346 | F32: Total Uses | I32: =I45 -> 221350000 | J32: =SUM(J28:J31) -> 1 | K32: =SUM(K28:K31) -> 1526551.7 | M32: Payroll | N32: ='Income Statement - AM'!DW77 -> 0 | O32: ='Income Statement - AM'!DX77 -> 0 | P32: ='Income Statement - AM'!DY77 -> 133853.12 | Q32: ='Income Statement - AM'!DZ77 -> 232906.25 | R32: ='Income Statement - AM'!EA77 -> 237256.25 | S32: ='Income Statement - AM'!EB80 -> 24160.625 | T32: ='Income Statement - AM'!EC80 -> 24595.625 | U32: ='Income Statement - AM'!ED80 -> 25030.625 | V32: ='Income Statement - AM'!EE80 -> 25465.625 | W32: ='Income Statement - AM'!EF80 -> 25900.625
B33: Construction Start | C33: 0 | D33: ='PERPETUITY MIDDLEMAN INPUT TAB'!C11 -> 45346 | M33: Utilities | N33: ='Income Statement - AM'!DW78 -> 0 | O33: ='Income Statement - AM'!DX78 -> 7499.7222 | P33: ='Income Statement - AM'!DY78 -> 15237.083 | Q33: ='Income Statement - AM'!DZ78 -> 15527.083 | R33: ='Income Statement - AM'!EA78 -> 15817.083 | S33: ='Income Statement - AM'!EB81 -> 80535.417 | T33: ='Income Statement - AM'!EC81 -> 81985.417 | U33: ='Income Statement - AM'!ED81 -> 83435.417 | V33: ='Income Statement - AM'!EE81 -> 84885.417 | W33: ='Income Statement - AM'!EF81 -> 86335.417
B34: Construction Completion | C34: ='PERPETUITY MIDDLEMAN INPUT TAB'!#REF! -> #REF! | D34: =EOMONTH($D$32,C34) -> #REF! | F34: Uses | I34: Closing Budget | J34: % | K34: Per Unit | M34: Turnover | N34: ='Income Statement - AM'!DW79 -> 0 | O34: ='Income Statement - AM'!DX79 -> 22499.167 | P34: ='Income Statement - AM'!DY79 -> 45711.25 | Q34: ='Income Statement - AM'!DZ79 -> 46581.25 | R34: ='Income Statement - AM'!EA79 -> 47451.25 | S34: ='Income Statement - AM'!EB82 -> 40267.708 | T34: ='Income Statement - AM'!EC82 -> 40992.708 | U34: ='Income Statement - AM'!ED82 -> 41717.708 | V34: ='Income Statement - AM'!EE82 -> 42442.708 | W34: ='Income Statement - AM'!EF82 -> 43167.708
B35: ='PERPETUITY MIDDLEMAN INPUT TAB'!B16 -> First Units Delivered (Opex Starts) | C35: ='PERPETUITY MIDDLEMAN INPUT TAB'!#REF! -> #REF! | D35: =EOMONTH($D$32,C35) -> #REF! | F35: Land Acquisition Costs | I35: ='Draw Schedule'!C9 -> 15000000 | J35: =I35/$I$45 -> 0.067765981 | K35: =I35/$D$8 -> 103448.28 | M35: Contract Services | N35: ='Income Statement - AM'!DW80 -> 0 | O35: ='Income Statement - AM'!DX80 -> 0 | P35: ='Income Statement - AM'!DY80 -> 13385.312 | Q35: ='Income Statement - AM'!DZ80 -> 23290.625 | R35: ='Income Statement - AM'!EA80 -> 23725.625 | S35: ='Income Statement - AM'!EB83 -> 48321.25 | T35: ='Income Statement - AM'!EC83 -> 49191.25 | U35: ='Income Statement - AM'!ED83 -> 50061.25 | V35: ='Income Statement - AM'!EE83 -> 50931.25 | W35: ='Income Statement - AM'!EF83 -> 51801.25
B36: ='PERPETUITY MIDDLEMAN INPUT TAB'!B17 -> Absorption Start | C36: ='PERPETUITY MIDDLEMAN INPUT TAB'!#REF! -> #REF! | D36: =EOMONTH($D$32,C36) -> #REF! | F36: Closing Costs | I36: ='Draw Schedule'!C10 -> 0 | J36: =I36/$I$45 -> 0 | K36: =I36/$D$8 -> 0 | M36: Repairs and Maintenance | N36: ='Income Statement - AM'!DW81 -> 0 | O36: ='Income Statement - AM'!DX81 -> 37498.611 | P36: ='Income Statement - AM'!DY81 -> 76185.417 | Q36: ='Income Statement - AM'!DZ81 -> 77635.417 | R36: ='Income Statement - AM'!EA81 -> 79085.417 | S36: ='Income Statement - AM'!EB84 -> 0 | T36: ='Income Statement - AM'!EC84 -> 0 | U36: ='Income Statement - AM'!ED84 -> 0 | V36: ='Income Statement - AM'!EE84 -> 0 | W36: ='Income Statement - AM'!EF84 -> 0
B37: NOI Breakeven | C37: 36 | D37: =EOMONTH($D$32,C37) -> 46446 | F37: Hard Cost | I37: ='Draw Schedule'!C14+'Draw Schedule'!C15+'Draw Schedule'!C16 -> 175000000 | J37: =I37/$I$45 -> 0.79060312 | K37: =I37/$D$8 -> 1206896.6 | M37: Leasing and Marketing | N37: ='Income Statement - AM'!DW82 -> 0 | O37: ='Income Statement - AM'!DX82 -> 0 | P37: ='Income Statement - AM'!DY82 -> 22308.854 | Q37: ='Income Statement - AM'!DZ82 -> 38817.708 | R37: ='Income Statement - AM'!EA82 -> 39542.708 | S37: =SUM(S29:S36) -> 499319.58 | T37: =SUM(T29:T36) -> 508309.58 | U37: =SUM(U29:U36) -> 517299.58 | V37: =SUM(V29:V36) -> 526289.58 | W37: =SUM(W29:W36) -> 535279.58
B38: Senior Debt Service Breakeven | C38: 40 | D38: =EOMONTH($D$32,C38) -> 46568 | F38: Hard Cost Contingency | I38: ='Draw Schedule'!C17 -> 0 | J38: =I38/$I$45 -> 0 | K38: =I38/$D$8 -> 0 | M38: General and Administrative | N38: ='Income Statement - AM'!DW83 -> 0 | O38: ='Income Statement - AM'!DX83 -> 0 | P38: ='Income Statement - AM'!DY83 -> 26770.625 | Q38: ='Income Statement - AM'!DZ83 -> 46581.25 | R38: ='Income Statement - AM'!EA83 -> 47451.25
B39: Stabilization | C39: 46 | D39: =EOMONTH($D$32,C39) -> 46752 | F39: Soft Costs | I39: ='Draw Schedule'!C32-'Draw Schedule'!C31 -> 22000000 | J39: =I39/$I$45 -> 0.099390106 | K39: =I39/$D$8 -> 151724.14 | M39: Other Expenses | N39: ='Income Statement - AM'!DW84 -> 0 | O39: ='Income Statement - AM'!DX84 -> 0 | P39: ='Income Statement - AM'!DY84 -> 0 | Q39: ='Income Statement - AM'!DZ84 -> 0 | R39: ='Income Statement - AM'!EA84 -> 0 | S39: ='Income Statement - AM'!EB87 -> 100757.24 | T39: ='Income Statement - AM'!EC87 -> 100757.24 | U39: ='Income Statement - AM'!ED87 -> 100757.24 | V39: ='Income Statement - AM'!EE87 -> 100757.24 | W39: ='Income Statement - AM'!EF87 -> 100757.24
B40: Sale Month | C40: =D44 -> #REF! | D40: =EOMONTH($D$32,C40) -> #REF! | F40: Soft Cost Contingency | I40: ='Draw Schedule'!C31 -> 0 | J40: =I40/$I$45 -> 0 | K40: =I40/$D$8 -> 0 | M40: Total Controllable Expenses | N40: =SUM(N32:N39) -> 0 | O40: =SUM(O32:O39) -> 67497.5 | P40: =SUM(P32:P39) -> 333451.67 | Q40: =SUM(Q32:Q39) -> 481339.58 | R40: =SUM(R32:R39) -> 490329.58 | S40: ='Income Statement - AM'!EB88 -> 64428.333 | T40: ='Income Statement - AM'!EC88 -> 65588.333 | U40: ='Income Statement - AM'!ED88 -> 66748.333 | V40: ='Income Statement - AM'!EE88 -> 67908.333 | W40: ='Income Statement - AM'!EF88 -> 69068.333
F41: Financing Costs | I41: ='Draw Schedule'!C45 -> 0 | J41: =I41/$I$45 -> 0 | K41: =I41/$D$8 -> 0 | S41: ='Income Statement - AM'!EB89 -> 845621.88 | T41: ='Income Statement - AM'!EC89 -> 860846.88 | U41: ='Income Statement - AM'!ED89 -> 876071.88 | V41: ='Income Statement - AM'!EE89 -> 891296.88 | W41: ='Income Statement - AM'!EF89 -> 906521.88
B42: Exit Assumptions | F42: Senior Interest Reserve | I42: ='Draw Schedule'!C49 -> 8500000 | J42: =I42/$I$45 -> 0.038400723 | K42: =I42/$D$8 -> 58620.69 | M42: Management Fee | N42: ='Income Statement - AM'!DW87 -> 0 | O42: ='Income Statement - AM'!DX87 -> 40724.272 | P42: ='Income Statement - AM'!DY87 -> 94655.536 | Q42: ='Income Statement - AM'!DZ87 -> 97030.163 | R42: ='Income Statement - AM'!EA87 -> 99559.051 | S42: ='Income Statement - AM'!EB90 -> 0 | T42: ='Income Statement - AM'!EC90 -> 0 | U42: ='Income Statement - AM'!ED90 -> 0 | V42: ='Income Statement - AM'!EE90 -> 0 | W42: ='Income Statement - AM'!EF90 -> 0
F43: Preferred Equity Interest Reserve | I43: 0 | J43: =I43/$I$45 -> 0 | K43: =I43/$D$8 -> 0 | M43: Insurance | N43: ='Income Statement - AM'!DW88 -> 0 | O43: ='Income Statement - AM'!DX88 -> 0 | P43: ='Income Statement - AM'!DY88 -> 35694.167 | Q43: ='Income Statement - AM'!DZ88 -> 62108.333 | R43: ='Income Statement - AM'!EA88 -> 63268.333 | S43: =SUM(S39:S42) -> 1010807.4 | T43: =SUM(T39:T42) -> 1027192.4 | U43: =SUM(U39:U42) -> 1043577.4 | V43: =SUM(V39:V42) -> 1059962.4 | W43: =SUM(W39:W42) -> 1076347.4
B44: Sale Month | D44: ='PERPETUITY MIDDLEMAN INPUT TAB'!#REF! -> #REF! | F44: Operating Reserve | I44: ='Draw Schedule'!C48 -> 850000 | J44: =I44/$I$45 -> 0.0038400723 | K44: =I44/$D$8 -> 5862.069 | M44: Property Taxes | N44: ='Income Statement - AM'!DW89 -> 0 | O44: ='Income Statement - AM'!DX89 -> 0 | P44: ='Income Statement - AM'!DY89 -> 468485.94 | Q44: ='Income Statement - AM'!DZ89 -> 815171.88 | R44: ='Income Statement - AM'!EA89 -> 830396.88
B45: Sale Date | D45: ='PERPETUITY MIDDLEMAN INPUT TAB'!#REF! -> #REF! | F45: Total Uses | I45: =SUM(I35:I44) -> 221350000 | J45: =SUM(J35:J44) -> 1 | K45: =SUM(K35:K44) -> 1526551.7 | M45: Other Taxes / Fees | N45: ='Income Statement - AM'!DW90 -> 0 | O45: ='Income Statement - AM'!DX90 -> 0 | P45: ='Income Statement - AM'!DY90 -> 0 | Q45: ='Income Statement - AM'!DZ90 -> 0 | R45: ='Income Statement - AM'!EA90 -> 0 | S45: ='Income Statement - AM'!EB97 -> 0 | T45: ='Income Statement - AM'!EC97 -> 0 | U45: ='Income Statement - AM'!ED97 -> 0 | V45: ='Income Statement - AM'!EE97 -> 0 | W45: ='Income Statement - AM'!EF97 -> 0
B46: NOI at Exit | D46: =D47*D50 -> #REF! | M46: Total Non-Controllable Expenses | N46: =SUM(N42:N45) -> 0 | O46: =SUM(O42:O45) -> 40724.272 | P46: =SUM(P42:P45) -> 598835.64 | Q46: =SUM(Q42:Q45) -> 974310.37 | R46: =SUM(R42:R45) -> 993224.26 | S46: =S45+S43+S37 -> 1510127 | T46: =T45+T43+T37 -> 1535502 | U46: =U45+U43+U37 -> 1560877 | V46: =V45+V43+V37 -> 1586252 | W46: =W45+W43+W37 -> 1611627
B47: Exit Cap Rate (Multifamily) | D47: ='PERPETUITY MIDDLEMAN INPUT TAB'!#REF! -> #REF! | F47: Joint Venture Waterfall
B48: Exit Cap Rate (Retail) | D48: ='PERPETUITY MIDDLEMAN INPUT TAB'!#REF! -> #REF! | M48: Replacement Reserves | N48: ='Income Statement - AM'!DW97 -> 0 | O48: ='Income Statement - AM'!DX97 -> 0 | P48: ='Income Statement - AM'!DY97 -> 0 | Q48: ='Income Statement - AM'!DZ97 -> 0 | R48: ='Income Statement - AM'!EA97 -> 0 | S48: =S26-S46 -> 1848447.5 | T48: =T26-T46 -> 1823072.5 | U48: =U26-U46 -> 1797697.5 | V48: =V26-V46 -> 1772322.5 | W48: =W26-W46 -> 1746947.5
F49: Waterfall | G49: ='AIRR Input Tab'!K18 -> Investar | H49: ='AIRR Input Tab'!L18 -> Ace | I49: ='AIRR Input Tab'!N18 -> Hurdle | J49: ='AIRR Input Tab'!O18 -> Multiple | K49: ='AIRR Input Tab'!P18 -> $ Amount | M49: Total Operating Expenses | N49: =N48+N46+N40 -> 0 | O49: =O48+O46+O40 -> 108221.77 | P49: =P48+P46+P40 -> 932287.31 | Q49: =Q48+Q46+Q40 -> 1455650 | R49: =R48+R46+R40 -> 1483553.8
B50: Gross Sale Price | D50: 250000000 | F50: Tier 1: | G50: ='AIRR Input Tab'!K21 -> 0.95 | H50: ='AIRR Input Tab'!L21 -> 0.05 | I50: ='AIRR Input Tab'!N21 -> 0 | J50: ='AIRR Input Tab'!O21 -> 0 | K50: ='AIRR Input Tab'!P21 -> 0 | S50: =S28-S48 -> -1848447.5 | T50: =T28-T48 -> -1823072.5 | U50: =U28-U48 -> -1797697.5 | V50: =V28-V48 -> -1772322.5 | W50: =W28-W48 -> -1746947.5
B51: Gross Sale Price / Unit | D51: =D50/H13 -> 454545.45 | F51: Tier 2: | G51: ='AIRR Input Tab'!K22 -> 0.8 | H51: ='AIRR Input Tab'!L22 -> 0.05 | I51: ='AIRR Input Tab'!N22 -> 0.08 | J51: ='AIRR Input Tab'!O22 -> 1 | K51: ='AIRR Input Tab'!P22 -> 0 | M51: Net Operating Income | N51: =N29-N49 -> -4.6566129e-10 | O51: =O29-O49 -> 1249254 | P51: =P29-P49 -> 2222897.2 | Q51: =Q29-Q49 -> 1778688.8 | R51: =R29-R49 -> 1835081.2
B52: Cost of Sale | C52: ='PERPETUITY MIDDLEMAN INPUT TAB'!#REF! -> #REF! | D52: =C52*D50 -> #REF! | F52: Tier 3: | G52: ='AIRR Input Tab'!K23 -> 0.7 | H52: ='AIRR Input Tab'!L23 -> 0.05 | I52: ='AIRR Input Tab'!N23 -> 0.1 | J52: ='AIRR Input Tab'!O23 -> 1 | K52: ='AIRR Input Tab'!P23 -> 0
B53: Net Sale Proceeds | D53: =D50-D52 -> #REF! | F53: Tier 4: | G53: ='AIRR Input Tab'!K24 -> 0.5 | H53: ='AIRR Input Tab'!L24 -> 0.05 | I53: ='AIRR Input Tab'!N24 -> 0.15 | J53: ='AIRR Input Tab'!O24 -> 1 | K53: ='AIRR Input Tab'!P24 -> 0 | M53: Return on Cost | N53: =N51/$I$45 -> -2.1037329e-18 | O53: =O51/$I$45 -> 0.0056437947 | P53: =P51/$I$45 -> 0.010042454 | Q53: =Q51/$I$45 -> 0.0080356395 | R53: =R51/$I$45 -> 0.0082904052
F54: Tier 5: | G54: ='AIRR Input Tab'!K25 -> 0.5 | H54: ='AIRR Input Tab'!L25 -> 0.05 | I54: ='AIRR Input Tab'!N25 -> 0.15 | J54: ='AIRR Input Tab'!O25 -> 1 | K54: ='AIRR Input Tab'!P25 -> 0
F55: Tier 6: | G55: ='AIRR Input Tab'!K26 -> 0.5 | H55: ='AIRR Input Tab'!L26 -> 0.05 | I55: ='AIRR Input Tab'!N26 -> 0.15 | J55: ='AIRR Input Tab'!O26 -> 1 | K55: ='AIRR Input Tab'!P26 -> 0
F57: Returns
H59: Unlevered | I59: Levered | J59: =G49 -> Investar | K59: =H49 -> Ace
F60: Investment | H60: =I45-I41-I42-I43 -> 212850000 | I60: =SUM(I29:I31) -> 88540000 | J60: =I30 -> 84113000 | K60: =I31 -> 4427000
F61: IRR | H61: 0.14 | I61: 0.2 | J61: 0.18 | K61: 0.3
F62: MOIC | H62: =(H60+H63)/H60 -> 1.1661153 | I62: =(I60+I63)/I60 -> 1.3993409 | J62: =(J60+J63)/J60 -> 1.4203588 | K62: =(K60+K63)/K60 -> 8.9868177
F63: Net Profit | H63: 35357642 | I63: 35357642 | J63: 35357642 | K63: 35357642
F64: Exit / Unit | H64: =$D$51 -> 454545.45 | I64: =$D$51 -> 454545.45 | J64: =$D$51 -> 454545.45 | K64: =$D$51 -> 454545.45
S66: Unlevered IRR
S77: Unlevered Equity Multiple
S78: Levered IRR
S79: Levered Equity Multiple
S80: Net Profit (Levered CF)
S108: Average Cash-on-Cash Return
S109: LP IRR
S110: LP MOIC
S111: GP IRR
S112: GP MOIC

Sheet Rent Roll -  Leasing Tracker

Sheet Net Operating Income Tracker
B2: ='Deal Landing Dashboard'!B2 -> West Village Complexes - Multifamily - New York
B5: Net Operating Income
B7: Total Units | C7: ='Deal Landing Dashboard'!$D$12 -> 145 | D7: ='Deal Landing Dashboard'!$D$12 -> 145 | E7: ='Deal Landing Dashboard'!$D$12 -> 145 | F7: ='Deal Landing Dashboard'!$D$12 -> 145 | G7: ='Deal Landing Dashboard'!$D$12 -> 145 | I7: ='Deal Landing Dashboard'!$D$12 -> 145
B8: Face Rents | C8: ='Income Statement - AM'!DW24 -> 1717.7779 | D8: ='Income Statement - AM'!DX24 -> 1756.9053 | E8: ='Income Statement - AM'!DY24 -> 1798.7185 | F8: ='Income Statement - AM'!DZ24 -> 1843.3656 | G8: ='Income Statement - AM'!EA24 -> 1891.0073 | I8: =J15 -> 3530
B9: Effective Rents | C9: ='Income Statement - AM'!DW32 -> 0 | D9: ='Income Statement - AM'!DX32 -> 1490.027 | E9: ='Income Statement - AM'!DY32 -> 2474.0368 | F9: ='Income Statement - AM'!DZ32 -> 1691.5041 | G9: ='Income Statement - AM'!EA32 -> 1735.2925 | I9: =SUM(I15:I16,I22:I25)/I7/12 -> #REF!
B10: Occupancy | C10: ='Income Statement - AM'!DW15 -> 0 | D10: ='Income Statement - AM'!DX15 -> 1 | E10: ='Income Statement - AM'!DY15 -> 1 | F10: ='Income Statement - AM'!DZ15 -> 1 | G10: ='Income Statement - AM'!EA15 -> 1 | I10: =1-J20 -> 0.94
B11: Rent Growth | C11: 0.05 | D11: 0.05 | E11: 0.05 | F11: 0.05 | G11: 0.05 | I11: --
B13: Actual / Forecast | C13: T12 | D13: T3 | E13: T1 | F13: F12 | G13: EXIT | I13: Custom Scenario | J13: Assumptions
B14: Date | C14: 45657 | D14: 45657 | E14: 45657 | F14: 46022 | G14: ='AIRR Model Summary'!E45 -> 48273
B15: Gross Potential Rent | C15: ='Income Statement - AM'!DW34 -> 2988933.6 | D15: ='Income Statement - AM'!DX34 -> 3057015.2 | E15: ='Income Statement - AM'!DY34 -> 3129770.1 | F15: ='Income Statement - AM'!DZ34 -> 3207456.2 | G15: ='Income Statement - AM'!EA34 -> 3290352.8 | I15: ='AIRR Model Summary'!I13*J15*12 -> 6142200 | J15: 3530
B16: Loss to Lease | C16: ='Income Statement - AM'!DW35 -> 0 | D16: ='Income Statement - AM'!DX35 -> 0 | E16: ='Income Statement - AM'!DY35 -> 0 | F16: ='Income Statement - AM'!DZ35 -> 0 | G16: ='Income Statement - AM'!EA35 -> 0 | I16: =-J16*I15 -> 0 | J16: 0
B17: Gross Potential Rent | C17: =SUM(C15:C16) -> 2988933.6 | D17: =SUM(D15:D16) -> 3057015.2 | E17: =SUM(E15:E16) -> 3129770.1 | F17: =SUM(F15:F16) -> 3207456.2 | G17: =SUM(G15:G16) -> 3290352.8 | I17: =SUM(I15:I16) -> 6142200
B18: Other Income | C18: ='Income Statement - AM'!DW55 -> 146788.47 | D18: ='Income Statement - AM'!DX55 -> 151253.18 | E18: ='Income Statement - AM'!DY55 -> 155853.69 | F18: ='Income Statement - AM'!DZ55 -> 160594.13 | G18: ='Income Statement - AM'!EA55 -> 165478.76 | I18: =VLOOKUP(B18,$B$13:$G$51,MATCH(J18,$B$13:$G$13,FALSE),FALSE) -> 165478.76 | J18: Exit
B19: Net Potential Income | C19: =C18+C17 -> 3135722 | D19: =D18+D17 -> 3208268.4 | E19: =E18+E17 -> 3285623.8 | F19: =F18+F17 -> 3368050.4 | G19: =G18+G17 -> 3455831.5 | I19: =I18+I17 -> 6307678.8
B20: Vacancy | C20: ='Income Statement - AM'!DW59 -> -3135722 | D20: ='Income Statement - AM'!DX59 -> -1605490.3 | E20: ='Income Statement - AM'!DY59 -> -98568.714 | F20: ='Income Statement - AM'!DZ59 -> -101041.51 | G20: ='Income Statement - AM'!EA59 -> -103674.95 | I20: =-J20*I19 -> -378460.73 | J20: 0.06
B21: Model Units | C21: ='Income Statement - AM'!DW60 -> 0 | D21: ='Income Statement - AM'!DX60 -> 0 | E21: ='Income Statement - AM'!DY60 -> 0 | F21: ='Income Statement - AM'!DZ60 -> 0 | G21: ='Income Statement - AM'!EA60 -> 0 | I21: =-J21*J15*12 -> -42360 | J21: 1
B22: Concessions - Lease Up (New) | C22: ='Income Statement - AM'!DW61 -> 0 | D22: ='Income Statement - AM'!DX61 -> -231590.51 | E22: ='Income Statement - AM'!DY61 -> 0 | F22: ='Income Statement - AM'!DZ61 -> 0 | G22: ='Income Statement - AM'!EA61 -> 0 | I22: =-J22*K22*$I$7*$J$15 -> #REF! | J22: 0 | K22: =1-'PERPETUITY MIDDLEMAN INPUT TAB'!#REF! -> #REF!
B23: Concessions - Lease Up (Renewal) | C23: ='Income Statement - AM'!DW62 -> 0 | D23: ='Income Statement - AM'!DX62 -> 0 | E23: ='Income Statement - AM'!DY62 -> 0 | F23: ='Income Statement - AM'!DZ62 -> 0 | G23: ='Income Statement - AM'!EA62 -> 0 | I23: =-J23*K23*$I$7*$J$15 -> #REF! | J23: 0 | K23: =1-$K$22 -> #REF!
B24: Concessions - Stabilized (New) | C24: ='Income Statement - AM'!DW63 -> 0 | D24: ='Income Statement - AM'!DX63 -> 0 | E24: ='Income Statement - AM'!DY63 -> 0 | F24: ='Income Statement - AM'!DZ63 -> 0 | G24: ='Income Statement - AM'!EA63 -> 0 | I24: =-J24*K24*$I$7*$J$15 -> #REF! | J24: 0.2 | K24: =K22 -> #REF!
B25: Concessions - Stabilized (Renewal) | C25: ='Income Statement - AM'!DW64 -> 0 | D25: ='Income Statement - AM'!DX64 -> 0 | E25: ='Income Statement - AM'!DY64 -> 0 | F25: ='Income Statement - AM'!DZ64 -> 0 | G25: ='Income Statement - AM'!EA64 -> 0 | I25: =-J25*K25*$I$7*$J$15 -> #REF! | J25: 0.5 | K25: =K23 -> #REF!
B26: Bad Debt | C26: ='Income Statement - AM'!DW65 -> 0 | D26: ='Income Statement - AM'!DX65 -> -13711.876 | E26: ='Income Statement - AM'!DY65 -> -31870.551 | F26: ='Income Statement - AM'!DZ65 -> -32670.089 | G26: ='Income Statement - AM'!EA65 -> -33521.566 | I26: =-J26*SUM(I19:I25) -> #REF! | J26: 0.0025
B27: Effective Gross Income (Multi) | C27: =SUM(C19:C26) -> -4.6566129e-10 | D27: =SUM(D19:D26) -> 1357475.7 | E27: =SUM(E19:E26) -> 3155184.5 | F27: =SUM(F19:F26) -> 3234338.8 | G27: =SUM(G19:G26) -> 3318635 | I27: =SUM(I19:I26) -> #REF!
B28: Retail | C28: ='Income Statement - AM'!DW67 -> 0 | D28: ='Income Statement - AM'!DX67 -> 0 | E28: ='Income Statement - AM'!DY67 -> 0 | F28: ='Income Statement - AM'!DZ67 -> 0 | G28: ='Income Statement - AM'!EA67 -> 0 | I28: =VLOOKUP(B28,$B$13:$G$51,MATCH(J28,$B$13:$G$13,FALSE),FALSE) -> 0 | J28: Exit
B29: Effective Gross Income (Total) | C29: =C28+C27 -> -4.6566129e-10 | D29: =D28+D27 -> 1357475.7 | E29: =E28+E27 -> 3155184.5 | F29: =F28+F27 -> 3234338.8 | G29: =G28+G27 -> 3318635 | I29: =I28+I27 -> #REF!
B31: Controllable Expenses
B32: Payroll | C32: ='Income Statement - AM'!DW77 -> 0 | D32: ='Income Statement - AM'!DX77 -> 0 | E32: ='Income Statement - AM'!DY77 -> 133853.12 | F32: ='Income Statement - AM'!DZ77 -> 232906.25 | G32: ='Income Statement - AM'!EA77 -> 237256.25 | I32: =VLOOKUP(B32,$B$13:$G$51,MATCH(J32,$B$13:$G$13,FALSE),FALSE) -> 237256.25 | J32: Exit
B33: Utilities | C33: ='Income Statement - AM'!DW78 -> 0 | D33: ='Income Statement - AM'!DX78 -> 7499.7222 | E33: ='Income Statement - AM'!DY78 -> 15237.083 | F33: ='Income Statement - AM'!DZ78 -> 15527.083 | G33: ='Income Statement - AM'!EA78 -> 15817.083 | I33: =VLOOKUP(B33,$B$13:$G$51,MATCH(J33,$B$13:$G$13,FALSE),FALSE) -> 15817.083 | J33: Exit
B34: Turnover | C34: ='Income Statement - AM'!DW79 -> 0 | D34: ='Income Statement - AM'!DX79 -> 22499.167 | E34: ='Income Statement - AM'!DY79 -> 45711.25 | F34: ='Income Statement - AM'!DZ79 -> 46581.25 | G34: ='Income Statement - AM'!EA79 -> 47451.25 | I34: =VLOOKUP(B34,$B$13:$G$51,MATCH(J34,$B$13:$G$13,FALSE),FALSE) -> 47451.25 | J34: Exit
B35: Contract Services | C35: ='Income Statement - AM'!DW80 -> 0 | D35: ='Income Statement - AM'!DX80 -> 0 | E35: ='Income Statement - AM'!DY80 -> 13385.312 | F35: ='Income Statement - AM'!DZ80 -> 23290.625 | G35: ='Income Statement - AM'!EA80 -> 23725.625 | I35: =VLOOKUP(B35,$B$13:$G$51,MATCH(J35,$B$13:$G$13,FALSE),FALSE) -> 23725.625 | J35: Exit
B36: Repairs and Maintenance | C36: ='Income Statement - AM'!DW81 -> 0 | D36: ='Income Statement - AM'!DX81 -> 37498.611 | E36: ='Income Statement - AM'!DY81 -> 76185.417 | F36: ='Income Statement - AM'!DZ81 -> 77635.417 | G36: ='Income Statement - AM'!EA81 -> 79085.417 | I36: =VLOOKUP(B36,$B$13:$G$51,MATCH(J36,$B$13:$G$13,FALSE),FALSE) -> 79085.417 | J36: Exit
B37: Leasing and Marketing | C37: ='Income Statement - AM'!DW82 -> 0 | D37: ='Income Statement - AM'!DX82 -> 0 | E37: ='Income Statement - AM'!DY82 -> 22308.854 | F37: ='Income Statement - AM'!DZ82 -> 38817.708 | G37: ='Income Statement - AM'!EA82 -> 39542.708 | I37: =VLOOKUP(B37,$B$13:$G$51,MATCH(J37,$B$13:$G$13,FALSE),FALSE) -> 39542.708 | J37: Exit
B38: General and Administrative | C38: ='Income Statement - AM'!DW83 -> 0 | D38: ='Income Statement - AM'!DX83 -> 0 | E38: ='Income Statement - AM'!DY83 -> 26770.625 | F38: ='Income Statement - AM'!DZ83 -> 46581.25 | G38: ='Income Statement - AM'!EA83 -> 47451.25 | I38: =VLOOKUP(B38,$B$13:$G$51,MATCH(J38,$B$13:$G$13,FALSE),FALSE) -> 47451.25 | J38: Exit
B39: Other Expenses | C39: ='Income Statement - AM'!DW84 -> 0 | D39: ='Income Statement - AM'!DX84 -> 0 | E39: ='Income Statement - AM'!DY84 -> 0 | F39: ='Income Statement - AM'!DZ84 -> 0 | G39: ='Income Statement - AM'!EA84 -> 0 | I39: =VLOOKUP(B39,$B$13:$G$51,MATCH(J39,$B$13:$G$13,FALSE),FALSE) -> 0 | J39: Exit
B40: Total Controllable Expenses | C40: =SUM(C32:C39) -> 0 | D40: =SUM(D32:D39) -> 67497.5 | E40: =SUM(E32:E39) -> 333451.67 | F40: =SUM(F32:F39) -> 481339.58 | G40: =SUM(G32:G39) -> 490329.58 | I40: =SUM(I32:I39) -> 490329.58
B42: Management Fee | C42: ='Income Statement - AM'!DW87 -> 0 | D42: ='Income Statement - AM'!DX87 -> 40724.272 | E42: ='Income Statement - AM'!DY87 -> 94655.536 | F42: ='Income Statement - AM'!DZ87 -> 97030.163 | G42: ='Income Statement - AM'!EA87 -> 99559.051 | I42: =VLOOKUP(B42,$B$13:$G$51,MATCH(J42,$B$13:$G$13,FALSE),FALSE) -> 99559.051 | J42: Exit
B43: Insurance | C43: ='Income Statement - AM'!DW88 -> 0 | D43: ='Income Statement - AM'!DX88 -> 0 | E43: ='Income Statement - AM'!DY88 -> 35694.167 | F43: ='Income Statement - AM'!DZ88 -> 62108.333 | G43: ='Income Statement - AM'!EA88 -> 63268.333 | I43: =VLOOKUP(B43,$B$13:$G$51,MATCH(J43,$B$13:$G$13,FALSE),FALSE) -> 63268.333 | J43: Exit
B44: Property Taxes | C44: ='Income Statement - AM'!DW89 -> 0 | D44: ='Income Statement - AM'!DX89 -> 0 | E44: ='Income Statement - AM'!DY89 -> 468485.94 | F44: ='Income Statement - AM'!DZ89 -> 815171.88 | G44: ='Income Statement - AM'!EA89 -> 830396.88 | I44: =VLOOKUP(B44,$B$13:$G$51,MATCH(J44,$B$13:$G$13,FALSE),FALSE) -> 830396.88 | J44: Exit
B45: Other Taxes / Fees | C45: ='Income Statement - AM'!DW90 -> 0 | D45: ='Income Statement - AM'!DX90 -> 0 | E45: ='Income Statement - AM'!DY90 -> 0 | F45: ='Income Statement - AM'!DZ90 -> 0 | G45: ='Income Statement - AM'!EA90 -> 0 | I45: =VLOOKUP(B45,$B$13:$G$51,MATCH(J45,$B$13:$G$13,FALSE),FALSE) -> 0 | J45: Exit
B46: Total Non-Controllable Expenses | C46: =SUM(C42:C45) -> 0 | D46: =SUM(D42:D45) -> 40724.272 | E46: =SUM(E42:E45) -> 598835.64 | F46: =SUM(F42:F45) -> 974310.37 | G46: =SUM(G42:G45) -> 993224.26 | I46: =SUM(I42:I45) -> 993224.26
B48: Replacement Reserves | C48: ='Income Statement - AM'!DW97 -> 0 | D48: ='Income Statement - AM'!DX97 -> 0 | E48: ='Income Statement - AM'!DY97 -> 0 | F48: ='Income Statement - AM'!DZ97 -> 0 | G48: ='Income Statement - AM'!EA97 -> 0 | I48: =VLOOKUP(B48,$B$13:$G$51,MATCH(J48,$B$13:$G$13,FALSE),FALSE) -> 0 | J48: Exit
B49: Total Operating Expenses | C49: =C48+C46+C40 -> 0 | D49: =D48+D46+D40 -> 108221.77 | E49: =E48+E46+E40 -> 932287.31 | F49: =F48+F46+F40 -> 1455650 | G49: =G48+G46+G40 -> 1483553.8 | I49: =I48+I46+I40 -> 1483553.8
B51: Net Operating Income | C51: =C29-C49 -> -4.6566129e-10 | D51: =D29-D49 -> 1249254 | E51: =E29-E49 -> 2222897.2 | F51: =F29-F49 -> 1778688.8 | G51: =G29-G49 -> 1835081.2 | I51: =I29-I49 -> #REF!
B53: Return on Cost | C53: =C51/'AIRR Model Summary'!$J$53 -> -1.2543e-17 | D53: =D51/'AIRR Model Summary'!$J$53 -> 0.033649764 | E53: =E51/'AIRR Model Summary'!$J$53 -> 0.05987571 | F53: =F51/'AIRR Model Summary'!$J$53 -> 0.047910562 | G53: =G51/'AIRR Model Summary'!$J$53 -> 0.04942954 | I53: =I51/'AIRR Model Summary'!$J$53 -> #REF!

Sheet AIRR Model vs. UW Model
B2: ='Performance Dashboard'!B3 -> West Village Complexes - Multifamily - New York
B5: Sources and Uses | I5: Exit Assumptions
B7: Sources | C7: Underwriting | E7: AIRR Model | G7: Variance | J7: Underwriting | K7: AIRR Model | L7: Variance
B8: Senior Debt | C8: 50000000 | E8: 50000000 | G8: =E8-C8 -> 0 | I8: Sale Month | J8: ='Underwriting Model Summary'!D44 -> #REF! | K8: ='AIRR Model Summary'!E44 -> 96 | L8: =K8-J8 -> #REF!
B9: Preferred Equity | C9: 50000000 | E9: 50000000 | G9: =E9-C9 -> 0 | I9: Sale Date | J9: ='Underwriting Model Summary'!D45 -> #REF! | K9: ='AIRR Model Summary'!E45 -> 48273 | L9: =K9-J9 -> #REF!
B10: LP Equity - JV | C10: 50000000 | E10: 50000000 | G10: =E10-C10 -> 0 | I10: NOI at Exit | J10: ='Underwriting Model Summary'!D46 -> #REF! | K10: ='AIRR Model Summary'!E46 -> 2219682.8 | L10: =K10-J10 -> #REF!
B11: GP Equity - JV | C11: 50000000 | E11: 50000000 | G11: =E11-C11 -> 0 | I11: Exit Cap Rate (Multifamily) | J11: ='Underwriting Model Summary'!D47 -> #REF! | K11: ='AIRR Model Summary'!E47 -> 0.06 | L11: =K11-J11 -> #REF!
B12: LP Equity - Priority Capital | C12: 50000000 | E12: 50000000 | G12: =E12-C12 -> 0 | I12: Exit Cap Rate (Retail) | J12: ='Underwriting Model Summary'!D48 -> #REF! | K12: ='AIRR Model Summary'!E48 -> 0.06 | L12: =K12-J12 -> #REF!
B13: GP Equity - Priority Capital | C13: 50000000 | E13: 50000000 | G13: =E13-C13 -> 0
B14: Total Uses | C14: =SUM(C8:C13) -> 300000000 | E14: =SUM(E8:E13) -> 300000000 | G14: =E14-C14 -> 0 | I14: Gross Sale Price | J14: ='Underwriting Model Summary'!D50 -> 250000000 | K14: ='AIRR Model Summary'!E50 -> 36994714 | L14: =K14-J14 -> -2.1300529e+08
I15: Gross Sale Price / Unit | J15: ='Underwriting Model Summary'!D51 -> 454545.45 | K15: ='AIRR Model Summary'!E51 -> 255135.96 | L15: =K15-J15 -> -199409.5
B16: Uses | C16: Underwriting | E16: AIRR Model | G16: Variance | I16: Cost of Sale | J16: ='Underwriting Model Summary'!D52 -> #REF! | K16: ='AIRR Model Summary'!E52 -> 369947.14 | L16: =K16-J16 -> #REF!
B17: Land Acquisition Costs | C17: 50000000 | E17: 50000000 | G17: =E17-C17 -> 0 | I17: Net Sale Proceeds | J17: ='Underwriting Model Summary'!D53 -> #REF! | K17: ='AIRR Model Summary'!E53 -> 36624767 | L17: =K17-J17 -> #REF!
B18: Closing Costs | C18: 50000000 | E18: 50000000 | G18: =E18-C18 -> 0
B19: Hard Costs | C19: 50000000 | E19: 50000000 | G19: =E19-C19 -> 0 | I19: Returns
B20: Soft Costs | C20: 50000000 | E20: 50000000 | G20: =E20-C20 -> 0
B21: Contingency | C21: 50000000 | E21: 50000000 | G21: =E21-C21 -> 0 | J21: Underwriting | K21: AIRR Model | L21: Variance
B22: Financing Fees | C22: 50000000 | E22: 50000000 | G22: =E22-C22 -> 0 | I22: Unlevered IRR | J22: ='Underwriting Model Summary'!H61 -> 0.14 | K22: ='AIRR Model Summary'!I69 -> 0.074705151 | L22: =K22-J22 -> -0.065294849
B23: Senior Interest Reserve | C23: 50000000 | E23: 50000000 | G23: =E23-C23 -> 0 | I23: Unlevered Equity Multiple | J23: ='Underwriting Model Summary'!H62 -> 1.1661153 | K23: ='AIRR Model Summary'!I70 -> 1.5855607 | L23: =K23-J23 -> 0.41944539
B24: Mezzanine Interest Reserve | C24: 50000000 | E24: 50000000 | G24: =E24-C24 -> 0 | I24: Levered IRR | J24: ='Underwriting Model Summary'!I61 -> 0.2 | K24: ='AIRR Model Summary'!J69 -> 0.048843762 | L24: =K24-J24 -> -0.15115624
B25: Operating Reserve | C25: 50000000 | E25: 50000000 | G25: =E25-C25 -> 0 | I25: Levered Equity Multiple | J25: ='Underwriting Model Summary'!I62 -> 1.3993409 | K25: ='AIRR Model Summary'!J70 -> 1.4622176 | L25: =K25-J25 -> 0.062876666
B26: Total Uses | C26: =SUM(C17:C25) -> 450000000 | E26: =SUM(E17:E25) -> 450000000 | G26: =E26-C26 -> 0 | I26: LP IRR | J26: ='Underwriting Model Summary'!J61 -> 0.18 | K26: ='AIRR Model Summary'!K69 -> 0.046859661 | L26: =K26-J26 -> -0.13314034
I27: LP MOIC | J27: ='Underwriting Model Summary'!J62 -> 1.4203588 | K27: ='AIRR Model Summary'!K70 -> 1.440323 | L27: =K27-J27 -> 0.019964207
B28: Rents | I28: GP IRR | J28: ='Underwriting Model Summary'!K61 -> 0.3 | K28: ='Underwriting Model Summary'!K61 -> 0.3 | L28: =K28-J28 -> 0
I29: GP MOIC | J29: ='Underwriting Model Summary'!K62 -> 8.9868177 | K29: ='Underwriting Model Summary'!K62 -> 8.9868177 | L29: =K29-J29 -> 0
B30: Month 48 | I30: Exit Price / Unit | J30: ='AIRR Model Summary'!K72 -> 255135.96 | K30: =J30 -> 255135.96 | L30: =K30-J30 -> 0
B31: Face Rents
B32: Unit Type | C32: # of Units | D32: SF | E32: Underwriting | F32: AIRR Model | G32: Variance | I32: NOI Comparison
B33: Studio | C33: 50 | D33: 600 | E33: 1425 | F33: 1425 | G33: =F33-E33 -> 0
B34: 1BR/1BA | C34: 50 | D34: 600 | E34: 1425 | F34: 1425 | G34: =F34-E34 -> 0 | I34: Sale | J34: Underwriting | K34: AIRR Model | L34: Variance
B35: 2BR/1BA | C35: 20 | D35: 725 | E35: 1600 | F35: 1600 | G35: =F35-E35 -> 0 | I35: Month | J35: ='Underwriting Model Summary'!D44 -> #REF! | K35: ='AIRR Model Summary'!E44 -> 96 | L35: =K35-J35 -> #REF!
B36: 2BR/2BA | C36: 65 | D36: 875 | E36: 1875 | F36: 1875 | G36: =F36-E36 -> 0 | I36: Date | J36: ='Underwriting Model Summary'!D45 -> #REF! | K36: ='AIRR Model Summary'!E45 -> 48273 | L36: =K36-J36 -> #REF!
B37: 3BR/2BA | C37: 10 | D37: 1025 | E37: 2100 | F37: 2100 | G37: =F37-E37 -> 0 | I37: Face Rents | J37: ='Underwriting Model Summary'!R7 -> 1891.0073 | K37: ='AIRR Model Summary'!T7 -> 1891.0073 | L37: =K37-J37 -> 0
B38: Total / Average | C38: =SUM(C33:C37) -> 195 | D38: =SUMPRODUCT(C33:C37,D33:D37)/C38 -> 726.28205 | E38: =SUMPRODUCT(C33:C37,E33:E37)/C38 -> 1627.5641 | F38: =SUMPRODUCT(C33:C37,F33:F37)/C38 -> 1627.5641 | G38: =F38-E38 -> 0 | I38: Effective Rents | J38: ='Underwriting Model Summary'!R8 -> 1735.2925 | K38: ='AIRR Model Summary'!T8 -> 1735.2925 | L38: =K38-J38 -> 0
I39: Occupancy | J39: ='Underwriting Model Summary'!R9 -> 1 | K39: ='AIRR Model Summary'!T9 -> 1 | L39: =K39-J39 -> 0
B40: Effective Rents | I40: Gross Potential Rent | J40: ='Underwriting Model Summary'!R15 -> 3290352.8 | K40: ='AIRR Model Summary'!T15 -> 3290352.8 | L40: =K40-J40 -> 0
B41: Unit Type | C41: # of Units | D41: SF | E41: Underwriting | F41: AIRR Model | G41: Variance | I41: Loss to Lease | J41: ='Underwriting Model Summary'!R16 -> 0 | K41: ='AIRR Model Summary'!T16 -> 0 | L41: =K41-J41 -> 0
B42: Studio | C42: 50 | D42: 600 | E42: 1425 | F42: 1425 | G42: =F42-E42 -> 0 | I42: Gross Potential Rent | J42: =SUM(J40:J41) -> 3290352.8 | K42: =SUM(K40:K41) -> 3290352.8 | L42: =K42-J42 -> 0
B43: 1BR/1BA | C43: 50 | D43: 600 | E43: 1425 | F43: 1425 | G43: =F43-E43 -> 0 | I43: Other Income | J43: ='Underwriting Model Summary'!R18 -> 165478.76 | K43: ='AIRR Model Summary'!T18 -> 165478.76 | L43: =K43-J43 -> 0
B44: 2BR/1BA | C44: 20 | D44: 725 | E44: 1600 | F44: 1600 | G44: =F44-E44 -> 0 | I44: Net Potential Income | J44: =J43+J42 -> 3455831.5 | K44: =K43+K42 -> 3455831.5 | L44: =K44-J44 -> 0
B45: 2BR/2BA | C45: 65 | D45: 875 | E45: 1875 | F45: 1875 | G45: =F45-E45 -> 0 | I45: Vacancy | J45: ='Underwriting Model Summary'!R20 -> -103674.95 | K45: ='AIRR Model Summary'!T20 -> -103674.95 | L45: =K45-J45 -> 0
B46: 3BR/2BA | C46: 10 | D46: 1025 | E46: 2100 | F46: 2100 | G46: =F46-E46 -> 0 | I46: Model Units | J46: ='Underwriting Model Summary'!R21 -> 0 | K46: ='AIRR Model Summary'!T21 -> 0 | L46: =K46-J46 -> 0
B47: Total / Average | C47: =SUM(C42:C46) -> 195 | D47: =SUMPRODUCT(C42:C46,D42:D46)/C47 -> 726.28205 | E47: =SUMPRODUCT(C42:C46,E42:E46)/C47 -> 1627.5641 | F47: =SUMPRODUCT(C42:C46,F42:F46)/C47 -> 1627.5641 | G47: =F47-E47 -> 0 | I47: Concessions - Lease Up (New) | J47: ='Underwriting Model Summary'!R22 -> 0 | K47: ='AIRR Model Summary'!T22 -> 0 | L47: =K47-J47 -> 0
I48: Concessions - Lease Up (Renewal) | J48: ='Underwriting Model Summary'!R23 -> 0 | K48: ='AIRR Model Summary'!T23 -> 0 | L48: =K48-J48 -> 0
B49: Key Dates and Assumptions | I49: Concessions - Stabilized (New) | J49: ='Underwriting Model Summary'!R24 -> 0 | K49: ='AIRR Model Summary'!T24 -> 0 | L49: =K49-J49 -> 0
I50: Concessions - Stabilized (Renewal) | J50: ='Underwriting Model Summary'!R25 -> 0 | K50: ='AIRR Model Summary'!T25 -> 0 | L50: =K50-J50 -> 0
C51: Underwriting | E51: AIRR Model | G51: Variance | I51: Bad Debt | J51: ='Underwriting Model Summary'!R26 -> -33521.566 | K51: ='AIRR Model Summary'!T26 -> -33521.566 | L51: =K51-J51 -> 0
B52: Land and JV Closing | C52: ='Underwriting Model Summary'!C32 -> 0 | E52: ='AIRR Model Summary'!D32 -> 0 | G52: =E52-C52 -> 0 | I52: Effective Gross Income (Multi) | J52: =SUM(J44:J51) -> 3318635 | K52: =SUM(K44:K51) -> 3318635 | L52: =K52-J52 -> 0
B53: Construction Start | C53: ='Underwriting Model Summary'!C33 -> 0 | E53: ='AIRR Model Summary'!D33 -> 0 | G53: =E53-C53 -> 0 | I53: Retail | J53: ='Income Statement - AM'!#REF! -> #REF! | K53: ='AIRR Model Summary'!T28 -> 0 | L53: =K53-J53 -> #REF!
B54: Construction Completion | C54: ='Underwriting Model Summary'!C34 -> #REF! | E54: ='AIRR Model Summary'!D34 -> 25 | G54: =E54-C54 -> #REF! | I54: Effective Gross Income (Total) | J54: =J53+J52 -> #REF! | K54: =K53+K52 -> 3318635 | L54: =K54-J54 -> #REF!
B55: First Units Delivered | C55: ='Underwriting Model Summary'!C35 -> #REF! | E55: ='AIRR Model Summary'!D35 -> 14 | G55: =E55-C55 -> #REF!
B56: Absorption Start | C56: ='Underwriting Model Summary'!C36 -> #REF! | E56: ='AIRR Model Summary'!D36 -> 14 | G56: =E56-C56 -> #REF! | I56: Controllable Expenses | J56: ='Underwriting Model Summary'!R31 -> 0 | K56: ='AIRR Model Summary'!T31 -> 0 | L56: =K56-J56 -> 0
B57: NOI Breakeven | C57: ='Underwriting Model Summary'!C37 -> 36 | E57: ='AIRR Model Summary'!D37 -> 36 | G57: =E57-C57 -> 0 | I57: Payroll | J57: ='Underwriting Model Summary'!R32 -> 237256.25 | K57: ='AIRR Model Summary'!T32 -> 237256.25 | L57: =K57-J57 -> 0
B58: Debt Service Breakeven | C58: ='Underwriting Model Summary'!C38 -> 40 | E58: ='AIRR Model Summary'!D38 -> 40 | G58: =E58-C58 -> 0 | I58: Utilities | J58: ='Underwriting Model Summary'!R33 -> 15817.083 | K58: ='AIRR Model Summary'!T33 -> 15817.083 | L58: =K58-J58 -> 0
B59: Stabilization | C59: ='Underwriting Model Summary'!C39 -> 46 | E59: ='AIRR Model Summary'!D39 -> 46 | G59: =E59-C59 -> 0 | I59: Turnover | J59: ='Underwriting Model Summary'!R34 -> 47451.25 | K59: ='AIRR Model Summary'!T34 -> 47451.25 | L59: =K59-J59 -> 0
B60: Loan Maturity | G60: =E60-C60 -> 0 | I60: Contract Services | J60: ='Underwriting Model Summary'!R35 -> 23725.625 | K60: ='AIRR Model Summary'!T35 -> 23725.625 | L60: =K60-J60 -> 0
B61: Sale Month | C61: ='Underwriting Model Summary'!C40 -> #REF! | E61: ='AIRR Model Summary'!D40 -> 96 | G61: =E61-C61 -> #REF! | I61: Repairs and Maintenance | J61: ='Underwriting Model Summary'!R36 -> 79085.417 | K61: ='AIRR Model Summary'!T36 -> 79085.417 | L61: =K61-J61 -> 0
I62: Leasing and Marketing | J62: ='Underwriting Model Summary'!R37 -> 39542.708 | K62: ='AIRR Model Summary'!T37 -> 39542.708 | L62: =K62-J62 -> 0
I63: General and Administrative | J63: ='Underwriting Model Summary'!R38 -> 47451.25 | K63: ='AIRR Model Summary'!T38 -> 47451.25 | L63: =K63-J63 -> 0
I64: Other Expenses | J64: ='Underwriting Model Summary'!R39 -> 0 | K64: ='AIRR Model Summary'!T39 -> 0 | L64: =K64-J64 -> 0
I65: Total Controllable Expenses | J65: =SUM(J57:J64) -> 490329.58 | K65: =SUM(K57:K64) -> 490329.58 | L65: =K65-J65 -> 0
I67: Management Fee | J67: ='Underwriting Model Summary'!R42 -> 99559.051 | K67: ='AIRR Model Summary'!T42 -> 99559.051 | L67: =K67-J67 -> 0
I68: Insurance | J68: ='Underwriting Model Summary'!R43 -> 63268.333 | K68: ='AIRR Model Summary'!T43 -> 63268.333 | L68: =K68-J68 -> 0
I69: Property Taxes | J69: ='Underwriting Model Summary'!R44 -> 830396.88 | K69: ='AIRR Model Summary'!T44 -> 830396.88 | L69: =K69-J69 -> 0
I70: Other Taxes / Fees | J70: ='Underwriting Model Summary'!R45 -> 0 | K70: ='AIRR Model Summary'!T45 -> 0 | L70: =K70-J70 -> 0
I71: Total Non-Controllable Expenses | J71: =SUM(J67:J70) -> 993224.26 | K71: =SUM(K67:K70) -> 993224.26 | L71: =K71-J71 -> 0
I73: Replacement Reserves | J73: ='Underwriting Model Summary'!R48 -> 0 | K73: ='AIRR Model Summary'!T48 -> 0 | L73: =K73-J73 -> 0
I74: Total Operating Expenses | J74: =J73+J71+J65 -> 1483553.8 | K74: =K73+K71+K65 -> 1483553.8 | L74: =K74-J74 -> 0
L75: =K75-J75 -> 0
I76: Net Operating Income | J76: =J54-J74 -> #REF! | K76: =K54-K74 -> 1835081.2 | L76: =K76-J76 -> #REF!

Sheet Senior Loan and Refinancing
B2: ='Deal Landing Dashboard'!B2 -> West Village Complexes - Multifamily - New York
B5: Senior Loan Terms | I5: Covenants and Extension Tests
B7: Loan to Cost % | G7: ='AIRR Input Tab'!D42 -> 0.6 | O7: ='Income Statement - AM'!EB24 -> 1913.5986 | P7: ='Income Statement - AM'!EC24 -> 1913.5986 | Q7: ='Income Statement - AM'!ED24 -> 1913.5986 | R7: ='Income Statement - AM'!EE24 -> 1913.5986 | S7: ='Income Statement - AM'!EF24 -> 1913.5986
B8: Initial Term | G8: ='AIRR Input Tab'!D50 -> 48 | I8: Test | J8: Test #1 | K8: Test #2 | L8: Initial Maturity | M8: Test #2 | N8: Final Maturity | O8: ='Income Statement - AM'!EB32 -> 1754.132 | P8: ='Income Statement - AM'!EC32 -> 1754.132 | Q8: ='Income Statement - AM'!ED32 -> 1754.132 | R8: ='Income Statement - AM'!EE32 -> 1754.132 | S8: ='Income Statement - AM'!EF32 -> 1754.132
B9: Interest Type - Fixed/Floating | G9: ='AIRR Input Tab'!D43 -> Floating | I9: Month | J9: 36 | K9: =J9+6 -> 42 | L9: =K9+6 -> 48 | M9: =L9+6 -> 54 | N9: =M9+6 -> 60 | O9: ='Income Statement - AM'!EB15 -> 1 | P9: ='Income Statement - AM'!EC15 -> 1 | Q9: ='Income Statement - AM'!ED15 -> 1 | R9: ='Income Statement - AM'!EE15 -> 1 | S9: ='Income Statement - AM'!EF15 -> 1
B10: SOFR Spread | G10: ='AIRR Input Tab'!D45 -> 0.025 | I10: Date | J10: 4/31/25 | K10: 4/31/25 | L10: 4/31/25 | M10: 4/31/25 | N10: 4/31/25
B11: SOFR Floor | G11: ='AIRR Input Tab'!D46 -> 0 | O11: =N9+1 -> 61 | P11: =O11+1 -> 62 | Q11: =P11+1 -> 63 | R11: =Q11+1 -> 64 | S11: =R11+1 -> 65
B12: Interest Only Period | G12: ='AIRR Input Tab'!D48 -> 36 | I12: Outstanding Loan Amount | J12: 143000000 | K12: 143000000 | L12: 143000000 | M12: 143000000 | N12: 143000000 | O12: ='Income Statement - AM'!EB34 -> 3329661.5 | P12: ='Income Statement - AM'!EC34 -> 3329661.5 | Q12: ='Income Statement - AM'!ED34 -> 3329661.5 | R12: ='Income Statement - AM'!EE34 -> 3329661.5 | S12: ='Income Statement - AM'!EF34 -> 3329661.5
B13: Amortization Schedule | G13: ='AIRR Input Tab'!D49 -> 30 | O13: ='Income Statement - AM'!EB35 -> 0 | P13: ='Income Statement - AM'!EC35 -> 0 | Q13: ='Income Statement - AM'!ED35 -> 0 | R13: ='Income Statement - AM'!EE35 -> 0 | S13: ='Income Statement - AM'!EF35 -> 0
I14: Projected Occupancy | J14: ='Income Statement - AM'!DW15 -> 0 | K14: ='Income Statement - AM'!DX15 -> 1 | L14: ='Income Statement - AM'!DY15 -> 1 | M14: ='Income Statement - AM'!DZ15 -> 1 | N14: ='Income Statement - AM'!EA15 -> 1 | O14: =SUM(O12:O13) -> 3329661.5 | P14: =SUM(P12:P13) -> 3329661.5 | Q14: =SUM(Q12:Q13) -> 3329661.5 | R14: =SUM(R12:R13) -> 3329661.5 | S14: =SUM(S12:S13) -> 3329661.5
B15: DSCR / DY Covenants | I15: Face Rents | J15: ='Income Statement - AM'!DW24 -> 1717.7779 | K15: ='Income Statement - AM'!DX24 -> 1756.9053 | L15: ='Income Statement - AM'!DY24 -> 1798.7185 | M15: ='Income Statement - AM'!DZ24 -> 1843.3656 | N15: ='Income Statement - AM'!EA24 -> 1891.0073 | O15: ='Income Statement - AM'!EB55 -> 167760.7 | P15: ='Income Statement - AM'!EC55 -> 167760.7 | Q15: ='Income Statement - AM'!ED55 -> 167760.7 | R15: ='Income Statement - AM'!EE55 -> 167760.7 | S15: ='Income Statement - AM'!EF55 -> 167760.7
I16: Effective Rents | J16: ='Income Statement - AM'!DW32 -> 0 | K16: ='Income Statement - AM'!DX32 -> 1490.027 | L16: ='Income Statement - AM'!DY32 -> 2474.0368 | M16: ='Income Statement - AM'!DZ32 -> 1691.5041 | N16: ='Income Statement - AM'!EA32 -> 1735.2925 | O16: =O15+O14 -> 3497422.2 | P16: =P15+P14 -> 3497422.2 | Q16: =Q15+Q14 -> 3497422.2 | R16: =R15+R14 -> 3497422.2 | S16: =S15+S14 -> 3497422.2
C17: NOI | D17: Occupancy | E17: DSCR | F17: DY | G17: LTV | I17: Projected NOI (Bank Defined) | J17: =SUM(J43:J44) -> 2988933.6 | K17: =SUM(K43:K44) -> 3057015.2 | L17: =SUM(L43:L44) -> 3129770.1 | M17: =SUM(M43:M44) -> 3207456.2 | N17: =SUM(N43:N44) -> 3290352.8 | O17: ='Income Statement - AM'!EB59 -> -104922.67 | P17: ='Income Statement - AM'!EC59 -> -104922.67 | Q17: ='Income Statement - AM'!ED59 -> -104922.67 | R17: ='Income Statement - AM'!EE59 -> -104922.67 | S17: ='Income Statement - AM'!EF59 -> -104922.67
B18: 36 | C18: T3 | D18: - | E18: 1 | F18: - | G18: - | I18: NOI Type | J18: T3 | K18: T3 | L18: T6 | M18: T6 | N18: - | O18: ='Income Statement - AM'!EB60 -> 0 | P18: ='Income Statement - AM'!EC60 -> 0 | Q18: ='Income Statement - AM'!ED60 -> 0 | R18: ='Income Statement - AM'!EE60 -> 0 | S18: ='Income Statement - AM'!EF60 -> 0
B19: =B18+6 -> 42 | C19: T3 | D19: - | E19: 1.1 | F19: - | G19: - | O19: ='Income Statement - AM'!EB61 -> 0 | P19: ='Income Statement - AM'!EC61 -> 0 | Q19: ='Income Statement - AM'!ED61 -> 0 | R19: ='Income Statement - AM'!EE61 -> 0 | S19: ='Income Statement - AM'!EF61 -> 0
B20: =B19+6 -> 48 | C20: T6 | D20: - | E20: 1.2 | F20: - | G20: 0.55 | I20: DSCR Test | O20: ='Income Statement - AM'!EB62 -> 0 | P20: ='Income Statement - AM'!EC62 -> 0 | Q20: ='Income Statement - AM'!ED62 -> 0 | R20: ='Income Statement - AM'!EE62 -> 0 | S20: ='Income Statement - AM'!EF62 -> 0
B21: =B20+6 -> 54 | C21: T6 | D21: - | E21: 1.2 | F21: - | G21: - | I21: DSCR Test | J21: 1 | K21: 1.1 | L21: 1.2 | M21: 1.2 | N21: - | O21: ='Income Statement - AM'!EB63 -> 0 | P21: ='Income Statement - AM'!EC63 -> 0 | Q21: ='Income Statement - AM'!ED63 -> 0 | R21: ='Income Statement - AM'!EE63 -> 0 | S21: ='Income Statement - AM'!EF63 -> 0
B22: =B21+6 -> 60 | C22: - | D22: - | E22: - | F22: - | G22: - | I22: Projected DSCR | J22: 1.25 | K22: 1.25 | L22: 1.25 | M22: 1.25 | N22: 1.25 | O22: ='Income Statement - AM'!EB64 -> 0 | P22: ='Income Statement - AM'!EC64 -> 0 | Q22: ='Income Statement - AM'!ED64 -> 0 | R22: ='Income Statement - AM'!EE64 -> 0 | S22: ='Income Statement - AM'!EF64 -> 0
I23: Pass / Fail | J23: Pass | K23: Pass | L23: Pass | M23: Pass | N23: Pass
B24: NOI / Interest Rate Definitions
I25: DSCR Test
B26: Rent | I26: Debt Yield Test | J26: - | K26: - | L26: - | M26: - | N26: -
B27: Expenses | I27: Projected Debt Yield | J27: =J17/J12 -> 0.020901633 | K27: =K17/K12 -> 0.021377729 | L27: =L17/L12 -> 0.021886504 | M27: =M17/M12 -> 0.022429764 | N27: =N17/N12 -> 0.02300946
B28: NOI | I28: Pass / Fail | J28: Pass | K28: Pass | L28: Pass | M28: Pass | N28: Pass | O28: ='Income Statement - AM'!EB65 -> -33924.995 | P28: ='Income Statement - AM'!EC65 -> -33924.995 | Q28: ='Income Statement - AM'!ED65 -> -33924.995 | R28: ='Income Statement - AM'!EE65 -> -33924.995 | S28: ='Income Statement - AM'!EF65 -> -33924.995
B29: Management Fee | O29: =SUM(O16:O28) -> 3358574.6 | P29: =SUM(P16:P28) -> 3358574.6 | Q29: =SUM(Q16:Q28) -> 3358574.6 | R29: =SUM(R16:R28) -> 3358574.6 | S29: =SUM(S16:S28) -> 3358574.6
I30: LTV Test
B31: Debt Service Definition | I31: LTV Test | J31: - | K31: - | L31: 0.55 | M31: - | N31: -
I32: Minimum Value to Achieve Test | J32: - | K32: - | M32: - | N32: -
B33: Rate | I33: Projected LTV | J33: - | K33: - | L33: 0.5 | M33: - | N33: - | O33: ='Income Statement - AM'!EB67 -> 0 | P33: ='Income Statement - AM'!EC67 -> 0 | Q33: ='Income Statement - AM'!ED67 -> 0 | R33: ='Income Statement - AM'!EE67 -> 0 | S33: ='Income Statement - AM'!EF67 -> 0
B34: Test 1: | I34: Projected Value | O34: =O33+O29 -> 3358574.6 | P34: =P33+P29 -> 3358574.6 | Q34: =Q33+Q29 -> 3358574.6 | R34: =R33+R29 -> 3358574.6 | S34: =S33+S29 -> 3358574.6
B35: Test 2: | I35: Assumed Cap rate
B36: Test 3: | I36: Pass / Fail | J36: Pass | K36: Pass | L36: Pass | M36: Pass | N36: Pass
B37: Amortization
I43: Gross Potential Rent | J43: ='Income Statement - AM'!DW34 -> 2988933.6 | K43: ='Income Statement - AM'!DX34 -> 3057015.2 | L43: ='Income Statement - AM'!DY34 -> 3129770.1 | M43: ='Income Statement - AM'!DZ34 -> 3207456.2 | N43: ='Income Statement - AM'!EA34 -> 3290352.8
I44: Loss to Lease | J44: ='Income Statement - AM'!DW35 -> 0 | K44: ='Income Statement - AM'!DX35 -> 0 | L44: ='Income Statement - AM'!DY35 -> 0 | M44: ='Income Statement - AM'!DZ35 -> 0 | N44: ='Income Statement - AM'!EA35 -> 0 | O44: Unlevered Equity Multiple
O45: Levered IRR
I46: Other Income | J46: ='Income Statement - AM'!DW55 -> 146788.47 | K46: ='Income Statement - AM'!DX55 -> 151253.18 | L46: ='Income Statement - AM'!DY55 -> 155853.69 | M46: ='Income Statement - AM'!DZ55 -> 160594.13 | N46: ='Income Statement - AM'!EA55 -> 165478.76 | O46: Levered Equity Multiple
I47: Net Potential Income | J47: =J46+J17 -> 3135722 | K47: =K46+K17 -> 3208268.4 | L47: =L46+L17 -> 3285623.8 | M47: =M46+M17 -> 3368050.4 | N47: =N46+N17 -> 3455831.5 | O47: Net Profit (Levered CF)
I48: Vacancy | J48: ='Income Statement - AM'!DW59 -> -3135722 | K48: ='Income Statement - AM'!DX59 -> -1605490.3 | L48: ='Income Statement - AM'!DY59 -> -98568.714 | M48: ='Income Statement - AM'!DZ59 -> -101041.51 | N48: ='Income Statement - AM'!EA59 -> -103674.95
I49: Model Units | J49: ='Income Statement - AM'!DW60 -> 0 | K49: ='Income Statement - AM'!DX60 -> 0 | L49: ='Income Statement - AM'!DY60 -> 0 | M49: ='Income Statement - AM'!DZ60 -> 0 | N49: ='Income Statement - AM'!EA60 -> 0
I50: Concessions - Lease Up (New) | J50: ='Income Statement - AM'!DW61 -> 0 | K50: ='Income Statement - AM'!DX61 -> -231590.51 | L50: ='Income Statement - AM'!DY61 -> 0 | M50: ='Income Statement - AM'!DZ61 -> 0 | N50: ='Income Statement - AM'!EA61 -> 0
I51: Concessions - Lease Up (Renewal) | J51: ='Income Statement - AM'!DW62 -> 0 | K51: ='Income Statement - AM'!DX62 -> 0 | L51: ='Income Statement - AM'!DY62 -> 0 | M51: ='Income Statement - AM'!DZ62 -> 0 | N51: ='Income Statement - AM'!EA62 -> 0
I52: Concessions - Stabilized (New) | J52: ='Income Statement - AM'!DW63 -> 0 | K52: ='Income Statement - AM'!DX63 -> 0 | L52: ='Income Statement - AM'!DY63 -> 0 | M52: ='Income Statement - AM'!DZ63 -> 0 | N52: ='Income Statement - AM'!EA63 -> 0
I53: Concessions - Stabilized (Renewal) | J53: ='Income Statement - AM'!DW64 -> 0 | K53: ='Income Statement - AM'!DX64 -> 0 | L53: ='Income Statement - AM'!DY64 -> 0 | M53: ='Income Statement - AM'!DZ64 -> 0 | N53: ='Income Statement - AM'!EA64 -> 0
I54: Bad Debt | J54: ='Income Statement - AM'!DW65 -> 0 | K54: ='Income Statement - AM'!DX65 -> -13711.876 | L54: ='Income Statement - AM'!DY65 -> -31870.551 | M54: ='Income Statement - AM'!DZ65 -> -32670.089 | N54: ='Income Statement - AM'!EA65 -> -33521.566
I55: Effective Gross Income (Multi) | J55: =SUM(J47:J54) -> -4.6566129e-10 | K55: =SUM(K47:K54) -> 1357475.7 | L55: =SUM(L47:L54) -> 3155184.5 | M55: =SUM(M47:M54) -> 3234338.8 | N55: =SUM(N47:N54) -> 3318635
I56: Retail | J56: ='Income Statement - AM'!DW67 -> 0 | K56: ='Income Statement - AM'!DX67 -> 0 | L56: ='Income Statement - AM'!DY67 -> 0 | M56: ='Income Statement - AM'!DZ67 -> 0 | N56: ='Income Statement - AM'!EA67 -> 0
O63: Average Cash-on-Cash Return
O64: LP IRR
O65: LP MOIC
O66: GP IRR
O67: GP MOIC

Sheet Exit and Return Sensitivities
B2: ='Performance Dashboard'!B3 -> West Village Complexes - Multifamily - New York
B5: RETURN SENSITIVTY - EXIT CAP RATE VS. RENTS | J5: RETURN SENSITIVTY - EXIT CAP RATE VS. SALE MONTH
B7: Deal Level | D7: Exit Cap Rate | J7: Deal Level | L7: Exit Cap Rate
C8: =CONCATENATE(TEXT('AIRR Model Summary'!J69,"0.0%")," / ",TEXT('AIRR Model Summary'!J70,"0.00x")," / ",TEXT(#REF!,"$0,0")) -> #REF! | D8: =E8-0.0025 -> 0.045 | E8: =F8-0.0025 -> 0.0475 | F8: 0.05 | G8: =F8+0.0025 -> 0.0525 | H8: =G8+0.0025 -> 0.055 | K8: 20.0% / 1.41x / $454,545 | L8: =M8-0.0025 -> 0.045 | M8: =N8-0.0025 -> 0.0475 | N8: 0.05 | O8: =N8+0.0025 -> 0.0525 | P8: =O8+0.0025 -> 0.055
C9: =C10-100 -> 2300 | D9: 20.0% / 1.41x / $454,545 | E9: 20.0% / 1.41x / $454,545 | F9: 20.0% / 1.41x / $454,545 | G9: 20.0% / 1.41x / $454,545 | H9: 20.0% / 1.41x / $454,545 | K9: =K10-6 -> 36 | L9: 20.0% / 1.41x / $454,545 | M9: 20.0% / 1.41x / $454,545 | N9: 20.0% / 1.41x / $454,545 | O9: 20.0% / 1.41x / $454,545 | P9: 20.0% / 1.41x / $454,545
C10: =C11-100 -> 2400 | D10: 20.0% / 1.41x / $454,545 | E10: 20.0% / 1.41x / $454,545 | F10: 20.0% / 1.41x / $454,545 | G10: 20.0% / 1.41x / $454,545 | H10: 20.0% / 1.41x / $454,545 | J10: Sale Month | K10: =K11-6 -> 42 | L10: 20.0% / 1.41x / $454,545 | M10: 20.0% / 1.41x / $454,545 | N10: 20.0% / 1.41x / $454,545 | O10: 20.0% / 1.41x / $454,545 | P10: 20.0% / 1.41x / $454,545
B11: Rents | C11: 2500 | D11: 20.0% / 1.41x / $454,545 | E11: 20.0% / 1.41x / $454,545 | F11: 20.0% / 1.41x / $454,545 | G11: 20.0% / 1.41x / $454,545 | H11: 20.0% / 1.41x / $454,545 | K11: 48 | L11: 20.0% / 1.41x / $454,545 | M11: 20.0% / 1.41x / $454,545 | N11: 20.0% / 1.41x / $454,545 | O11: 20.0% / 1.41x / $454,545 | P11: 20.0% / 1.41x / $454,545
C12: =C11+1 -> 2501 | D12: 20.0% / 1.41x / $454,545 | E12: 20.0% / 1.41x / $454,545 | F12: 20.0% / 1.41x / $454,545 | G12: 20.0% / 1.41x / $454,545 | H12: 20.0% / 1.41x / $454,545 | K12: =K11+6 -> 54 | L12: 20.0% / 1.41x / $454,545 | M12: 20.0% / 1.41x / $454,545 | N12: 20.0% / 1.41x / $454,545 | O12: 20.0% / 1.41x / $454,545 | P12: 20.0% / 1.41x / $454,545
C13: =C12+1 -> 2502 | D13: 20.0% / 1.41x / $454,545 | E13: 20.0% / 1.41x / $454,545 | F13: 20.0% / 1.41x / $454,545 | G13: 20.0% / 1.41x / $454,545 | H13: 20.0% / 1.41x / $454,545 | K13: =K12+6 -> 60 | L13: 20.0% / 1.41x / $454,545 | M13: 20.0% / 1.41x / $454,545 | N13: 20.0% / 1.41x / $454,545 | O13: 20.0% / 1.41x / $454,545 | P13: 20.0% / 1.41x / $454,545
B15: LP | D15: Exit Cap Rate | J15: LP | L15: Exit Cap Rate
C16: =CONCATENATE(TEXT('AIRR Model Summary'!#REF!,"0.0%")," / ",TEXT('AIRR Model Summary'!#REF!,"0.00x")," / ",TEXT(#REF!,"$0,0")) -> #REF! | D16: =E16-0.0025 -> 0.045 | E16: =F16-0.0025 -> 0.0475 | F16: 0.05 | G16: =F16+0.0025 -> 0.0525 | H16: =G16+0.0025 -> 0.055 | K16: 20.0% / 1.41x / $454,545 | L16: =M16-0.0025 -> 0.045 | M16: =N16-0.0025 -> 0.0475 | N16: 0.05 | O16: =N16+0.0025 -> 0.0525 | P16: =O16+0.0025 -> 0.055
C17: =C18-100 -> 2300 | D17: 20.0% / 1.41x / $454,545 | E17: 20.0% / 1.41x / $454,545 | F17: 20.0% / 1.41x / $454,545 | G17: 20.0% / 1.41x / $454,545 | H17: 20.0% / 1.41x / $454,545 | K17: =K18-6 -> 36 | L17: 20.0% / 1.41x / $454,545 | M17: 20.0% / 1.41x / $454,545 | N17: 20.0% / 1.41x / $454,545 | O17: 20.0% / 1.41x / $454,545 | P17: 20.0% / 1.41x / $454,545
C18: =C19-100 -> 2400 | D18: 20.0% / 1.41x / $454,545 | E18: 20.0% / 1.41x / $454,545 | F18: 20.0% / 1.41x / $454,545 | G18: 20.0% / 1.41x / $454,545 | H18: 20.0% / 1.41x / $454,545 | J18: Sale Month | K18: =K19-6 -> 42 | L18: 20.0% / 1.41x / $454,545 | M18: 20.0% / 1.41x / $454,545 | N18: 20.0% / 1.41x / $454,545 | O18: 20.0% / 1.41x / $454,545 | P18: 20.0% / 1.41x / $454,545
B19: Rents | C19: 2500 | D19: 20.0% / 1.41x / $454,545 | E19: 20.0% / 1.41x / $454,545 | F19: 20.0% / 1.41x / $454,545 | G19: 20.0% / 1.41x / $454,545 | H19: 20.0% / 1.41x / $454,545 | K19: 48 | L19: 20.0% / 1.41x / $454,545 | M19: 20.0% / 1.41x / $454,545 | N19: 20.0% / 1.41x / $454,545 | O19: 20.0% / 1.41x / $454,545 | P19: 20.0% / 1.41x / $454,545
C20: =C19+1 -> 2501 | D20: 20.0% / 1.41x / $454,545 | E20: 20.0% / 1.41x / $454,545 | F20: 20.0% / 1.41x / $454,545 | G20: 20.0% / 1.41x / $454,545 | H20: 20.0% / 1.41x / $454,545 | K20: =K19+6 -> 54 | L20: 20.0% / 1.41x / $454,545 | M20: 20.0% / 1.41x / $454,545 | N20: 20.0% / 1.41x / $454,545 | O20: 20.0% / 1.41x / $454,545 | P20: 20.0% / 1.41x / $454,545
C21: =C20+1 -> 2502 | D21: 20.0% / 1.41x / $454,545 | E21: 20.0% / 1.41x / $454,545 | F21: 20.0% / 1.41x / $454,545 | G21: 20.0% / 1.41x / $454,545 | H21: 20.0% / 1.41x / $454,545 | K21: =K20+6 -> 60 | L21: 20.0% / 1.41x / $454,545 | M21: 20.0% / 1.41x / $454,545 | N21: 20.0% / 1.41x / $454,545 | O21: 20.0% / 1.41x / $454,545 | P21: 20.0% / 1.41x / $454,545
B23: GP | D23: Exit Cap Rate | J23: GP | L23: Exit Cap Rate
C24: =CONCATENATE(TEXT('AIRR Model Summary'!#REF!,"0.0%")," / ",TEXT('AIRR Model Summary'!#REF!,"0.00x")," / ",TEXT(#REF!,"$0,0")) -> #REF! | D24: =E24-0.0025 -> 0.045 | E24: =F24-0.0025 -> 0.0475 | F24: 0.05 | G24: =F24+0.0025 -> 0.0525 | H24: =G24+0.0025 -> 0.055 | K24: 20.0% / 1.41x / $454,545 | L24: =M24-0.0025 -> 0.045 | M24: =N24-0.0025 -> 0.0475 | N24: 0.05 | O24: =N24+0.0025 -> 0.0525 | P24: =O24+0.0025 -> 0.055
C25: =C26-100 -> 2300 | D25: 20.0% / 1.41x / $454,545 | E25: 20.0% / 1.41x / $454,545 | F25: 20.0% / 1.41x / $454,545 | G25: 20.0% / 1.41x / $454,545 | H25: 20.0% / 1.41x / $454,545 | K25: =K26-6 -> 36 | L25: 20.0% / 1.41x / $454,545 | M25: 20.0% / 1.41x / $454,545 | N25: 20.0% / 1.41x / $454,545 | O25: 20.0% / 1.41x / $454,545 | P25: 20.0% / 1.41x / $454,545
C26: =C27-100 -> 2400 | D26: 20.0% / 1.41x / $454,545 | E26: 20.0% / 1.41x / $454,545 | F26: 20.0% / 1.41x / $454,545 | G26: 20.0% / 1.41x / $454,545 | H26: 20.0% / 1.41x / $454,545 | J26: Sale Month | K26: =K27-6 -> 42 | L26: 20.0% / 1.41x / $454,545 | M26: 20.0% / 1.41x / $454,545 | N26: 20.0% / 1.41x / $454,545 | O26: 20.0% / 1.41x / $454,545 | P26: 20.0% / 1.41x / $454,545
B27: Rents | C27: 2500 | D27: 20.0% / 1.41x / $454,545 | E27: 20.0% / 1.41x / $454,545 | F27: 20.0% / 1.41x / $454,545 | G27: 20.0% / 1.41x / $454,545 | H27: 20.0% / 1.41x / $454,545 | K27: 48 | L27: 20.0% / 1.41x / $454,545 | M27: 20.0% / 1.41x / $454,545 | N27: 20.0% / 1.41x / $454,545 | O27: 20.0% / 1.41x / $454,545 | P27: 20.0% / 1.41x / $454,545
C28: =C27+1 -> 2501 | D28: 20.0% / 1.41x / $454,545 | E28: 20.0% / 1.41x / $454,545 | F28: 20.0% / 1.41x / $454,545 | G28: 20.0% / 1.41x / $454,545 | H28: 20.0% / 1.41x / $454,545 | K28: =K27+6 -> 54 | L28: 20.0% / 1.41x / $454,545 | M28: 20.0% / 1.41x / $454,545 | N28: 20.0% / 1.41x / $454,545 | O28: 20.0% / 1.41x / $454,545 | P28: 20.0% / 1.41x / $454,545
C29: =C28+1 -> 2502 | D29: 20.0% / 1.41x / $454,545 | E29: 20.0% / 1.41x / $454,545 | F29: 20.0% / 1.41x / $454,545 | G29: 20.0% / 1.41x / $454,545 | H29: 20.0% / 1.41x / $454,545 | K29: =K28+6 -> 60 | L29: 20.0% / 1.41x / $454,545 | M29: 20.0% / 1.41x / $454,545 | N29: 20.0% / 1.41x / $454,545 | O29: 20.0% / 1.41x / $454,545 | P29: 20.0% / 1.41x / $454,545

Sheet Summary Dashboards-->

Sheet UW VS. ASSET MANAGEMENT
B5: Sources and Uses | I5: Key Dates and Assumptions
J6: Underwriting | K6: Asset Management | L6: Variance
B7: Sources | C7: Closing Budget | D7: Post-Closing | E7: Current AM Model | F7: Variance | G7: Spent to Date | I7: Construction Start | J7: ='PERPETUITY MIDDLEMAN INPUT TAB'!C11 -> 45346
B8: Senior Debt | C8: 50000000 | E8: 50000000 | F8: 50000000 | G8: 50000000 | I8: First Unit Delivery | J8: ='PERPETUITY MIDDLEMAN INPUT TAB'!C16 -> 14
B9: Preferred Equity | C9: 50000000 | E9: 50000000 | F9: 50000000 | G9: 50000000 | I9: Last Unit Delivery | J9: ='PERPETUITY MIDDLEMAN INPUT TAB'!C18 -> 24
B10: LP Equity - JV | C10: 50000000 | E10: 50000000 | F10: 50000000 | G10: 50000000 | I10: First Unit Occupancy | J10: ='PERPETUITY MIDDLEMAN INPUT TAB'!#REF! -> #REF!
B11: GP Equity - JV | C11: 50000000 | E11: 50000000 | F11: 50000000 | G11: 50000000 | I11: Construction Completion | J11: ='PERPETUITY MIDDLEMAN INPUT TAB'!C14 -> 24
B12: LP Equity - Priority Capital | C12: 50000000 | E12: 50000000 | F12: 50000000 | G12: 50000000 | I12: Average Unit Absoprtion Per Month | J12: ='PERPETUITY MIDDLEMAN INPUT TAB'!C36 -> 25
B13: GP Equity - Priority Capital | C13: 50000000 | E13: 50000000 | F13: 50000000 | G13: 50000000
B14: Total Uses | C14: =SUM(C8:C13) -> 300000000 | D14: =SUM(D8:D13) -> 0 | E14: =SUM(E8:E13) -> 300000000 | F14: =SUM(F8:F13) -> 300000000 | G14: =SUM(G8:G13) -> 300000000 | I14: NOI Breakeven
I15: Senior Debt Service Breakeven
B16: Uses | C16: Closing Budget | D16: Post-Closing | E16: Current AM Model | F16: Variance | G16: Spent to Date
B17: Land Acquisition Costs | C17: 50000000 | E17: 50000000 | F17: 50000000 | G17: 50000000 | I17: Stabilization
B18: Closing Costs | C18: 50000000 | E18: 50000000 | F18: 50000000 | G18: 50000000 | I18: Sale Month
B19: Hard Costs | C19: 50000000 | E19: 50000000 | F19: 50000000 | G19: 50000000 | I19: Hold Period
B20: Soft Costs | C20: 50000000 | E20: 50000000 | F20: 50000000 | G20: 50000000
B21: Contingency | C21: 50000000 | E21: 50000000 | F21: 50000000 | G21: 50000000 | I21: Returns
B22: Financing Fees | C22: 50000000 | E22: 50000000 | F22: 50000000 | G22: 50000000 | J22: Underwriting | K22: Asset Management | L22: Variance
B23: Senior Interest Reserve | C23: 50000000 | E23: 50000000 | F23: 50000000 | G23: 50000000 | I23: Unlevered IRR
B24: Mezzanine Interest Reserve | C24: 50000000 | E24: 50000000 | F24: 50000000 | G24: 50000000 | I24: Unlevered Equity Multiple
B25: Operating Reserve | C25: 50000000 | E25: 50000000 | F25: 50000000 | G25: 50000000 | I25: Levered IRR
B26: Total Uses | C26: =SUM(C17:C25) -> 450000000 | D26: =SUM(D17:D25) -> 0 | E26: =SUM(E17:E25) -> 450000000 | F26: =SUM(F17:F25) -> 450000000 | G26: =SUM(G17:G25) -> 450000000 | I26: Levered Equity Multiple
I27: Net Profit (Levered CF)
B28: Rent Comparison | I28: Average Cash-on-Cash Return
B29: Month 48 | I29: LP IRR
B30: Face Rents | I30: LP MOIC
B31: Unit Type | C31: # of Units | D31: SF | E31: Trended UW Rent | F31: AM Model | G31: Variance | I31: GP IRR
B32: Studio | C32: 50 | D32: 600 | E32: 1425 | F32: 1425 | G32: =E32-F32 -> 0 | I32: GP MOIC
B33: 1BR/1BA | C33: 50 | D33: 600 | E33: 1425 | F33: 1425 | G33: =E33-F33 -> 0
B34: 2BR/1BA | C34: 20 | D34: 725 | E34: 1600 | F34: 1600 | G34: =E34-F34 -> 0 | I34: Sale
B35: 2BR/2BA | C35: 65 | D35: 875 | E35: 1875 | F35: 1875 | G35: =E35-F35 -> 0 | J35: Underwriting | K35: Asset Management | L35: Variance
B36: 3BR/2BA | C36: 10 | D36: 1025 | E36: 2100 | F36: 2100 | G36: =E36-F36 -> 0 | I36: Sale Month
B37: Total / Average | C37: =SUM(C32:C36) -> 195 | D37: =SUMPRODUCT(C32:C36,D32:D36)/C37 -> 726.28205 | E37: =SUMPRODUCT(C32:C36,E32:E36)/C37 -> 1627.5641 | F37: =SUMPRODUCT(C32:C36,F32:F36)/C37 -> 1627.5641 | G37: =SUMPRODUCT(C32:C36,G32:G36)/C37 -> 0 | I37: Sale Date
I38: NOI at Exit
I39: Exit Cap Rate
B40: Effective Rents
B41: Unit Type | C41: # of Units | D41: SF | E41: Trended UW Rent | F41: AM Model | G41: Variance | I41: Gross Sale Price
B42: Studio | C42: 50 | D42: 600 | E42: 1425 | F42: 1425 | G42: =E42-F42 -> 0 | I42: Gross Sale Price / Unit
B43: 1BR/1BA | C43: 50 | D43: 600 | E43: 1425 | F43: 1425 | G43: =E43-F43 -> 0 | I43: Cost of Sale
B44: 2BR/1BA | C44: 20 | D44: 725 | E44: 1600 | F44: 1600 | G44: =E44-F44 -> 0 | I44: Net Sale Proceeds
B45: 2BR/2BA | C45: 65 | D45: 875 | E45: 1875 | F45: 1875 | G45: =E45-F45 -> 0
B46: 3BR/2BA | C46: 10 | D46: 1025 | E46: 2100 | F46: 2100 | G46: =E46-F46 -> 0 | I46: NOI Comparison
B47: Total / Average | C47: =SUM(C42:C46) -> 195 | D47: =SUMPRODUCT(C42:C46,D42:D46)/C47 -> 726.28205 | E47: =SUMPRODUCT(C42:C46,E42:E46)/C47 -> 1627.5641 | F47: =SUMPRODUCT(C42:C46,F42:F46)/C47 -> 1627.5641 | G47: =SUMPRODUCT(C42:C46,G42:G46)/C47 -> 0 | I47: Sale | J47: Underwriting | K47: Asset Management | L47: Variance
I48: Occupancy
I49: In-Place Rents
I51: Revenue
I52: Gross Potential Rent
I53: Loss to Lease
I54: Net Potential Rent
I55: Other Income
I56: Net Potential Income
I57: Vacancy
I58: Concessions (Lease-Up)
I59: Concessions (Stabilized)
I60: Bad Debt
... I82: Net Operating Margin

Sheet COLOR CODING LEGEND
B2: Information Source Guide
B3: Color coding below corresponds to cells on the inputs tabs
B4: 1 | C4: Joint Venture Agreement
B5: =B4+1 -> 2 | C5: Loan Document
B6: =B5+1 -> 3 | C6: Underwriting Model
B7: =B6+1 -> 4 | C7: Rent Roll
B8: =B7+1 -> 5 | C8: Monthly Financials
B9: =B8+1 -> 6 | C9: Investment Committee Memo / Offering Memorandum
B10: =B9+1 -> 7 | C10: Draft Client Intake Form - Manual spreadsheet filled out by clients outlining key details on all deals / users. User profile creation and deal information intake will be driven by the inputs of this form.
B11: =B10+1 -> 8 | C11: Human Entry - From Analyst

Sheet Sample RR
AI1: Other
A2: Unit | C2: Floorplan | F2: unit designation | I2: SQFT | K2: Unit/Lease Status | M2: Name | Q2: Move-In Move-Out | T2: Lease Start | V2: Lease End | Y2: Market + Addl. | AA2: Sub Trans Journal Code | AF2: Lease Charges/ Total Dep balance Rent Credits Billing On Hand
A4: 111A | C4: 4x4 | F4: N/A | I4: 325 | K4: Occupied | M4: Coutee, Gabriel | Q4: 44776 | T4: 44776 | V4: 45138 | Y4: 564 | AA4: RESIDENT CONC-RECURRIN | AF4: 0 | AH4: -45 | AK4: 514 | AN4: 0 | AQ4: 1736.93
AA5: RESIDENT RENT | AF5: 544 | AH5: 0
AA6: RESIDENT RENTERS INS | AF6: 0 | AH6: 15
A7: 111B | C7: 4x4 | F7: N/A | I7: 325 | K7: Occupied | M7: Brown, Ceasar | Q7: 44775 | T7: 44775 | V7: 45138 | Y7: 564 | AA7: RESIDENT CONC-RECURRIN | AF7: 0 | AH7: -10 | AK7: 509 | AN7: 0 | AQ7: 9
AA8: RESIDENT RENT | AF8: 519 | AH8: 0
A9: 111C | C9: 4x4 | F9: N/A | I9: 325 | K9: Occupied | M9: Walker, Taliayah | Q9: 44775 | T9: 44775 | V9: 45138 | Y9: 564 | AA9: RESIDENT CONC-RECURRIN | AF9: 0 | AH9: -35 | AK9: 499 | AN9: 0 | AQ9: 803.78
AA10: RESIDENT RENT | AF10: 534 | AH10: 0
A11: 111D | C11: 4x4 | F11: N/A | I11: 325 | K11: Occupied | M11: Jones, Travonn | Q11: 44783 | T11: 44783 | V11: 45138 | Y11: 564 | AA11: RESIDENT CONC-RECURRIN | AF11: 0 | AH11: -45 | AK11: 514 | AN11: 0 | AQ11: 0
AA12: RESIDENT RENT | AF12: 544 | AH12: 0
AA13: RESIDENT RENTERS INS | AF13: 0 | AH13: 15
A14: 112A | C14: 4x4 | F14: N/A | I14: 325 | K14: Occupied | M14: Smith, Tyeryka | Q14: 44776 | T14: 44776 | V14: 45138 | Y14: 564 | AA14: RESIDENT CONC-RECURRIN | AF14: 0 | AH14: -45 | AK14: 514 | AN14: 0 | AQ14: 169.83
AA15: RESIDENT RENT | AF15: 544 | AH15: 0
AA16: RESIDENT RENTERS INS | AF16: 0 | AH16: 15
A17: 112B | C17: 4x4 | F17: N/A | I17: 325 | K17: Occupied | M17: Brown, ShaRron | Q17: 44763 | T17: 44774 | V17: 45138 | Y17: 564 | AA17: RESIDENT CONC-RECURRIN | AF17: 0 | AH17: -50 | AK17: 514 | AN17: 0 | AQ17: 184.26
AA18: RESIDENT RENT | AF18: 549 | AH18: 0
AA19: RESIDENT RENTERS INS | AF19: 0 | AH19: 15
A20: 112C | C20: 4x4 | F20: N/A | I20: 325 | K20: Occupied | M20: Carter, Kyla | Q20: 44805 | T20: 44805 | V20: 45138 | Y20: 564 | AA20: RESIDENT CONC-RECURRIN | AF20: 0 | AH20: -50 | AK20: 499 | AN20: 0 | AQ20: 124.13
AA21: RESIDENT RENT | AF21: 549 | AH21: 0
A22: 112D | C22: 4x4 | F22: N/A | I22: 325 | K22: Occupied | M22: Norton, Daysia | Q22: 44866 | T22: 44866 | V22: 45138 | Y22: 564 | AA22: RESIDENT CONC-RECURRIN | AF22: 0 | AH22: -35 | AK22: 514 | AN22: 0 | AQ22: 62
AA23: RESIDENT RENT | AF23: 534 | AH23: 0
AA24: RESIDENT RENTERS INS | AF24: 0 | AH24: 15
A25: 113A | C25: 4x4 | F25: N/A | I25: 325 | K25: Vacant | M25: VACANT | Y25: 564 | AF25: 0 | AH25: 0
A26: 113B | C26: 4x4 | F26: N/A | I26: 325 | K26: Vacant | M26: VACANT | Y26: 564 | AF26: 0 | AH26: 0
A27: 113C | C27: 4x4 | F27: N/A | I27: 325 | K27: Occupied | M27: Gibson $, Raykivus | Q27: 44569 | T27: 44774 | V27: 45138 | Y27: 564 | AA27: RESIDENT CONC-RECURRIN | AF27: 0 | AH27: -35 | AK27: 514 | AN27: 0 | AQ27: 647.18
AA28: RESIDENT RENT | AF28: 534 | AH28: 0
AA29: RESIDENT RENTERS INS | AF29: 0 | AH29: 15
A30: 113D | C30: 4x4 | F30: N/A | I30: 325 | K30: Occupied | M30: Caldwell, Ronald | Q30: 44635 | T30: 44774 | V30: 45138 | Y30: 564 | AA30: RESIDENT CONC-RECURRIN | AF30: 0 | AH30: -45 | AK30: 295 | AN30: 0 | AQ30: -396.5
AA31: RESIDENT EMETSCHOLAR | AF31: 0 | AH31: -249
AA32: RESIDENT PET RENT | AF32: 0 | AH32: 30
AI33: Other
A34: Unit | C34: Floorplan | F34: unit designation | I34: SQFT | K34: Unit/Lease Status | M34: Name | Q34: Move-In Move-Out | T34: Lease Start | V34: Lease End | Y34: Market + Addl. | AA34: Sub Trans Journal Code | AF34: Lease Charges/ Total Dep balance Rent Credits Billing On Hand
AA36: RESIDENT RENT | AF36: 544 | AH36: 0
AA37: RESIDENT RENTERS INS | AF37: 0 | AH37: 15
A38: 114A | C38: 4x4 | F38: N/A | I38: 325 | K38: Occupied | M38: Thomas, Christian | Q38: 44776 | T38: 44776 | V38: 45138 | Y38: 564 | AA38: RESIDENT CONC-RECURRIN | AF38: 0 | AH38: -45 | AK38: 514 | AN38: 0 | AQ38: 1954
AA39: RESIDENT RENT | AF39: 544 | AH39: 0
AA40: RESIDENT RENTERS INS | AF40: 0 | AH40: 15
A41: 114B | C41: 4x4 | F41: N/A | I41: 325 | K41: Occupied | M41: Fegans $, Antwon | Q41: 44805 | T41: 44805 | V41: 45138 | Y41: 564 | AA41: RESIDENT CONC-RECURRIN | AF41: 0 | AH41: -45 | AK41: 514 | AN41: 0 | AQ41: 154.5
AA42: RESIDENT RENT | AF42: 544 | AH42: 0
AA43: RESIDENT RENTERS INS | AF43: 0 | AH43: 15
A44: 114C | C44: 4x4 | F44: N/A | I44: 325 | K44: Vacant | M44: VACANT | Y44: 564 | AF44: 0 | AH44: 0
A45: 114D | C45: 4x4 | F45: N/A | I45: 325 | K45: Vacant | M45: VACANT | Y45: 564 | AF45: 0 | AH45: 0
A46: 121A | C46: 4x4 | F46: N/A | I46: 325 | K46: Occupied | M46: McGuire, Chanquavion | Q46: 44799 | T46: 44799 | V46: 45138 | Y46: 564 | AA46: RESIDENT CONC-RECURRIN | AF46: 0 | AH46: -45 | AK46: 514 | AN46: 0 | AQ46: 180.61
AA47: RESIDENT RENT | AF47: 544 | AH47: 0
AA48: RESIDENT RENTERS INS | AF48: 0 | AH48: 15
A49: 121B | C49: 4x4 | F49: N/A | I49: 325 | K49: Occupied | M49: Webb, Dagan | Q49: 44452 | T49: 44774 | V49: 45138 | Y49: 564 | AA49: RESIDENT CONC-RECURRIN | AF49: 0 | AH49: -45 | AK49: 265 | AN49: 0 | AQ49: 0
